Workbook
Name __DAT1: #REF!
Name __DAT1: #REF!
Name __DAT1: #REF!
Name __DAT10: #REF!
Name __DAT10: #REF!
Name __DAT10: #REF!
Name __DAT11: #REF!
Name __DAT11: #REF!
Name __DAT11: #REF!
Name __DAT12: #REF!
Name __DAT12: #REF!
Name __DAT12: #REF!
Name __DAT13: #REF!
Name __DAT13: #REF!
Name __DAT13: #REF!
Name __DAT14: #REF!
Name __DAT14: #REF!
Name __DAT14: #REF!
Name __DAT15: #REF!
Name __DAT15: #REF!
Name __DAT15: #REF!
Name __DAT16: #REF!
Name __DAT16: #REF!
Name __DAT16: #REF!
Name __DAT17: #REF!
Name __DAT17: #REF!
Name __DAT17: #REF!
Name __DAT18: #REF!
Name __DAT18: #REF!
Name __DAT18: #REF!
Name __DAT19: #REF!
Name __DAT19: #REF!
Name __DAT19: #REF!
Name __DAT2: #REF!
Name __DAT2: #REF!
Name __DAT2: #REF!
Name __DAT20: #REF!
Name __DAT20: #REF!
Name __DAT20: #REF!
Name __DAT21: #REF!
Name __DAT21: #REF!
Name __DAT21: #REF!
Name __DAT3: #REF!
Name __DAT3: #REF!
Name __DAT3: #REF!
Name __DAT4: #REF!
Name __DAT4: #REF!
Name __DAT4: #REF!
Name __DAT5: #REF!
Name __DAT5: #REF!
Name __DAT5: #REF!
Name __DAT6: #REF!
Name __DAT6: #REF!
Name __DAT6: #REF!
Name __DAT7: #REF!
Name __DAT7: #REF!
Name __DAT7: #REF!
Name __DAT8: #REF!
Name __DAT8: #REF!
Name __DAT8: #REF!

Sheet MATRIZ
B2: MATRIZ DE PRIORIDADE
G3: =IFERROR(VLOOKUP(C3,#REF!,4,FALSE),"") | H3: =VLOOKUP(C3,Dados!B:AW,10,0) -> #N/A | I3: =(VLOOKUP(C3,Dados!B:AW,47,0)) -> #N/A | K3: =IFERROR((VLOOKUP(C3,Dados!B:AW,43,0)),0) -> 0 | L3: =IFERROR((VLOOKUP(C3,Dados!B:AW,44,0)),0) -> 0 | M3: =IFERROR((VLOOKUP(C3,Dados!B:AW,42,0)),0) -> 0 | N3: =IFERROR((VLOOKUP(C3,Dados!B:AW,46,0)),0) -> 0 | O3: =IF(AND(J3="Parcial",N3>0,H3>1),-1,IF(AND(J3="Parcial",N3>0,H3<1.1),1,IF(AND(J3="Parcial",N3<0,H3>1.09),-1,IF(J3="Total",-1,IF(H3>1.09,1,2))))) -> #N/A
B4: ID | C4: TAG | D4: Mini Fábrica | E4: Célula | F4: Denominação | I4: Obsolescência | K4: Custos Projetados | L4: (7 anos) | N4: LCC | AB4: -1 | AC4: =COUNTIF($AC$7:$AC$540,$AB4) -> 132 | AD4: =COUNTIF($AD$7:$AD$540,$AB4) -> 127 | AE4: =COUNTIF($AE$7:$AE$540,$AB4) -> 127
G5: β (2022) | H5: β (atual) | I5: Comportamento das Falhas | J5: Situação | K5: Atual | L5: Novo | M5: Potencial Ganho (7 Anos) | N5: ROI | O5: Farol | T5: Priorizar | V5: RISK MANAGEMENT | AB5: 1 | AC5: =COUNTIF($AC$7:$AC$540,$AB5) -> 2 | AD5: =COUNTIF($AD$7:$AD$540,$AB5) -> 2 | AE5: =COUNTIF($AE$7:$AE$540,$AB5) -> 162 | AH5: MOD012 | AI5: =CONCATENATE(AH5,"*") -> MOD012*
B6: 293 | C6: EMP123 | D6: UMO | E6: - | F6: EMP123-EMPILHADEIRA HIDRÁULICA MANUAL | G6: =IFERROR(VLOOKUP(C6,#REF!,4,FALSE),"") | H6: =VLOOKUP(C6,Dados!B:AW,11,0) -> 0 | I6: =(VLOOKUP(C6,Dados!B:AW,48,0)) -> Confiabilidade em Crescimento | J6: Em análise | K6: =IFERROR((VLOOKUP(C6,Dados!B:AW,44,0)),0) -> 0 | L6: =IFERROR((VLOOKUP(C6,Dados!B:AW,45,0)),0) -> 0 | M6: =IFERROR((VLOOKUP(C6,Dados!B:AW,43,0)),0) -> 0 | N6: =IFERROR((VLOOKUP(C6,Dados!B:AW,47,0)),0) -> 0 | O6: =IF(AND(J6="Parcial",N6>0,H6>1),-1,IF(AND(J6="Parcial",N6>0,H6<1.1),1,IF(AND(J6="Parcial",N6<0,H6>1.09),-1,IF(J6="Total",-1,IF(H6>1.09,1,2))))) -> 2 | P6: =IF(G6="",0,IF(H6>G6,-1,1)) -> 0 | S6: -1 | T6: Substituir | AB6: 2 | AC6: =COUNTIF($AC$7:$AC$540,$AB6) -> 399 | AD6: =COUNTIF($AD$7:$AD$540,$AB6) -> 404 | AE6: =COUNTIF($AE$7:$AE$540,$AB6) -> 244 | AH6: ROB040 | AI6: =CONCATENATE(AH6,"*") -> ROB040*
B7: 328 | C7: FOR083 | D7: ZCP | E7: - | F7: FOR083-FORNO CONTÍNUO | G7: =IFERROR(VLOOKUP(C7,#REF!,4,FALSE),"") | H7: =VLOOKUP(C7,Dados!B:AW,11,0) -> 0.77 | I7: =(VLOOKUP(C7,Dados!B:AW,48,0)) -> Confiabilidade em Crescimento | J7: Em análise | K7: =IFERROR((VLOOKUP(C7,Dados!B:AW,44,0)),0) -> 0 | L7: =IFERROR((VLOOKUP(C7,Dados!B:AW,45,0)),0) -> 0 | M7: =IFERROR((VLOOKUP(C7,Dados!B:AW,43,0)),0) -> 0 | N7: =IFERROR((VLOOKUP(C7,Dados!B:AW,47,0)),0) -> 0 | O7: =IF(AND(J7="Parcial",N7>0,H7>1),-1,IF(AND(J7="Parcial",N7>0,H7<1.1),1,IF(AND(J7="Parcial",N7<0,H7>1.09),-1,IF(J7="Total",-1,IF(H7>1.09,1,2))))) -> 2 | P7: =IF(G7="",0,IF(H7>G7,-1,1)) -> 0 | S7: 1 | T7: Acompanhar | AC7: -1 | AD7: -1 | AE7: -1 | AH7: ROB038 | AI7: =CONCATENATE(AH7,"*") -> ROB038*
B8: 17 | C8: BRU024 | D8: ZCP | E8: BRUC01 | F8: BRU024-BRUNIDORA | G8: =IFERROR(VLOOKUP(C8,#REF!,4,FALSE),"") | H8: =VLOOKUP(C8,Dados!B:AW,11,0) -> 1.64 | I8: =(VLOOKUP(C8,Dados!B:AW,48,0)) -> Fase de Degradação | J8: Total | K8: =IFERROR((VLOOKUP(C8,Dados!B:AW,44,0)),0) -> 0 | L8: =IFERROR((VLOOKUP(C8,Dados!B:AW,45,0)),0) -> 0 | M8: =IFERROR((VLOOKUP(C8,Dados!B:AW,43,0)),0) -> 0 | N8: =IFERROR((VLOOKUP(C8,Dados!B:AW,47,0)),0) -> 0 | O8: =IF(AND(J8="Parcial",N8>0,H8>1),-1,IF(AND(J8="Parcial",N8>0,H8<1.1),1,IF(AND(J8="Parcial",N8<0,H8>1.09),-1,IF(J8="Total",-1,IF(H8>1.09,1,2))))) -> -1 | P8: =IF(G8="",0,IF(H8>G8,-1,1)) -> 0 | S8: 2 | T8: Manter | AC8: 2 | AD8: 2 | AE8: 2 | AH8: PON008 | AI8: =CONCATENATE(AH8,"*") -> PON008*
B9: 19 | C9: BRU026 | D9: ZCP | E9: BRUC01 | F9: BRU026-BRUNIDORA | G9: =IFERROR(VLOOKUP(C9,#REF!,4,FALSE),"") | H9: =VLOOKUP(C9,Dados!B:AW,11,0) -> 1.19 | I9: =(VLOOKUP(C9,Dados!B:AW,48,0)) -> Fase de Degradação | J9: Total | K9: =IFERROR((VLOOKUP(C9,Dados!B:AW,44,0)),0) -> 0 | L9: =IFERROR((VLOOKUP(C9,Dados!B:AW,45,0)),0) -> 0 | M9: =IFERROR((VLOOKUP(C9,Dados!B:AW,43,0)),0) -> 0 | N9: =IFERROR((VLOOKUP(C9,Dados!B:AW,47,0)),0) -> 0 | O9: =IF(AND(J9="Parcial",N9>0,H9>1),-1,IF(AND(J9="Parcial",N9>0,H9<1.1),1,IF(AND(J9="Parcial",N9<0,H9>1.09),-1,IF(J9="Total",-1,IF(H9>1.09,1,2))))) -> -1 | P9: =IF(G9="",0,IF(H9>G9,-1,1)) -> 0 | AC9: 2 | AD9: 2 | AE9: 1 | AH9: GRV012 | AI9: =CONCATENATE(AH9,"*") -> GRV012*
B10: 11 | C10: BRU008 | D10: ZCP | E10: BRUC02 | F10: =VLOOKUP(C10,[9]Dados!B:C,2,0) -> BRU008-BRUNIDORA | G10: =IFERROR(VLOOKUP(C10,#REF!,4,FALSE),"") | H10: =VLOOKUP(C10,Dados!B:AW,11,0) -> 0.95 | I10: =(VLOOKUP(C10,Dados!B:AW,48,0)) -> Confiabilidade em Crescimento | J10: Não há | K10: =IFERROR((VLOOKUP(C10,Dados!B:AW,44,0)),0) -> 0 | L10: =IFERROR((VLOOKUP(C10,Dados!B:AW,45,0)),0) -> 0 | M10: =IFERROR((VLOOKUP(C10,Dados!B:AW,43,0)),0) -> 0 | N10: =IFERROR((VLOOKUP(C10,Dados!B:AW,47,0)),0) -> 0 | O10: =IF(AND(J10="Parcial",N10>0,H10>1),-1,IF(AND(J10="Parcial",N10>0,H10<1.1),1,IF(AND(J10="Parcial",N10<0,H10>1.09),-1,IF(J10="Total",-1,IF(H10>1.09,1,2))))) -> 2 | P10: =IF(G10="",0,IF(H10>G10,-1,1)) -> 0 | AC10: 2 | AD10: 2 | AE10: 1 | AH10: ROB007 | AI10: =CONCATENATE(AH10,"*") -> ROB007*
B11: 65 | C11: BRU072 | D11: ZCP | E11: BRUC02 | F11: BRU072-BRUNIDORA | G11: =IFERROR(VLOOKUP(C11,#REF!,4,FALSE),"") | H11: =VLOOKUP(C11,Dados!B:AW,11,0) -> 0.99 | I11: =(VLOOKUP(C11,Dados!B:AW,48,0)) -> Confiabilidade em Crescimento | K11: =IFERROR((VLOOKUP(C11,Dados!B:AW,44,0)),0) -> 0 | L11: =IFERROR((VLOOKUP(C11,Dados!B:AW,45,0)),0) -> 0 | M11: =IFERROR((VLOOKUP(C11,Dados!B:AW,43,0)),0) -> 0 | N11: =IFERROR((VLOOKUP(C11,Dados!B:AW,47,0)),0) -> 0 | O11: =IF(AND(J11="Parcial",N11>0,H11>1),-1,IF(AND(J11="Parcial",N11>0,H11<1.1),1,IF(AND(J11="Parcial",N11<0,H11>1.09),-1,IF(J11="Total",-1,IF(H11>1.09,1,2))))) -> 2 | P11: =IF(G11="",0,IF(H11>G11,-1,1)) -> 0 | AC11: 2 | AD11: 2 | AE11: 2 | AH11: EST127 | AI11: =CONCATENATE(AH11,"*") -> EST127*
B12: 16 | C12: BRU014 | D12: ZCP | E12: BRUC04 | F12: =VLOOKUP(C12,[9]Dados!B:C,2,0) -> BRU014-BRUNIDORA | G12: =IFERROR(VLOOKUP(C12,#REF!,4,FALSE),"") | H12: =VLOOKUP(C12,Dados!B:AW,11,0) -> 1.39 | I12: =(VLOOKUP(C12,Dados!B:AW,48,0)) -> Fase de Degradação | J12: Não há | K12: =IFERROR((VLOOKUP(C12,Dados!B:AW,44,0)),0) -> 0 | L12: =IFERROR((VLOOKUP(C12,Dados!B:AW,45,0)),0) -> 0 | M12: =IFERROR((VLOOKUP(C12,Dados!B:AW,43,0)),0) -> 0 | N12: =IFERROR((VLOOKUP(C12,Dados!B:AW,47,0)),0) -> 0 | O12: =IF(AND(J12="Parcial",N12>0,H12>1),-1,IF(AND(J12="Parcial",N12>0,H12<1.1),1,IF(AND(J12="Parcial",N12<0,H12>1.09),-1,IF(J12="Total",-1,IF(H12>1.09,1,2))))) -> 1 | P12: =IF(G12="",0,IF(H12>G12,-1,1)) -> 0 | AC12: 2 | AD12: 2 | AE12: 2 | AH12: TAN042 | AI12: =CONCATENATE(AH12,"*") -> TAN042*
B13: 55 | C13: BRU062 | D13: ZCP | E13: BRUC04 | F13: BRU062-BRUNIDORA | G13: =IFERROR(VLOOKUP(C13,#REF!,4,FALSE),"") | H13: =VLOOKUP(C13,Dados!B:AW,11,0) -> 1.2 | I13: =(VLOOKUP(C13,Dados!B:AW,48,0)) -> Fase de Degradação | K13: =IFERROR((VLOOKUP(C13,Dados!B:AW,44,0)),0) -> 0 | L13: =IFERROR((VLOOKUP(C13,Dados!B:AW,45,0)),0) -> 0 | M13: =IFERROR((VLOOKUP(C13,Dados!B:AW,43,0)),0) -> 0 | N13: =IFERROR((VLOOKUP(C13,Dados!B:AW,47,0)),0) -> 0 | O13: =IF(AND(J13="Parcial",N13>0,H13>1),-1,IF(AND(J13="Parcial",N13>0,H13<1.1),1,IF(AND(J13="Parcial",N13<0,H13>1.09),-1,IF(J13="Total",-1,IF(H13>1.09,1,2))))) -> 1 | P13: =IF(G13="",0,IF(H13>G13,-1,1)) -> 0 | AC13: -1 | AD13: -1 | AE13: -1 | AH13: BRU037 | AI13: =CONCATENATE(AH13,"*") -> BRU037*
B14: 15 | C14: BRU012 | D14: ZCP | E14: BRUC05 | F14: =VLOOKUP(C14,[9]Dados!B:C,2,0) -> BRU012-BRUNIDORA | G14: =IFERROR(VLOOKUP(C14,#REF!,4,FALSE),"") | H14: =VLOOKUP(C14,Dados!B:AW,11,0) -> 1.36 | I14: =(VLOOKUP(C14,Dados!B:AW,48,0)) -> Fase de Degradação | J14: Não há | K14: =IFERROR((VLOOKUP(C14,Dados!B:AW,44,0)),0) -> 0 | L14: =IFERROR((VLOOKUP(C14,Dados!B:AW,45,0)),0) -> 0 | M14: =IFERROR((VLOOKUP(C14,Dados!B:AW,43,0)),0) -> 0 | N14: =IFERROR((VLOOKUP(C14,Dados!B:AW,47,0)),0) -> 0 | O14: =IF(AND(J14="Parcial",N14>0,H14>1),-1,IF(AND(J14="Parcial",N14>0,H14<1.1),1,IF(AND(J14="Parcial",N14<0,H14>1.09),-1,IF(J14="Total",-1,IF(H14>1.09,1,2))))) -> 1 | P14: =IF(G14="",0,IF(H14>G14,-1,1)) -> 0 | AC14: -1 | AD14: -1 | AE14: -1 | AH14: BRU039 | AI14: =CONCATENATE(AH14,"*") -> BRU039*
B15: 18 | C15: BRU025 | D15: ZCP | E15: BRUC05 | F15: =VLOOKUP(C15,[9]Dados!B:C,2,0) -> BRU025-BRUNIDORA | G15: =IFERROR(VLOOKUP(C15,#REF!,4,FALSE),"") | H15: =VLOOKUP(C15,Dados!B:AW,11,0) -> 0.93 | I15: =(VLOOKUP(C15,Dados!B:AW,48,0)) -> Confiabilidade em Crescimento | J15: Não há | K15: =IFERROR((VLOOKUP(C15,Dados!B:AW,44,0)),0) -> 0 | L15: =IFERROR((VLOOKUP(C15,Dados!B:AW,45,0)),0) -> 0 | M15: =IFERROR((VLOOKUP(C15,Dados!B:AW,43,0)),0) -> 0 | N15: =IFERROR((VLOOKUP(C15,Dados!B:AW,47,0)),0) -> 0 | O15: =IF(AND(J15="Parcial",N15>0,H15>1),-1,IF(AND(J15="Parcial",N15>0,H15<1.1),1,IF(AND(J15="Parcial",N15<0,H15>1.09),-1,IF(J15="Total",-1,IF(H15>1.09,1,2))))) -> 2 | P15: =IF(G15="",0,IF(H15>G15,-1,1)) -> 0 | AC15: -1 | AD15: -1 | AE15: -1 | AH15: ROB066 | AI15: =CONCATENATE(AH15,"*") -> ROB066*
B16: 52 | C16: BRU059 | D16: ZCP | E16: BRUC05 | F16: BRU059-BRUNIDORA | G16: =IFERROR(VLOOKUP(C16,#REF!,4,FALSE),"") | H16: =VLOOKUP(C16,Dados!B:AW,11,0) -> 0.48 | I16: =(VLOOKUP(C16,Dados!B:AW,48,0)) -> Confiabilidade em Crescimento | K16: =IFERROR((VLOOKUP(C16,Dados!B:AW,44,0)),0) -> 0 | L16: =IFERROR((VLOOKUP(C16,Dados!B:AW,45,0)),0) -> 0 | M16: =IFERROR((VLOOKUP(C16,Dados!B:AW,43,0)),0) -> 0 | N16: =IFERROR((VLOOKUP(C16,Dados!B:AW,47,0)),0) -> 0 | O16: =IF(AND(J16="Parcial",N16>0,H16>1),-1,IF(AND(J16="Parcial",N16>0,H16<1.1),1,IF(AND(J16="Parcial",N16<0,H16>1.09),-1,IF(J16="Total",-1,IF(H16>1.09,1,2))))) -> 2 | P16: =IF(G16="",0,IF(H16>G16,-1,1)) -> 0 | AC16: 2 | AD16: 2 | AE16: 2 | AH16: ROB042 | AI16: =CONCATENATE(AH16,"*") -> ROB042*
B17: 26 | C17: BRU033 | D17: ZCP | E17: BRUC06 | F17: =VLOOKUP(C17,[9]Dados!B:C,2,0) -> BRU033-BRUNIDORA | G17: =IFERROR(VLOOKUP(C17,#REF!,4,FALSE),"") | H17: =VLOOKUP(C17,Dados!B:AW,11,0) -> 1.26 | I17: =(VLOOKUP(C17,Dados!B:AW,48,0)) -> Fase de Degradação | J17: Não há | K17: =IFERROR((VLOOKUP(C17,Dados!B:AW,44,0)),0) -> 0 | L17: =IFERROR((VLOOKUP(C17,Dados!B:AW,45,0)),0) -> 0 | M17: =IFERROR((VLOOKUP(C17,Dados!B:AW,43,0)),0) -> 0 | N17: =IFERROR((VLOOKUP(C17,Dados!B:AW,47,0)),0) -> 0 | O17: =IF(AND(J17="Parcial",N17>0,H17>1),-1,IF(AND(J17="Parcial",N17>0,H17<1.1),1,IF(AND(J17="Parcial",N17<0,H17>1.09),-1,IF(J17="Total",-1,IF(H17>1.09,1,2))))) -> 1 | P17: =IF(G17="",0,IF(H17>G17,-1,1)) -> 0 | AC17: 2 | AD17: 2 | AE17: 2 | AH17: ELE008 | AI17: =CONCATENATE(AH17,"*") -> ELE008*
B18: 27 | C18: BRU034 | D18: ZCP | E18: BRUC06 | F18: =VLOOKUP(C18,[9]Dados!B:C,2,0) -> BRU034-BRUNIDORA | G18: =IFERROR(VLOOKUP(C18,#REF!,4,FALSE),"") | H18: =VLOOKUP(C18,Dados!B:AW,11,0) -> 1.56 | I18: =(VLOOKUP(C18,Dados!B:AW,48,0)) -> Fase de Degradação | J18: Total | K18: =IFERROR((VLOOKUP(C18,Dados!B:AW,44,0)),0) -> 0 | L18: =IFERROR((VLOOKUP(C18,Dados!B:AW,45,0)),0) -> 0 | M18: =IFERROR((VLOOKUP(C18,Dados!B:AW,43,0)),0) -> 0 | N18: =IFERROR((VLOOKUP(C18,Dados!B:AW,47,0)),0) -> 0 | O18: =IF(AND(J18="Parcial",N18>0,H18>1),-1,IF(AND(J18="Parcial",N18>0,H18<1.1),1,IF(AND(J18="Parcial",N18<0,H18>1.09),-1,IF(J18="Total",-1,IF(H18>1.09,1,2))))) -> -1 | P18: =IF(G18="",0,IF(H18>G18,-1,1)) -> 0 | AC18: -1 | AD18: -1 | AE18: -1 | AH18: ELE018 | AI18: =CONCATENATE(AH18,"*") -> ELE018*
B19: 20 | C19: BRU027 | D19: ZCP | E19: BRUC08 | F19: BRU027-BRUNIDORA | G19: =IFERROR(VLOOKUP(C19,#REF!,4,FALSE),"") | H19: =VLOOKUP(C19,Dados!B:AW,11,0) -> 1.62 | I19: =(VLOOKUP(C19,Dados!B:AW,48,0)) -> Fase de Degradação | J19: Não há | K19: =IFERROR((VLOOKUP(C19,Dados!B:AW,44,0)),0) -> 0 | L19: =IFERROR((VLOOKUP(C19,Dados!B:AW,45,0)),0) -> 0 | M19: =IFERROR((VLOOKUP(C19,Dados!B:AW,43,0)),0) -> 0 | N19: =IFERROR((VLOOKUP(C19,Dados!B:AW,47,0)),0) -> 0 | O19: =IF(AND(J19="Parcial",N19>0,H19>1),-1,IF(AND(J19="Parcial",N19>0,H19<1.1),1,IF(AND(J19="Parcial",N19<0,H19>1.09),-1,IF(J19="Total",-1,IF(H19>1.09,1,2))))) -> 1 | P19: =IF(G19="",0,IF(H19>G19,-1,1)) -> 0 | AC19: -1 | AD19: -1 | AE19: -1 | AH19: CEN043 | AI19: =CONCATENATE(AH19,"*") -> CEN043*
B20: 21 | C20: BRU028 | D20: ZCP | E20: BRUC08 | F20: =VLOOKUP(C20,[9]Dados!B:C,2,0) -> BRU028-BRUNIDORA | G20: =IFERROR(VLOOKUP(C20,#REF!,4,FALSE),"") | H20: =VLOOKUP(C20,Dados!B:AW,11,0) -> 1.43 | I20: =(VLOOKUP(C20,Dados!B:AW,48,0)) -> Fase de Degradação | J20: Total | K20: =IFERROR((VLOOKUP(C20,Dados!B:AW,44,0)),0) -> 0 | L20: =IFERROR((VLOOKUP(C20,Dados!B:AW,45,0)),0) -> 0 | M20: =IFERROR((VLOOKUP(C20,Dados!B:AW,43,0)),0) -> 0 | N20: =IFERROR((VLOOKUP(C20,Dados!B:AW,47,0)),0) -> 0 | O20: =IF(AND(J20="Parcial",N20>0,H20>1),-1,IF(AND(J20="Parcial",N20>0,H20<1.1),1,IF(AND(J20="Parcial",N20<0,H20>1.09),-1,IF(J20="Total",-1,IF(H20>1.09,1,2))))) -> -1 | P20: =IF(G20="",0,IF(H20>G20,-1,1)) -> 0 | AC20: 2 | AD20: 2 | AE20: 1 | AH20: JAT003 | AI20: =CONCATENATE(AH20,"*") -> JAT003*
B21: 22 | C21: BRU029 | D21: ZCP | E21: BRUC10 | F21: =VLOOKUP(C21,[9]Dados!B:C,2,0) -> BRU029-BRUNIDORA | G21: =IFERROR(VLOOKUP(C21,#REF!,4,FALSE),"") | H21: =VLOOKUP(C21,Dados!B:AW,11,0) -> 1.23 | I21: =(VLOOKUP(C21,Dados!B:AW,48,0)) -> Fase de Degradação | J21: Não há | K21: =IFERROR((VLOOKUP(C21,Dados!B:AW,44,0)),0) -> 0 | L21: =IFERROR((VLOOKUP(C21,Dados!B:AW,45,0)),0) -> 0 | M21: =IFERROR((VLOOKUP(C21,Dados!B:AW,43,0)),0) -> 0 | N21: =IFERROR((VLOOKUP(C21,Dados!B:AW,47,0)),0) -> 0 | O21: =IF(AND(J21="Parcial",N21>0,H21>1),-1,IF(AND(J21="Parcial",N21>0,H21<1.1),1,IF(AND(J21="Parcial",N21<0,H21>1.09),-1,IF(J21="Total",-1,IF(H21>1.09,1,2))))) -> 1 | P21: =IF(G21="",0,IF(H21>G21,-1,1)) -> 0 | AC21: -1 | AD21: -1 | AE21: -1 | AH21: BRU035 | AI21: =CONCATENATE(AH21,"*") -> BRU035*
B22: 23 | C22: BRU030 | D22: ZCP | E22: BRUC10 | F22: =VLOOKUP(C22,[9]Dados!B:C,2,0) -> BRU030-BRUNIDORA | G22: =IFERROR(VLOOKUP(C22,#REF!,4,FALSE),"") | H22: =VLOOKUP(C22,Dados!B:AW,11,0) -> 1.71 | I22: =(VLOOKUP(C22,Dados!B:AW,48,0)) -> Fase de Degradação | J22: Total | K22: =IFERROR((VLOOKUP(C22,Dados!B:AW,44,0)),0) -> 0 | L22: =IFERROR((VLOOKUP(C22,Dados!B:AW,45,0)),0) -> 0 | M22: =IFERROR((VLOOKUP(C22,Dados!B:AW,43,0)),0) -> 0 | N22: =IFERROR((VLOOKUP(C22,Dados!B:AW,47,0)),0) -> 0 | O22: =IF(AND(J22="Parcial",N22>0,H22>1),-1,IF(AND(J22="Parcial",N22>0,H22<1.1),1,IF(AND(J22="Parcial",N22<0,H22>1.09),-1,IF(J22="Total",-1,IF(H22>1.09,1,2))))) -> -1 | P22: =IF(G22="",0,IF(H22>G22,-1,1)) -> 0 | AC22: -1 | AD22: -1 | AE22: -1 | AH22: ROB006 | AI22: =CONCATENATE(AH22,"*") -> ROB006*
B23: 13 | C23: BRU010 | D23: ZCP | E23: BRUC12 | F23: =VLOOKUP(C23,[9]Dados!B:C,2,0) -> BRU010-BRUNIDORA | G23: =IFERROR(VLOOKUP(C23,#REF!,4,FALSE),"") | H23: =VLOOKUP(C23,Dados!B:AW,11,0) -> 1.26 | I23: =(VLOOKUP(C23,Dados!B:AW,48,0)) -> Fase de Degradação | J23: Não há | K23: =IFERROR((VLOOKUP(C23,Dados!B:AW,44,0)),0) -> 0 | L23: =IFERROR((VLOOKUP(C23,Dados!B:AW,45,0)),0) -> 0 | M23: =IFERROR((VLOOKUP(C23,Dados!B:AW,43,0)),0) -> 0 | N23: =IFERROR((VLOOKUP(C23,Dados!B:AW,47,0)),0) -> 0 | O23: =IF(AND(J23="Parcial",N23>0,H23>1),-1,IF(AND(J23="Parcial",N23>0,H23<1.1),1,IF(AND(J23="Parcial",N23<0,H23>1.09),-1,IF(J23="Total",-1,IF(H23>1.09,1,2))))) -> 1 | P23: =IF(G23="",0,IF(H23>G23,-1,1)) -> 0 | AC23: 2 | AD23: 2 | AE23: 1 | AH23: BRU036 | AI23: =CONCATENATE(AH23,"*") -> BRU036*
B24: 66 | C24: BRU073 | D24: ZCP | E24: BRUC12 | F24: BRU073-BRUNIDORA | G24: =IFERROR(VLOOKUP(C24,#REF!,4,FALSE),"") | H24: =VLOOKUP(C24,Dados!B:AW,11,0) -> 1.07 | I24: =(VLOOKUP(C24,Dados!B:AW,48,0)) -> Fase de Vida Útil | J24: Não há | K24: =IFERROR((VLOOKUP(C24,Dados!B:AW,44,0)),0) -> 0 | L24: =IFERROR((VLOOKUP(C24,Dados!B:AW,45,0)),0) -> 0 | M24: =IFERROR((VLOOKUP(C24,Dados!B:AW,43,0)),0) -> 0 | N24: =IFERROR((VLOOKUP(C24,Dados!B:AW,47,0)),0) -> 0 | O24: =IF(AND(J24="Parcial",N24>0,H24>1),-1,IF(AND(J24="Parcial",N24>0,H24<1.1),1,IF(AND(J24="Parcial",N24<0,H24>1.09),-1,IF(J24="Total",-1,IF(H24>1.09,1,2))))) -> 2 | P24: =IF(G24="",0,IF(H24>G24,-1,1)) -> 0 | AC24: -1 | AD24: -1 | AE24: -1 | AH24: INJ004 | AI24: =CONCATENATE(AH24,"*") -> INJ004*
B25: 24 | C25: BRU031 | D25: ZCP | E25: BRUC13 | F25: =VLOOKUP(C25,[9]Dados!B:C,2,0) -> BRU031-BRUNIDORA | G25: =IFERROR(VLOOKUP(C25,#REF!,4,FALSE),"") | H25: =VLOOKUP(C25,Dados!B:AW,11,0) -> 1.4 | I25: =(VLOOKUP(C25,Dados!B:AW,48,0)) -> Fase de Degradação | J25: Não há | K25: =IFERROR((VLOOKUP(C25,Dados!B:AW,44,0)),0) -> 0 | L25: =IFERROR((VLOOKUP(C25,Dados!B:AW,45,0)),0) -> 0 | M25: =IFERROR((VLOOKUP(C25,Dados!B:AW,43,0)),0) -> 0 | N25: =IFERROR((VLOOKUP(C25,Dados!B:AW,47,0)),0) -> 0 | O25: =IF(AND(J25="Parcial",N25>0,H25>1),-1,IF(AND(J25="Parcial",N25>0,H25<1.1),1,IF(AND(J25="Parcial",N25<0,H25>1.09),-1,IF(J25="Total",-1,IF(H25>1.09,1,2))))) -> 1 | P25: =IF(G25="",0,IF(H25>G25,-1,1)) -> 0 | AC25: 2 | AD25: 2 | AE25: 1 | AH25: CAB110 | AI25: =CONCATENATE(AH25,"*") -> CAB110*
B26: 25 | C26: BRU032 | D26: ZCP | E26: BRUC13 | F26: =VLOOKUP(C26,[9]Dados!B:C,2,0) -> BRU032-BRUNIDORA | G26: =IFERROR(VLOOKUP(C26,#REF!,4,FALSE),"") | H26: =VLOOKUP(C26,Dados!B:AW,11,0) -> 1.97 | I26: =(VLOOKUP(C26,Dados!B:AW,48,0)) -> Fase de Degradação | J26: Total | K26: =IFERROR((VLOOKUP(C26,Dados!B:AW,44,0)),0) -> 0 | L26: =IFERROR((VLOOKUP(C26,Dados!B:AW,45,0)),0) -> 0 | M26: =IFERROR((VLOOKUP(C26,Dados!B:AW,43,0)),0) -> 0 | N26: =IFERROR((VLOOKUP(C26,Dados!B:AW,47,0)),0) -> 0 | O26: =IF(AND(J26="Parcial",N26>0,H26>1),-1,IF(AND(J26="Parcial",N26>0,H26<1.1),1,IF(AND(J26="Parcial",N26<0,H26>1.09),-1,IF(J26="Total",-1,IF(H26>1.09,1,2))))) -> -1 | P26: =IF(G26="",0,IF(H26>G26,-1,1)) -> 0 | AC26: -1 | AD26: -1 | AE26: -1 | AH26: ROB039 | AI26: =CONCATENATE(AH26,"*") -> ROB039*
B27: 12 | C27: BRU009 | D27: ZCP | E27: BRUC14 | F27: BRU009-BRUNIDORA | G27: =IFERROR(VLOOKUP(C27,#REF!,4,FALSE),"") | H27: =VLOOKUP(C27,Dados!B:AW,11,0) -> 1.35 | I27: =(VLOOKUP(C27,Dados!B:AW,48,0)) -> Fase de Degradação | J27: Não há | K27: =IFERROR((VLOOKUP(C27,Dados!B:AW,44,0)),0) -> 0 | L27: =IFERROR((VLOOKUP(C27,Dados!B:AW,45,0)),0) -> 0 | M27: =IFERROR((VLOOKUP(C27,Dados!B:AW,43,0)),0) -> 0 | N27: =IFERROR((VLOOKUP(C27,Dados!B:AW,47,0)),0) -> 0 | O27: =IF(AND(J27="Parcial",N27>0,H27>1),-1,IF(AND(J27="Parcial",N27>0,H27<1.1),1,IF(AND(J27="Parcial",N27<0,H27>1.09),-1,IF(J27="Total",-1,IF(H27>1.09,1,2))))) -> 1 | P27: =IF(G27="",0,IF(H27>G27,-1,1)) -> 0 | AC27: 2 | AD27: 2 | AE27: 1 | AH27: ROB017 | AI27: =CONCATENATE(AH27,"*") -> ROB017*
B28: 50 | C28: BRU057 | D28: ZCP | E28: BRUC14 | F28: BRU057-BRUNIDORA | G28: =IFERROR(VLOOKUP(C28,#REF!,4,FALSE),"") | H28: =VLOOKUP(C28,Dados!B:AW,11,0) -> 1.13 | I28: =(VLOOKUP(C28,Dados!B:AW,48,0)) -> Fase de Degradação | K28: =IFERROR((VLOOKUP(C28,Dados!B:AW,44,0)),0) -> 0 | L28: =IFERROR((VLOOKUP(C28,Dados!B:AW,45,0)),0) -> 0 | M28: =IFERROR((VLOOKUP(C28,Dados!B:AW,43,0)),0) -> 0 | N28: =IFERROR((VLOOKUP(C28,Dados!B:AW,47,0)),0) -> 0 | O28: =IF(AND(J28="Parcial",N28>0,H28>1),-1,IF(AND(J28="Parcial",N28>0,H28<1.1),1,IF(AND(J28="Parcial",N28<0,H28>1.09),-1,IF(J28="Total",-1,IF(H28>1.09,1,2))))) -> 1 | P28: =IF(G28="",0,IF(H28>G28,-1,1)) -> 0 | AC28: -1 | AD28: -1 | AE28: -1 | AH28: PRE010 | AI28: =CONCATENATE(AH28,"*") -> PRE010*
B29: 28 | C29: BRU035 | D29: ZCP | E29: BRUC15 | F29: =VLOOKUP(C29,[9]Dados!B:C,2,0) -> BRU035-BRUNIDORA | G29: =IFERROR(VLOOKUP(C29,#REF!,4,FALSE),"") | H29: =VLOOKUP(C29,Dados!B:AW,11,0) -> 2.4 | I29: =(VLOOKUP(C29,Dados!B:AW,48,0)) -> Fase de Degradação | J29: Total | K29: =IFERROR((VLOOKUP(C29,Dados!B:AW,44,0)),0) -> 0 | L29: =IFERROR((VLOOKUP(C29,Dados!B:AW,45,0)),0) -> 0 | M29: =IFERROR((VLOOKUP(C29,Dados!B:AW,43,0)),0) -> 0 | N29: =IFERROR((VLOOKUP(C29,Dados!B:AW,47,0)),0) -> 0 | O29: =IF(AND(J29="Parcial",N29>0,H29>1),-1,IF(AND(J29="Parcial",N29>0,H29<1.1),1,IF(AND(J29="Parcial",N29<0,H29>1.09),-1,IF(J29="Total",-1,IF(H29>1.09,1,2))))) -> -1 | P29: =IF(G29="",0,IF(H29>G29,-1,1)) -> 0 | AC29: 2 | AD29: 2 | AE29: 1 | AH29: ROB005 | AI29: =CONCATENATE(AH29,"*") -> ROB005*
B30: 29 | C30: BRU036 | D30: ZCP | E30: BRUC15 | F30: =VLOOKUP(C30,[9]Dados!B:C,2,0) -> BRU036-BRUNIDORA | G30: =IFERROR(VLOOKUP(C30,#REF!,4,FALSE),"") | H30: =VLOOKUP(C30,Dados!B:AW,11,0) -> 2.08 | I30: =(VLOOKUP(C30,Dados!B:AW,48,0)) -> Fase de Degradação | J30: Não há | K30: =IFERROR((VLOOKUP(C30,Dados!B:AW,44,0)),0) -> 0 | L30: =IFERROR((VLOOKUP(C30,Dados!B:AW,45,0)),0) -> 0 | M30: =IFERROR((VLOOKUP(C30,Dados!B:AW,43,0)),0) -> 0 | N30: =IFERROR((VLOOKUP(C30,Dados!B:AW,47,0)),0) -> 0 | O30: =IF(AND(J30="Parcial",N30>0,H30>1),-1,IF(AND(J30="Parcial",N30>0,H30<1.1),1,IF(AND(J30="Parcial",N30<0,H30>1.09),-1,IF(J30="Total",-1,IF(H30>1.09,1,2))))) -> 1 | P30: =IF(G30="",0,IF(H30>G30,-1,1)) -> 0 | AC30: -1 | AD30: -1 | AE30: -1 | AH30: TOR020 | AI30: =CONCATENATE(AH30,"*") -> TOR020*
B31: 30 | C31: BRU037 | D31: ZCP | E31: BRUC16 | F31: =VLOOKUP(C31,[9]Dados!B:C,2,0) -> BRU037-BRUNIDORA | G31: =IFERROR(VLOOKUP(C31,#REF!,4,FALSE),"") | H31: =VLOOKUP(C31,Dados!B:AW,11,0) -> 2.59 | I31: =(VLOOKUP(C31,Dados!B:AW,48,0)) -> Fase de Degradação | J31: Não há | K31: =IFERROR((VLOOKUP(C31,Dados!B:AW,44,0)),0) -> 0 | L31: =IFERROR((VLOOKUP(C31,Dados!B:AW,45,0)),0) -> 0 | M31: =IFERROR((VLOOKUP(C31,Dados!B:AW,43,0)),0) -> 0 | N31: =IFERROR((VLOOKUP(C31,Dados!B:AW,47,0)),0) -> 0 | O31: =IF(AND(J31="Parcial",N31>0,H31>1),-1,IF(AND(J31="Parcial",N31>0,H31<1.1),1,IF(AND(J31="Parcial",N31<0,H31>1.09),-1,IF(J31="Total",-1,IF(H31>1.09,1,2))))) -> 1 | P31: =IF(G31="",0,IF(H31>G31,-1,1)) -> 0 | AC31: 2 | AD31: 2 | AE31: 1 | AH31: TOR021 | AI31: =CONCATENATE(AH31,"*") -> TOR021*
B32: 31 | C32: BRU038 | D32: ZCP | E32: BRUC16 | F32: BRU038-BRUNIDORA | G32: =IFERROR(VLOOKUP(C32,#REF!,4,FALSE),"") | H32: =VLOOKUP(C32,Dados!B:AW,11,0) -> 1.82 | I32: =(VLOOKUP(C32,Dados!B:AW,48,0)) -> Fase de Degradação | J32: Não há | K32: =IFERROR((VLOOKUP(C32,Dados!B:AW,44,0)),0) -> 0 | L32: =IFERROR((VLOOKUP(C32,Dados!B:AW,45,0)),0) -> 0 | M32: =IFERROR((VLOOKUP(C32,Dados!B:AW,43,0)),0) -> 0 | N32: =IFERROR((VLOOKUP(C32,Dados!B:AW,47,0)),0) -> 0 | O32: =IF(AND(J32="Parcial",N32>0,H32>1),-1,IF(AND(J32="Parcial",N32>0,H32<1.1),1,IF(AND(J32="Parcial",N32<0,H32>1.09),-1,IF(J32="Total",-1,IF(H32>1.09,1,2))))) -> 1 | P32: =IF(G32="",0,IF(H32>G32,-1,1)) -> 0 | AC32: -1 | AD32: -1 | AE32: -1 | AH32: TOR028 | AI32: =CONCATENATE(AH32,"*") -> TOR028*
B33: 32 | C33: BRU039 | D33: ZCP | E33: BRUC17 | F33: BRU039-BRUNIDORA | G33: =IFERROR(VLOOKUP(C33,#REF!,4,FALSE),"") | H33: =VLOOKUP(C33,Dados!B:AW,11,0) -> 2.34 | I33: =(VLOOKUP(C33,Dados!B:AW,48,0)) -> Fase de Degradação | J33: Total | K33: =IFERROR((VLOOKUP(C33,Dados!B:AW,44,0)),0) -> 0 | L33: =IFERROR((VLOOKUP(C33,Dados!B:AW,45,0)),0) -> 0 | M33: =IFERROR((VLOOKUP(C33,Dados!B:AW,43,0)),0) -> 0 | N33: =IFERROR((VLOOKUP(C33,Dados!B:AW,47,0)),0) -> 0 | O33: =IF(AND(J33="Parcial",N33>0,H33>1),-1,IF(AND(J33="Parcial",N33>0,H33<1.1),1,IF(AND(J33="Parcial",N33<0,H33>1.09),-1,IF(J33="Total",-1,IF(H33>1.09,1,2))))) -> -1 | P33: =IF(G33="",0,IF(H33>G33,-1,1)) -> 0 | AC33: -1 | AD33: -1 | AE33: -1 | AH33: CEN058 | AI33: =CONCATENATE(AH33,"*") -> CEN058*
B34: 33 | C34: BRU040 | D34: ZCP | E34: BRUC17 | F34: BRU040-BRUNIDORA | G34: =IFERROR(VLOOKUP(C34,#REF!,4,FALSE),"") | H34: =VLOOKUP(C34,Dados!B:AW,11,0) -> 1.39 | I34: =(VLOOKUP(C34,Dados!B:AW,48,0)) -> Fase de Degradação | J34: Não há | K34: =IFERROR((VLOOKUP(C34,Dados!B:AW,44,0)),0) -> 0 | L34: =IFERROR((VLOOKUP(C34,Dados!B:AW,45,0)),0) -> 0 | M34: =IFERROR((VLOOKUP(C34,Dados!B:AW,43,0)),0) -> 0 | N34: =IFERROR((VLOOKUP(C34,Dados!B:AW,47,0)),0) -> 0 | O34: =IF(AND(J34="Parcial",N34>0,H34>1),-1,IF(AND(J34="Parcial",N34>0,H34<1.1),1,IF(AND(J34="Parcial",N34<0,H34>1.09),-1,IF(J34="Total",-1,IF(H34>1.09,1,2))))) -> 1 | P34: =IF(G34="",0,IF(H34>G34,-1,1)) -> 0 | AC34: 2 | AD34: 2 | AE34: 1 | AH34: ROB010 | AI34: =CONCATENATE(AH34,"*") -> ROB010*
B35: 35 | C35: BRU042 | D35: ZCP | E35: BRUC18 | F35: BRU042-BRUNIDORA | G35: =IFERROR(VLOOKUP(C35,#REF!,4,FALSE),"") | H35: =VLOOKUP(C35,Dados!B:AW,11,0) -> 1.22 | I35: =(VLOOKUP(C35,Dados!B:AW,48,0)) -> Fase de Degradação | J35: Total | K35: =IFERROR((VLOOKUP(C35,Dados!B:AW,44,0)),0) -> 0 | L35: =IFERROR((VLOOKUP(C35,Dados!B:AW,45,0)),0) -> 0 | M35: =IFERROR((VLOOKUP(C35,Dados!B:AW,43,0)),0) -> 0 | N35: =IFERROR((VLOOKUP(C35,Dados!B:AW,47,0)),0) -> 0 | O35: =IF(AND(J35="Parcial",N35>0,H35>1),-1,IF(AND(J35="Parcial",N35>0,H35<1.1),1,IF(AND(J35="Parcial",N35<0,H35>1.09),-1,IF(J35="Total",-1,IF(H35>1.09,1,2))))) -> -1 | P35: =IF(G35="",0,IF(H35>G35,-1,1)) -> 0 | AC35: -1 | AD35: -1 | AE35: -1 | AH35: ROB037 | AI35: =CONCATENATE(AH35,"*") -> ROB037*
B36: 36 | C36: BRU043 | D36: ZCP | E36: BRUC18 | F36: BRU043-BRUNIDORA | G36: =IFERROR(VLOOKUP(C36,#REF!,4,FALSE),"") | H36: =VLOOKUP(C36,Dados!B:AW,11,0) -> 1.35 | I36: =(VLOOKUP(C36,Dados!B:AW,48,0)) -> Fase de Degradação | J36: Não há | K36: =IFERROR((VLOOKUP(C36,Dados!B:AW,44,0)),0) -> 0 | L36: =IFERROR((VLOOKUP(C36,Dados!B:AW,45,0)),0) -> 0 | M36: =IFERROR((VLOOKUP(C36,Dados!B:AW,43,0)),0) -> 0 | N36: =IFERROR((VLOOKUP(C36,Dados!B:AW,47,0)),0) -> 0 | O36: =IF(AND(J36="Parcial",N36>0,H36>1),-1,IF(AND(J36="Parcial",N36>0,H36<1.1),1,IF(AND(J36="Parcial",N36<0,H36>1.09),-1,IF(J36="Total",-1,IF(H36>1.09,1,2))))) -> 1 | P36: =IF(G36="",0,IF(H36>G36,-1,1)) -> 0 | AC36: 2 | AD36: 2 | AE36: 1 | AH36: CEN064 | AI36: =CONCATENATE(AH36,"*") -> CEN064*
B37: 37 | C37: BRU044 | D37: ZCP | E37: BRUC19 | F37: =VLOOKUP(C37,[9]Dados!B:C,2,0) -> BRU044-BRUNIDORA | G37: =IFERROR(VLOOKUP(C37,#REF!,4,FALSE),"") | H37: =VLOOKUP(C37,Dados!B:AW,11,0) -> 1.39 | I37: =(VLOOKUP(C37,Dados!B:AW,48,0)) -> Fase de Degradação | J37: Não há | K37: =IFERROR((VLOOKUP(C37,Dados!B:AW,44,0)),0) -> 0 | L37: =IFERROR((VLOOKUP(C37,Dados!B:AW,45,0)),0) -> 0 | M37: =IFERROR((VLOOKUP(C37,Dados!B:AW,43,0)),0) -> 0 | N37: =IFERROR((VLOOKUP(C37,Dados!B:AW,47,0)),0) -> 0 | O37: =IF(AND(J37="Parcial",N37>0,H37>1),-1,IF(AND(J37="Parcial",N37>0,H37<1.1),1,IF(AND(J37="Parcial",N37<0,H37>1.09),-1,IF(J37="Total",-1,IF(H37>1.09,1,2))))) -> 1 | P37: =IF(G37="",0,IF(H37>G37,-1,1)) -> 0 | AC37: -1 | AD37: -1 | AE37: -1 | AH37: TOR027 | AI37: =CONCATENATE(AH37,"*") -> TOR027*
B38: 38 | C38: BRU045 | D38: ZCP | E38: BRUC19 | F38: =VLOOKUP(C38,[9]Dados!B:C,2,0) -> BRU045-BRUNIDORA | G38: =IFERROR(VLOOKUP(C38,#REF!,4,FALSE),"") | H38: =VLOOKUP(C38,Dados!B:AW,11,0) -> 1.79 | I38: =(VLOOKUP(C38,Dados!B:AW,48,0)) -> Fase de Degradação | J38: Não há | K38: =IFERROR((VLOOKUP(C38,Dados!B:AW,44,0)),0) -> 0 | L38: =IFERROR((VLOOKUP(C38,Dados!B:AW,45,0)),0) -> 0 | M38: =IFERROR((VLOOKUP(C38,Dados!B:AW,43,0)),0) -> 0 | N38: =IFERROR((VLOOKUP(C38,Dados!B:AW,47,0)),0) -> 0 | O38: =IF(AND(J38="Parcial",N38>0,H38>1),-1,IF(AND(J38="Parcial",N38>0,H38<1.1),1,IF(AND(J38="Parcial",N38<0,H38>1.09),-1,IF(J38="Total",-1,IF(H38>1.09,1,2))))) -> 1 | P38: =IF(G38="",0,IF(H38>G38,-1,1)) -> 0 | AC38: 2 | AD38: 2 | AE38: 1 | AH38: CEN094 | AI38: =CONCATENATE(AH38,"*") -> CEN094*
B39: 39 | C39: BRU046 | D39: ZCP | E39: BRUC20 | F39: =VLOOKUP(C39,[9]Dados!B:C,2,0) -> BRU046-BRUNIDORA | G39: =IFERROR(VLOOKUP(C39,#REF!,4,FALSE),"") | H39: =VLOOKUP(C39,Dados!B:AW,11,0) -> 1.69 | I39: =(VLOOKUP(C39,Dados!B:AW,48,0)) -> Fase de Degradação | J39: Total | K39: =IFERROR((VLOOKUP(C39,Dados!B:AW,44,0)),0) -> 0 | L39: =IFERROR((VLOOKUP(C39,Dados!B:AW,45,0)),0) -> 0 | M39: =IFERROR((VLOOKUP(C39,Dados!B:AW,43,0)),0) -> 0 | N39: =IFERROR((VLOOKUP(C39,Dados!B:AW,47,0)),0) -> 0 | O39: =IF(AND(J39="Parcial",N39>0,H39>1),-1,IF(AND(J39="Parcial",N39>0,H39<1.1),1,IF(AND(J39="Parcial",N39<0,H39>1.09),-1,IF(J39="Total",-1,IF(H39>1.09,1,2))))) -> -1 | P39: =IF(G39="",0,IF(H39>G39,-1,1)) -> 0 | AC39: -1 | AD39: -1 | AE39: -1 | AH39: BRU045 | AI39: =CONCATENATE(AH39,"*") -> BRU045*
B40: 40 | C40: BRU047 | D40: ZCP | E40: BRUC20 | F40: BRU047-BRUNIDORA | G40: =IFERROR(VLOOKUP(C40,#REF!,4,FALSE),"") | H40: =VLOOKUP(C40,Dados!B:AW,11,0) -> 1.05 | I40: =(VLOOKUP(C40,Dados!B:AW,48,0)) -> Fase de Vida Útil | J40: Não há | K40: =IFERROR((VLOOKUP(C40,Dados!B:AW,44,0)),0) -> 0 | L40: =IFERROR((VLOOKUP(C40,Dados!B:AW,45,0)),0) -> 0 | M40: =IFERROR((VLOOKUP(C40,Dados!B:AW,43,0)),0) -> 0 | N40: =IFERROR((VLOOKUP(C40,Dados!B:AW,47,0)),0) -> 0 | O40: =IF(AND(J40="Parcial",N40>0,H40>1),-1,IF(AND(J40="Parcial",N40>0,H40<1.1),1,IF(AND(J40="Parcial",N40<0,H40>1.09),-1,IF(J40="Total",-1,IF(H40>1.09,1,2))))) -> 2 | P40: =IF(G40="",0,IF(H40>G40,-1,1)) -> 0 | AC40: -1 | AD40: -1 | AE40: -1 | AH40: CEN065 | AI40: =CONCATENATE(AH40,"*") -> CEN065*
B41: 41 | C41: BRU048 | D41: ZCP | E41: BRUC21 | F41: BRU048-BRUNIDORA | G41: =IFERROR(VLOOKUP(C41,#REF!,4,FALSE),"") | H41: =VLOOKUP(C41,Dados!B:AW,11,0) -> 1.06 | I41: =(VLOOKUP(C41,Dados!B:AW,48,0)) -> Fase de Vida Útil | J41: Não há | K41: =IFERROR((VLOOKUP(C41,Dados!B:AW,44,0)),0) -> 0 | L41: =IFERROR((VLOOKUP(C41,Dados!B:AW,45,0)),0) -> 0 | M41: =IFERROR((VLOOKUP(C41,Dados!B:AW,43,0)),0) -> 0 | N41: =IFERROR((VLOOKUP(C41,Dados!B:AW,47,0)),0) -> 0 | O41: =IF(AND(J41="Parcial",N41>0,H41>1),-1,IF(AND(J41="Parcial",N41>0,H41<1.1),1,IF(AND(J41="Parcial",N41<0,H41>1.09),-1,IF(J41="Total",-1,IF(H41>1.09,1,2))))) -> 2 | P41: =IF(G41="",0,IF(H41>G41,-1,1)) -> 0 | AC41: 2 | AD41: 2 | AE41: 1 | AH41: TOR025 | AI41: =CONCATENATE(AH41,"*") -> TOR025*
B42: 42 | C42: BRU049 | D42: ZCP | E42: BRUC22 | F42: BRU049-BRUNIDORA | G42: =IFERROR(VLOOKUP(C42,#REF!,4,FALSE),"") | H42: =VLOOKUP(C42,Dados!B:AW,11,0) -> 1.18 | I42: =(VLOOKUP(C42,Dados!B:AW,48,0)) -> Fase de Degradação | J42: Não há | K42: =IFERROR((VLOOKUP(C42,Dados!B:AW,44,0)),0) -> 0 | L42: =IFERROR((VLOOKUP(C42,Dados!B:AW,45,0)),0) -> 0 | M42: =IFERROR((VLOOKUP(C42,Dados!B:AW,43,0)),0) -> 0 | N42: =IFERROR((VLOOKUP(C42,Dados!B:AW,47,0)),0) -> 0 | O42: =IF(AND(J42="Parcial",N42>0,H42>1),-1,IF(AND(J42="Parcial",N42>0,H42<1.1),1,IF(AND(J42="Parcial",N42<0,H42>1.09),-1,IF(J42="Total",-1,IF(H42>1.09,1,2))))) -> 1 | P42: =IF(G42="",0,IF(H42>G42,-1,1)) -> 0 | AC42: -1 | AD42: -1 | AE42: -1 | AH42: SOP008 | AI42: =CONCATENATE(AH42,"*") -> SOP008*
B43: 43 | C43: BRU050 | D43: ZCP | E43: BRUC23 | F43: BRU050-BRUNIDORA | G43: =IFERROR(VLOOKUP(C43,#REF!,4,FALSE),"") | H43: =VLOOKUP(C43,Dados!B:AW,11,0) -> 1.78 | I43: =(VLOOKUP(C43,Dados!B:AW,48,0)) -> Fase de Degradação | J43: Não há | K43: =IFERROR((VLOOKUP(C43,Dados!B:AW,44,0)),0) -> 0 | L43: =IFERROR((VLOOKUP(C43,Dados!B:AW,45,0)),0) -> 0 | M43: =IFERROR((VLOOKUP(C43,Dados!B:AW,43,0)),0) -> 0 | N43: =IFERROR((VLOOKUP(C43,Dados!B:AW,47,0)),0) -> 0 | O43: =IF(AND(J43="Parcial",N43>0,H43>1),-1,IF(AND(J43="Parcial",N43>0,H43<1.1),1,IF(AND(J43="Parcial",N43<0,H43>1.09),-1,IF(J43="Total",-1,IF(H43>1.09,1,2))))) -> 1 | P43: =IF(G43="",0,IF(H43>G43,-1,1)) -> 0 | AC43: 2 | AD43: 2 | AE43: 1 | AH43: BRU032 | AI43: =CONCATENATE(AH43,"*") -> BRU032*
B44: 44 | C44: BRU051 | D44: ZCP | E44: BRUC23 | F44: BRU051-BRUNIDORA | G44: =IFERROR(VLOOKUP(C44,#REF!,4,FALSE),"") | H44: =VLOOKUP(C44,Dados!B:AW,11,0) -> 1.21 | I44: =(VLOOKUP(C44,Dados!B:AW,48,0)) -> Fase de Degradação | J44: Não há | K44: =IFERROR((VLOOKUP(C44,Dados!B:AW,44,0)),0) -> 0 | L44: =IFERROR((VLOOKUP(C44,Dados!B:AW,45,0)),0) -> 0 | M44: =IFERROR((VLOOKUP(C44,Dados!B:AW,43,0)),0) -> 0 | N44: =IFERROR((VLOOKUP(C44,Dados!B:AW,47,0)),0) -> 0 | O44: =IF(AND(J44="Parcial",N44>0,H44>1),-1,IF(AND(J44="Parcial",N44>0,H44<1.1),1,IF(AND(J44="Parcial",N44<0,H44>1.09),-1,IF(J44="Total",-1,IF(H44>1.09,1,2))))) -> 1 | P44: =IF(G44="",0,IF(H44>G44,-1,1)) -> 0 | AC44: -1 | AD44: -1 | AE44: -1 | AH44: BRU052 | AI44: =CONCATENATE(AH44,"*") -> BRU052*
B45: 45 | C45: BRU052 | D45: ZCP | E45: BRUC24 | F45: BRU052-BRUNIDORA | G45: =IFERROR(VLOOKUP(C45,#REF!,4,FALSE),"") | H45: =VLOOKUP(C45,Dados!B:AW,11,0) -> 1.96 | I45: =(VLOOKUP(C45,Dados!B:AW,48,0)) -> Fase de Degradação | J45: Não há | K45: =IFERROR((VLOOKUP(C45,Dados!B:AW,44,0)),0) -> 0 | L45: =IFERROR((VLOOKUP(C45,Dados!B:AW,45,0)),0) -> 0 | M45: =IFERROR((VLOOKUP(C45,Dados!B:AW,43,0)),0) -> 0 | N45: =IFERROR((VLOOKUP(C45,Dados!B:AW,47,0)),0) -> 0 | O45: =IF(AND(J45="Parcial",N45>0,H45>1),-1,IF(AND(J45="Parcial",N45>0,H45<1.1),1,IF(AND(J45="Parcial",N45<0,H45>1.09),-1,IF(J45="Total",-1,IF(H45>1.09,1,2))))) -> 1 | P45: =IF(G45="",0,IF(H45>G45,-1,1)) -> 0 | AC45: 2 | AD45: 2 | AE45: 2 | AH45: BRU038 | AI45: =CONCATENATE(AH45,"*") -> BRU038*
B46: 46 | C46: BRU053 | D46: ZCP | E46: BRUC24 | F46: BRU053-BRUNIDORA | G46: =IFERROR(VLOOKUP(C46,#REF!,4,FALSE),"") | H46: =VLOOKUP(C46,Dados!B:AW,11,0) -> 1.02 | I46: =(VLOOKUP(C46,Dados!B:AW,48,0)) -> Fase de Vida Útil | J46: Não há | K46: =IFERROR((VLOOKUP(C46,Dados!B:AW,44,0)),0) -> 0 | L46: =IFERROR((VLOOKUP(C46,Dados!B:AW,45,0)),0) -> 0 | M46: =IFERROR((VLOOKUP(C46,Dados!B:AW,43,0)),0) -> 0 | N46: =IFERROR((VLOOKUP(C46,Dados!B:AW,47,0)),0) -> 0 | O46: =IF(AND(J46="Parcial",N46>0,H46>1),-1,IF(AND(J46="Parcial",N46>0,H46<1.1),1,IF(AND(J46="Parcial",N46<0,H46>1.09),-1,IF(J46="Total",-1,IF(H46>1.09,1,2))))) -> 2 | P46: =IF(G46="",0,IF(H46>G46,-1,1)) -> 0 | AC46: 2 | AD46: 2 | AE46: 2 | AH46: MAQ159 | AI46: =CONCATENATE(AH46,"*") -> MAQ159*
B47: 605 | C47: ROB086 | D47: ZCP | E47: BRUC24 | F47: ROB086-ROBÔ | G47: =IFERROR(VLOOKUP(C47,#REF!,4,FALSE),"") | H47: =VLOOKUP(C47,Dados!B:AW,11,0) -> 0 | I47: =(VLOOKUP(C47,Dados!B:AW,48,0)) -> Confiabilidade em Crescimento | J47: Não há | K47: =IFERROR((VLOOKUP(C47,Dados!B:AW,44,0)),0) -> 0 | L47: =IFERROR((VLOOKUP(C47,Dados!B:AW,45,0)),0) -> 0 | M47: =IFERROR((VLOOKUP(C47,Dados!B:AW,43,0)),0) -> 0 | N47: =IFERROR((VLOOKUP(C47,Dados!B:AW,47,0)),0) -> 0 | O47: =IF(AND(J47="Parcial",N47>0,H47>1),-1,IF(AND(J47="Parcial",N47>0,H47<1.1),1,IF(AND(J47="Parcial",N47<0,H47>1.09),-1,IF(J47="Total",-1,IF(H47>1.09,1,2))))) -> 2 | P47: =IF(G47="",0,IF(H47>G47,-1,1)) -> 0 | AC47: 2 | AD47: 2 | AE47: 2 | AH47: BRU046 | AI47: =CONCATENATE(AH47,"*") -> BRU046*
B48: 47 | C48: BRU054 | D48: ZCP | E48: BRUC25 | F48: BRU054-BRUNIDORA | G48: =IFERROR(VLOOKUP(C48,#REF!,4,FALSE),"") | H48: =VLOOKUP(C48,Dados!B:AW,11,0) -> 1.29 | I48: =(VLOOKUP(C48,Dados!B:AW,48,0)) -> Fase de Degradação | J48: Não há | K48: =IFERROR((VLOOKUP(C48,Dados!B:AW,44,0)),0) -> 0 | L48: =IFERROR((VLOOKUP(C48,Dados!B:AW,45,0)),0) -> 0 | M48: =IFERROR((VLOOKUP(C48,Dados!B:AW,43,0)),0) -> 0 | N48: =IFERROR((VLOOKUP(C48,Dados!B:AW,47,0)),0) -> 0 | O48: =IF(AND(J48="Parcial",N48>0,H48>1),-1,IF(AND(J48="Parcial",N48>0,H48<1.1),1,IF(AND(J48="Parcial",N48<0,H48>1.09),-1,IF(J48="Total",-1,IF(H48>1.09,1,2))))) -> 1 | P48: =IF(G48="",0,IF(H48>G48,-1,1)) -> 0 | AC48: 2 | AD48: 2 | AE48: 2 | AH48: ELE013 | AI48: =CONCATENATE(AH48,"*") -> ELE013*
B49: 48 | C49: BRU055 | D49: ZCP | E49: BRUC25 | F49: BRU055-BRUNIDORA | G49: =IFERROR(VLOOKUP(C49,#REF!,4,FALSE),"") | H49: =VLOOKUP(C49,Dados!B:AW,11,0) -> 0.94 | I49: =(VLOOKUP(C49,Dados!B:AW,48,0)) -> Confiabilidade em Crescimento | J49: Não há | K49: =IFERROR((VLOOKUP(C49,Dados!B:AW,44,0)),0) -> 0 | L49: =IFERROR((VLOOKUP(C49,Dados!B:AW,45,0)),0) -> 0 | M49: =IFERROR((VLOOKUP(C49,Dados!B:AW,43,0)),0) -> 0 | N49: =IFERROR((VLOOKUP(C49,Dados!B:AW,47,0)),0) -> 0 | O49: =IF(AND(J49="Parcial",N49>0,H49>1),-1,IF(AND(J49="Parcial",N49>0,H49<1.1),1,IF(AND(J49="Parcial",N49<0,H49>1.09),-1,IF(J49="Total",-1,IF(H49>1.09,1,2))))) -> 2 | P49: =IF(G49="",0,IF(H49>G49,-1,1)) -> 0 | AC49: 2 | AD49: 2 | AE49: 1 | AH49: CEN051 | AI49: =CONCATENATE(AH49,"*") -> CEN051*
B50: 49 | C50: BRU056 | D50: ZCP | E50: BRUC26 | F50: BRU056-BRUNIDORA | G50: =IFERROR(VLOOKUP(C50,#REF!,4,FALSE),"") | H50: =VLOOKUP(C50,Dados!B:AW,11,0) -> 0.96 | I50: =(VLOOKUP(C50,Dados!B:AW,48,0)) -> Confiabilidade em Crescimento | K50: =IFERROR((VLOOKUP(C50,Dados!B:AW,44,0)),0) -> 0 | L50: =IFERROR((VLOOKUP(C50,Dados!B:AW,45,0)),0) -> 0 | M50: =IFERROR((VLOOKUP(C50,Dados!B:AW,43,0)),0) -> 0 | N50: =IFERROR((VLOOKUP(C50,Dados!B:AW,47,0)),0) -> 0 | O50: =IF(AND(J50="Parcial",N50>0,H50>1),-1,IF(AND(J50="Parcial",N50>0,H50<1.1),1,IF(AND(J50="Parcial",N50<0,H50>1.09),-1,IF(J50="Total",-1,IF(H50>1.09,1,2))))) -> 2 | P50: =IF(G50="",0,IF(H50>G50,-1,1)) -> 0 | AC50: 2 | AD50: 2 | AE50: 1 | AH50: CEN089 | AI50: =CONCATENATE(AH50,"*") -> CEN089*
B51: 60 | C51: BRU067 | D51: ZCP | E51: BRUC26 | F51: BRU067-BRUNIDORA | G51: =IFERROR(VLOOKUP(C51,#REF!,4,FALSE),"") | H51: =VLOOKUP(C51,Dados!B:AW,11,0) -> 0.85 | I51: =(VLOOKUP(C51,Dados!B:AW,48,0)) -> Confiabilidade em Crescimento | K51: =IFERROR((VLOOKUP(C51,Dados!B:AW,44,0)),0) -> 0 | L51: =IFERROR((VLOOKUP(C51,Dados!B:AW,45,0)),0) -> 0 | M51: =IFERROR((VLOOKUP(C51,Dados!B:AW,43,0)),0) -> 0 | N51: =IFERROR((VLOOKUP(C51,Dados!B:AW,47,0)),0) -> 0 | O51: =IF(AND(J51="Parcial",N51>0,H51>1),-1,IF(AND(J51="Parcial",N51>0,H51<1.1),1,IF(AND(J51="Parcial",N51<0,H51>1.09),-1,IF(J51="Total",-1,IF(H51>1.09,1,2))))) -> 2 | P51: =IF(G51="",0,IF(H51>G51,-1,1)) -> 0 | AC51: 2 | AD51: 2 | AE51: 1 | AH51: RET002 | AI51: =CONCATENATE(AH51,"*") -> RET002*
B52: 14 | C52: BRU011 | D52: ZCP | E52: BRUC27 | F52: =VLOOKUP(C52,[9]Dados!B:C,2,0) -> BRU011-BRUNIDORA | G52: =IFERROR(VLOOKUP(C52,#REF!,4,FALSE),"") | H52: =VLOOKUP(C52,Dados!B:AW,11,0) -> 1.47 | I52: =(VLOOKUP(C52,Dados!B:AW,48,0)) -> Fase de Degradação | J52: Não há | K52: =IFERROR((VLOOKUP(C52,Dados!B:AW,44,0)),0) -> 0 | L52: =IFERROR((VLOOKUP(C52,Dados!B:AW,45,0)),0) -> 0 | M52: =IFERROR((VLOOKUP(C52,Dados!B:AW,43,0)),0) -> 0 | N52: =IFERROR((VLOOKUP(C52,Dados!B:AW,47,0)),0) -> 0 | O52: =IF(AND(J52="Parcial",N52>0,H52>1),-1,IF(AND(J52="Parcial",N52>0,H52<1.1),1,IF(AND(J52="Parcial",N52<0,H52>1.09),-1,IF(J52="Total",-1,IF(H52>1.09,1,2))))) -> 1 | P52: =IF(G52="",0,IF(H52>G52,-1,1)) -> 0 | AC52: 2 | AD52: 2 | AE52: 2 | AH52: PRE019 | AI52: =CONCATENATE(AH52,"*") -> PRE019*
B53: 51 | C53: BRU058 | D53: ZCP | E53: BRUC27 | F53: BRU058-BRUNIDORA | G53: =IFERROR(VLOOKUP(C53,#REF!,4,FALSE),"") | H53: =VLOOKUP(C53,Dados!B:AW,11,0) -> 0.61 | I53: =(VLOOKUP(C53,Dados!B:AW,48,0)) -> Confiabilidade em Crescimento | K53: =IFERROR((VLOOKUP(C53,Dados!B:AW,44,0)),0) -> 0 | L53: =IFERROR((VLOOKUP(C53,Dados!B:AW,45,0)),0) -> 0 | M53: =IFERROR((VLOOKUP(C53,Dados!B:AW,43,0)),0) -> 0 | N53: =IFERROR((VLOOKUP(C53,Dados!B:AW,47,0)),0) -> 0 | O53: =IF(AND(J53="Parcial",N53>0,H53>1),-1,IF(AND(J53="Parcial",N53>0,H53<1.1),1,IF(AND(J53="Parcial",N53<0,H53>1.09),-1,IF(J53="Total",-1,IF(H53>1.09,1,2))))) -> 2 | P53: =IF(G53="",0,IF(H53>G53,-1,1)) -> 0 | AC53: 2 | AD53: 2 | AE53: 2 | AH53: PRE055 | AI53: =CONCATENATE(AH53,"*") -> PRE055*
B54: 53 | C54: BRU060 | D54: ZCP | E54: BRUC28 | F54: BRU060-BRUNIDORA | G54: =IFERROR(VLOOKUP(C54,#REF!,4,FALSE),"") | H54: =VLOOKUP(C54,Dados!B:AW,11,0) -> 0.57 | I54: =(VLOOKUP(C54,Dados!B:AW,48,0)) -> Confiabilidade em Crescimento | K54: =IFERROR((VLOOKUP(C54,Dados!B:AW,44,0)),0) -> 0 | L54: =IFERROR((VLOOKUP(C54,Dados!B:AW,45,0)),0) -> 0 | M54: =IFERROR((VLOOKUP(C54,Dados!B:AW,43,0)),0) -> 0 | N54: =IFERROR((VLOOKUP(C54,Dados!B:AW,47,0)),0) -> 0 | O54: =IF(AND(J54="Parcial",N54>0,H54>1),-1,IF(AND(J54="Parcial",N54>0,H54<1.1),1,IF(AND(J54="Parcial",N54<0,H54>1.09),-1,IF(J54="Total",-1,IF(H54>1.09,1,2))))) -> 2 | P54: =IF(G54="",0,IF(H54>G54,-1,1)) -> 0 | AC54: 2 | AD54: 2 | AE54: 2 | AH54: BRU050 | AI54: =CONCATENATE(AH54,"*") -> BRU050*
B55: 54 | C55: BRU061 | D55: ZCP | E55: BRUC28 | F55: BRU061-BRUNIDORA | G55: =IFERROR(VLOOKUP(C55,#REF!,4,FALSE),"") | H55: =VLOOKUP(C55,Dados!B:AW,11,0) -> 1.41 | I55: =(VLOOKUP(C55,Dados!B:AW,48,0)) -> Fase de Degradação | K55: =IFERROR((VLOOKUP(C55,Dados!B:AW,44,0)),0) -> 0 | L55: =IFERROR((VLOOKUP(C55,Dados!B:AW,45,0)),0) -> 0 | M55: =IFERROR((VLOOKUP(C55,Dados!B:AW,43,0)),0) -> 0 | N55: =IFERROR((VLOOKUP(C55,Dados!B:AW,47,0)),0) -> 0 | O55: =IF(AND(J55="Parcial",N55>0,H55>1),-1,IF(AND(J55="Parcial",N55>0,H55<1.1),1,IF(AND(J55="Parcial",N55<0,H55>1.09),-1,IF(J55="Total",-1,IF(H55>1.09,1,2))))) -> 1 | P55: =IF(G55="",0,IF(H55>G55,-1,1)) -> 0 | AC55: 2 | AD55: 2 | AE55: 2 | AH55: ROB016 | AI55: =CONCATENATE(AH55,"*") -> ROB016*
B56: 56 | C56: BRU063 | D56: ZCP | E56: BRUC29 | F56: BRU063-BRUNIDORA | G56: =IFERROR(VLOOKUP(C56,#REF!,4,FALSE),"") | H56: =VLOOKUP(C56,Dados!B:AW,11,0) -> 0.48 | I56: =(VLOOKUP(C56,Dados!B:AW,48,0)) -> Confiabilidade em Crescimento | K56: =IFERROR((VLOOKUP(C56,Dados!B:AW,44,0)),0) -> 0 | L56: =IFERROR((VLOOKUP(C56,Dados!B:AW,45,0)),0) -> 0 | M56: =IFERROR((VLOOKUP(C56,Dados!B:AW,43,0)),0) -> 0 | N56: =IFERROR((VLOOKUP(C56,Dados!B:AW,47,0)),0) -> 0 | O56: =IF(AND(J56="Parcial",N56>0,H56>1),-1,IF(AND(J56="Parcial",N56>0,H56<1.1),1,IF(AND(J56="Parcial",N56<0,H56>1.09),-1,IF(J56="Total",-1,IF(H56>1.09,1,2))))) -> 2 | P56: =IF(G56="",0,IF(H56>G56,-1,1)) -> 0 | AC56: 2 | AD56: 2 | AE56: 2 | AH56: ROB041 | AI56: =CONCATENATE(AH56,"*") -> ROB041*
B57: 57 | C57: BRU064 | D57: ZCP | E57: BRUC29 | F57: BRU064-BRUNIDORA | G57: =IFERROR(VLOOKUP(C57,#REF!,4,FALSE),"") | H57: =VLOOKUP(C57,Dados!B:AW,11,0) -> 0.7 | I57: =(VLOOKUP(C57,Dados!B:AW,48,0)) -> Confiabilidade em Crescimento | K57: =IFERROR((VLOOKUP(C57,Dados!B:AW,44,0)),0) -> 0 | L57: =IFERROR((VLOOKUP(C57,Dados!B:AW,45,0)),0) -> 0 | M57: =IFERROR((VLOOKUP(C57,Dados!B:AW,43,0)),0) -> 0 | N57: =IFERROR((VLOOKUP(C57,Dados!B:AW,47,0)),0) -> 0 | O57: =IF(AND(J57="Parcial",N57>0,H57>1),-1,IF(AND(J57="Parcial",N57>0,H57<1.1),1,IF(AND(J57="Parcial",N57<0,H57>1.09),-1,IF(J57="Total",-1,IF(H57>1.09,1,2))))) -> 2 | P57: =IF(G57="",0,IF(H57>G57,-1,1)) -> 0 | AC57: 2 | AD57: 2 | AE57: 2 | AH57: CEN096 | AI57: =CONCATENATE(AH57,"*") -> CEN096*
B58: 58 | C58: BRU065 | D58: ZCP | E58: BRUC30 | F58: BRU065-BRUNIDORA | G58: =IFERROR(VLOOKUP(C58,#REF!,4,FALSE),"") | H58: =VLOOKUP(C58,Dados!B:AW,11,0) -> 0.52 | I58: =(VLOOKUP(C58,Dados!B:AW,48,0)) -> Confiabilidade em Crescimento | K58: =IFERROR((VLOOKUP(C58,Dados!B:AW,44,0)),0) -> 0 | L58: =IFERROR((VLOOKUP(C58,Dados!B:AW,45,0)),0) -> 0 | M58: =IFERROR((VLOOKUP(C58,Dados!B:AW,43,0)),0) -> 0 | N58: =IFERROR((VLOOKUP(C58,Dados!B:AW,47,0)),0) -> 0 | O58: =IF(AND(J58="Parcial",N58>0,H58>1),-1,IF(AND(J58="Parcial",N58>0,H58<1.1),1,IF(AND(J58="Parcial",N58<0,H58>1.09),-1,IF(J58="Total",-1,IF(H58>1.09,1,2))))) -> 2 | P58: =IF(G58="",0,IF(H58>G58,-1,1)) -> 0 | AC58: 2 | AD58: 2 | AE58: 2 | AH58: CEN046 | AI58: =CONCATENATE(AH58,"*") -> CEN046*
B59: 59 | C59: BRU066 | D59: ZCP | E59: BRUC30 | F59: BRU066-BRUNIDORA | G59: =IFERROR(VLOOKUP(C59,#REF!,4,FALSE),"") | H59: =VLOOKUP(C59,Dados!B:AW,11,0) -> 1.29 | I59: =(VLOOKUP(C59,Dados!B:AW,48,0)) -> Fase de Degradação | K59: =IFERROR((VLOOKUP(C59,Dados!B:AW,44,0)),0) -> 0 | L59: =IFERROR((VLOOKUP(C59,Dados!B:AW,45,0)),0) -> 0 | M59: =IFERROR((VLOOKUP(C59,Dados!B:AW,43,0)),0) -> 0 | N59: =IFERROR((VLOOKUP(C59,Dados!B:AW,47,0)),0) -> 0 | O59: =IF(AND(J59="Parcial",N59>0,H59>1),-1,IF(AND(J59="Parcial",N59>0,H59<1.1),1,IF(AND(J59="Parcial",N59<0,H59>1.09),-1,IF(J59="Total",-1,IF(H59>1.09,1,2))))) -> 1 | P59: =IF(G59="",0,IF(H59>G59,-1,1)) -> 0 | AC59: 2 | AD59: 2 | AE59: 2 | AH59: CEN097 | AI59: =CONCATENATE(AH59,"*") -> CEN097*
B60: 61 | C60: BRU068 | D60: ZCP | E60: BRUC31 | F60: BRU068-BRUNIDORA | G60: =IFERROR(VLOOKUP(C60,#REF!,4,FALSE),"") | H60: =VLOOKUP(C60,Dados!B:AW,11,0) -> 1 | I60: =(VLOOKUP(C60,Dados!B:AW,48,0)) -> Fase de Vida Útil | K60: =IFERROR((VLOOKUP(C60,Dados!B:AW,44,0)),0) -> 0 | L60: =IFERROR((VLOOKUP(C60,Dados!B:AW,45,0)),0) -> 0 | M60: =IFERROR((VLOOKUP(C60,Dados!B:AW,43,0)),0) -> 0 | N60: =IFERROR((VLOOKUP(C60,Dados!B:AW,47,0)),0) -> 0 | O60: =IF(AND(J60="Parcial",N60>0,H60>1),-1,IF(AND(J60="Parcial",N60>0,H60<1.1),1,IF(AND(J60="Parcial",N60<0,H60>1.09),-1,IF(J60="Total",-1,IF(H60>1.09,1,2))))) -> 2 | P60: =IF(G60="",0,IF(H60>G60,-1,1)) -> 0 | AC60: 2 | AD60: 2 | AE60: 2 | AH60: ROB015 | AI60: =CONCATENATE(AH60,"*") -> ROB015*
B61: 63 | C61: BRU070 | D61: ZCP | E61: BRUC31 | F61: BRU070-BRUNIDORA | G61: =IFERROR(VLOOKUP(C61,#REF!,4,FALSE),"") | H61: =VLOOKUP(C61,Dados!B:AW,11,0) -> 0.95 | I61: =(VLOOKUP(C61,Dados!B:AW,48,0)) -> Confiabilidade em Crescimento | K61: =IFERROR((VLOOKUP(C61,Dados!B:AW,44,0)),0) -> 0 | L61: =IFERROR((VLOOKUP(C61,Dados!B:AW,45,0)),0) -> 0 | M61: =IFERROR((VLOOKUP(C61,Dados!B:AW,43,0)),0) -> 0 | N61: =IFERROR((VLOOKUP(C61,Dados!B:AW,47,0)),0) -> 0 | O61: =IF(AND(J61="Parcial",N61>0,H61>1),-1,IF(AND(J61="Parcial",N61>0,H61<1.1),1,IF(AND(J61="Parcial",N61<0,H61>1.09),-1,IF(J61="Total",-1,IF(H61>1.09,1,2))))) -> 2 | P61: =IF(G61="",0,IF(H61>G61,-1,1)) -> 0 | AC61: 2 | AD61: 2 | AE61: 2 | AH61: BRU022 | AI61: =CONCATENATE(AH61,"*") -> BRU022*
B62: 62 | C62: BRU069 | D62: ZCP | E62: BRUC32 | F62: BRU069-BRUNIDORA | G62: =IFERROR(VLOOKUP(C62,#REF!,4,FALSE),"") | H62: =VLOOKUP(C62,Dados!B:AW,11,0) -> 1.01 | I62: =(VLOOKUP(C62,Dados!B:AW,48,0)) -> Fase de Vida Útil | K62: =IFERROR((VLOOKUP(C62,Dados!B:AW,44,0)),0) -> 0 | L62: =IFERROR((VLOOKUP(C62,Dados!B:AW,45,0)),0) -> 0 | M62: =IFERROR((VLOOKUP(C62,Dados!B:AW,43,0)),0) -> 0 | N62: =IFERROR((VLOOKUP(C62,Dados!B:AW,47,0)),0) -> 0 | O62: =IF(AND(J62="Parcial",N62>0,H62>1),-1,IF(AND(J62="Parcial",N62>0,H62<1.1),1,IF(AND(J62="Parcial",N62<0,H62>1.09),-1,IF(J62="Total",-1,IF(H62>1.09,1,2))))) -> 2 | P62: =IF(G62="",0,IF(H62>G62,-1,1)) -> 0 | AC62: 2 | AD62: 2 | AE62: 2 | AH62: CEN039 | AI62: =CONCATENATE(AH62,"*") -> CEN039*
B63: 64 | C63: BRU071 | D63: ZCP | E63: BRUC32 | F63: BRU071-BRUNIDORA | G63: =IFERROR(VLOOKUP(C63,#REF!,4,FALSE),"") | H63: =VLOOKUP(C63,Dados!B:AW,11,0) -> 1.03 | I63: =(VLOOKUP(C63,Dados!B:AW,48,0)) -> Fase de Vida Útil | K63: =IFERROR((VLOOKUP(C63,Dados!B:AW,44,0)),0) -> 0 | L63: =IFERROR((VLOOKUP(C63,Dados!B:AW,45,0)),0) -> 0 | M63: =IFERROR((VLOOKUP(C63,Dados!B:AW,43,0)),0) -> 0 | N63: =IFERROR((VLOOKUP(C63,Dados!B:AW,47,0)),0) -> 0 | O63: =IF(AND(J63="Parcial",N63>0,H63>1),-1,IF(AND(J63="Parcial",N63>0,H63<1.1),1,IF(AND(J63="Parcial",N63<0,H63>1.09),-1,IF(J63="Total",-1,IF(H63>1.09,1,2))))) -> 2 | P63: =IF(G63="",0,IF(H63>G63,-1,1)) -> 0 | AC63: 2 | AD63: 2 | AE63: 2 | AH63: MON001 | AI63: =CONCATENATE(AH63,"*") -> MON001*
B64: 305 | C64: FIL007 | D64: ZCP | E64: BRUNI1 | F64: FIL007-FILTRO ALUVIÃO | G64: =IFERROR(VLOOKUP(C64,#REF!,4,FALSE),"") | H64: =VLOOKUP(C64,Dados!B:AW,11,0) -> 1.24 | I64: =(VLOOKUP(C64,Dados!B:AW,48,0)) -> Fase de Degradação | J64: Não há | K64: =IFERROR((VLOOKUP(C64,Dados!B:AW,44,0)),0) -> 0 | L64: =IFERROR((VLOOKUP(C64,Dados!B:AW,45,0)),0) -> 0 | M64: =IFERROR((VLOOKUP(C64,Dados!B:AW,43,0)),0) -> 0 | N64: =IFERROR((VLOOKUP(C64,Dados!B:AW,47,0)),0) -> 0 | O64: =IF(AND(J64="Parcial",N64>0,H64>1),-1,IF(AND(J64="Parcial",N64>0,H64<1.1),1,IF(AND(J64="Parcial",N64<0,H64>1.09),-1,IF(J64="Total",-1,IF(H64>1.09,1,2))))) -> 1 | P64: =IF(G64="",0,IF(H64>G64,-1,1)) -> 0 | AC64: 2 | AD64: 2 | AE64: 2 | AH64: TRO011 | AI64: =CONCATENATE(AH64,"*") -> TRO011*
B65: 309 | C65: FIL058 | D65: ZCP | E65: BRUNI1 | F65: FIL058-FILTRO ALUVIÃO | G65: =IFERROR(VLOOKUP(C65,#REF!,4,FALSE),"") | H65: =VLOOKUP(C65,Dados!B:AW,11,0) -> 0.87 | I65: =(VLOOKUP(C65,Dados!B:AW,48,0)) -> Confiabilidade em Crescimento | J65: Não há | K65: =IFERROR((VLOOKUP(C65,Dados!B:AW,44,0)),0) -> 0 | L65: =IFERROR((VLOOKUP(C65,Dados!B:AW,45,0)),0) -> 0 | M65: =IFERROR((VLOOKUP(C65,Dados!B:AW,43,0)),0) -> 0 | N65: =IFERROR((VLOOKUP(C65,Dados!B:AW,47,0)),0) -> 0 | O65: =IF(AND(J65="Parcial",N65>0,H65>1),-1,IF(AND(J65="Parcial",N65>0,H65<1.1),1,IF(AND(J65="Parcial",N65<0,H65>1.09),-1,IF(J65="Total",-1,IF(H65>1.09,1,2))))) -> 2 | P65: =IF(G65="",0,IF(H65>G65,-1,1)) -> 0 | AC65: 2 | AD65: 2 | AE65: 2 | AH65: BRU027 | AI65: =CONCATENATE(AH65,"*") -> BRU027*
B66: 306 | C66: FIL023 | D66: ZCP | E66: BRUNI2 | F66: FIL023-FILTRO ALUVIÃO | G66: =IFERROR(VLOOKUP(C66,#REF!,4,FALSE),"") | H66: =VLOOKUP(C66,Dados!B:AW,11,0) -> 1.04 | I66: =(VLOOKUP(C66,Dados!B:AW,48,0)) -> Fase de Vida Útil | J66: Em análise | K66: =IFERROR((VLOOKUP(C66,Dados!B:AW,44,0)),0) -> 0 | L66: =IFERROR((VLOOKUP(C66,Dados!B:AW,45,0)),0) -> 0 | M66: =IFERROR((VLOOKUP(C66,Dados!B:AW,43,0)),0) -> 0 | N66: =IFERROR((VLOOKUP(C66,Dados!B:AW,47,0)),0) -> 0 | O66: =IF(AND(J66="Parcial",N66>0,H66>1),-1,IF(AND(J66="Parcial",N66>0,H66<1.1),1,IF(AND(J66="Parcial",N66<0,H66>1.09),-1,IF(J66="Total",-1,IF(H66>1.09,1,2))))) -> 2 | P66: =IF(G66="",0,IF(H66>G66,-1,1)) -> 0 | AC66: 2 | AD66: 2 | AE66: 2 | AH66: CEN010 | AI66: =CONCATENATE(AH66,"*") -> CEN010*
B67: 127 | C67: CEN010 | D67: UMG | E67: CARTER | F67: CEN010-CENTRO DE USINAGEM | G67: =IFERROR(VLOOKUP(C67,#REF!,4,FALSE),"") | H67: =VLOOKUP(C67,Dados!B:AW,11,0) -> 1.73 | I67: =(VLOOKUP(C67,Dados!B:AW,48,0)) -> Fase de Degradação | J67: Parcial | K67: =IFERROR((VLOOKUP(C67,Dados!B:AW,44,0)),0) -> 0 | L67: =IFERROR((VLOOKUP(C67,Dados!B:AW,45,0)),0) -> 0 | M67: =IFERROR((VLOOKUP(C67,Dados!B:AW,43,0)),0) -> 0 | N67: =IFERROR((VLOOKUP(C67,Dados!B:AW,47,0)),0) -> 0 | O67: =IF(AND(J67="Parcial",N67>0,H67>1),-1,IF(AND(J67="Parcial",N67>0,H67<1.1),1,IF(AND(J67="Parcial",N67<0,H67>1.09),-1,IF(J67="Total",-1,IF(H67>1.09,1,2))))) -> 1 | P67: =IF(G67="",0,IF(H67>G67,-1,1)) -> 0 | AC67: 2 | AD67: 2 | AE67: 2 | AH67: ROB062 | AI67: =CONCATENATE(AH67,"*") -> ROB062*
B68: 131 | C68: CEN021 | D68: UMG | E68: CARTER | F68: CEN021-CENTRO DE USINAGEM | G68: =IFERROR(VLOOKUP(C68,#REF!,4,FALSE),"") | H68: =VLOOKUP(C68,Dados!B:AW,11,0) -> 1.05 | I68: =(VLOOKUP(C68,Dados!B:AW,48,0)) -> Fase de Vida Útil | J68: Parcial | K68: =IFERROR((VLOOKUP(C68,Dados!B:AW,44,0)),0) -> 0 | L68: =IFERROR((VLOOKUP(C68,Dados!B:AW,45,0)),0) -> 0 | M68: =IFERROR((VLOOKUP(C68,Dados!B:AW,43,0)),0) -> 0 | N68: =IFERROR((VLOOKUP(C68,Dados!B:AW,47,0)),0) -> 0 | O68: =IF(AND(J68="Parcial",N68>0,H68>1),-1,IF(AND(J68="Parcial",N68>0,H68<1.1),1,IF(AND(J68="Parcial",N68<0,H68>1.09),-1,IF(J68="Total",-1,IF(H68>1.09,1,2))))) -> 2 | P68: =IF(G68="",0,IF(H68>G68,-1,1)) -> 0 | AC68: 2 | AD68: 2 | AE68: 2 | AH68: TOR033 | AI68: =CONCATENATE(AH68,"*") -> TOR033*
B69: 161 | C69: CEN051 | D69: UMG | E69: CARTER | F69: CEN051-CENTRO DE USINAGEM | G69: =IFERROR(VLOOKUP(C69,#REF!,4,FALSE),"") | H69: =VLOOKUP(C69,Dados!B:AW,11,0) -> 1.79 | I69: =(VLOOKUP(C69,Dados!B:AW,48,0)) -> Fase de Degradação | J69: Não há | K69: =IFERROR((VLOOKUP(C69,Dados!B:AW,44,0)),0) -> 0 | L69: =IFERROR((VLOOKUP(C69,Dados!B:AW,45,0)),0) -> 0 | M69: =IFERROR((VLOOKUP(C69,Dados!B:AW,43,0)),0) -> 0 | N69: =IFERROR((VLOOKUP(C69,Dados!B:AW,47,0)),0) -> 0 | O69: =IF(AND(J69="Parcial",N69>0,H69>1),-1,IF(AND(J69="Parcial",N69>0,H69<1.1),1,IF(AND(J69="Parcial",N69<0,H69>1.09),-1,IF(J69="Total",-1,IF(H69>1.09,1,2))))) -> 1 | P69: =IF(G69="",0,IF(H69>G69,-1,1)) -> 0 | AC69: 2 | AD69: 2 | AE69: 2 | AH69: BRU024 | AI69: =CONCATENATE(AH69,"*") -> BRU024*
B70: 163 | C70: CEN053 | D70: UMG | E70: CARTER | F70: CEN053-CENTRO DE USINAGEM | G70: =IFERROR(VLOOKUP(C70,#REF!,4,FALSE),"") | H70: =VLOOKUP(C70,Dados!B:AW,11,0) -> 1.51 | I70: =(VLOOKUP(C70,Dados!B:AW,48,0)) -> Fase de Degradação | J70: Não há | K70: =IFERROR((VLOOKUP(C70,Dados!B:AW,44,0)),0) -> 0 | L70: =IFERROR((VLOOKUP(C70,Dados!B:AW,45,0)),0) -> 0 | M70: =IFERROR((VLOOKUP(C70,Dados!B:AW,43,0)),0) -> 0 | N70: =IFERROR((VLOOKUP(C70,Dados!B:AW,47,0)),0) -> 0 | O70: =IF(AND(J70="Parcial",N70>0,H70>1),-1,IF(AND(J70="Parcial",N70>0,H70<1.1),1,IF(AND(J70="Parcial",N70<0,H70>1.09),-1,IF(J70="Total",-1,IF(H70>1.09,1,2))))) -> 1 | P70: =IF(G70="",0,IF(H70>G70,-1,1)) -> 0 | AC70: 2 | AD70: 2 | AE70: 2 | AH70: CEN075 | AI70: =CONCATENATE(AH70,"*") -> CEN075*
B71: 164 | C71: CEN054 | D71: UMG | E71: CARTER | F71: CEN054-CENTRO DE USINAGEM | G71: =IFERROR(VLOOKUP(C71,#REF!,4,FALSE),"") | H71: =VLOOKUP(C71,Dados!B:AW,11,0) -> 1.27 | I71: =(VLOOKUP(C71,Dados!B:AW,48,0)) -> Fase de Degradação | J71: Não há | K71: =IFERROR((VLOOKUP(C71,Dados!B:AW,44,0)),0) -> 0 | L71: =IFERROR((VLOOKUP(C71,Dados!B:AW,45,0)),0) -> 0 | M71: =IFERROR((VLOOKUP(C71,Dados!B:AW,43,0)),0) -> 0 | N71: =IFERROR((VLOOKUP(C71,Dados!B:AW,47,0)),0) -> 0 | O71: =IF(AND(J71="Parcial",N71>0,H71>1),-1,IF(AND(J71="Parcial",N71>0,H71<1.1),1,IF(AND(J71="Parcial",N71<0,H71>1.09),-1,IF(J71="Total",-1,IF(H71>1.09,1,2))))) -> 1 | P71: =IF(G71="",0,IF(H71>G71,-1,1)) -> 0 | AC71: 2 | AD71: 2 | AE71: 2 | AH71: FOR045 | AI71: =CONCATENATE(AH71,"*") -> FOR045*
B72: 169 | C72: CEN059 | D72: UMG | E72: CARTER | F72: CEN059-CENTRO DE USINAGEM | G72: =IFERROR(VLOOKUP(C72,#REF!,4,FALSE),"") | H72: =VLOOKUP(C72,Dados!B:AW,11,0) -> 1.54 | I72: =(VLOOKUP(C72,Dados!B:AW,48,0)) -> Fase de Degradação | J72: Não há | K72: =IFERROR((VLOOKUP(C72,Dados!B:AW,44,0)),0) -> 0 | L72: =IFERROR((VLOOKUP(C72,Dados!B:AW,45,0)),0) -> 0 | M72: =IFERROR((VLOOKUP(C72,Dados!B:AW,43,0)),0) -> 0 | N72: =IFERROR((VLOOKUP(C72,Dados!B:AW,47,0)),0) -> 0 | O72: =IF(AND(J72="Parcial",N72>0,H72>1),-1,IF(AND(J72="Parcial",N72>0,H72<1.1),1,IF(AND(J72="Parcial",N72<0,H72>1.09),-1,IF(J72="Total",-1,IF(H72>1.09,1,2))))) -> 1 | P72: =IF(G72="",0,IF(H72>G72,-1,1)) -> 0 | AC72: 2 | AD72: 2 | AE72: 2 | AH72: ROB058 | AI72: =CONCATENATE(AH72,"*") -> ROB058*
B73: 171 | C73: CEN061 | D73: UMG | E73: CARTER | F73: CEN061-CENTRO DE USINAGEM | G73: =IFERROR(VLOOKUP(C73,#REF!,4,FALSE),"") | H73: =VLOOKUP(C73,Dados!B:AW,11,0) -> 1.63 | I73: =(VLOOKUP(C73,Dados!B:AW,48,0)) -> Fase de Degradação | J73: Não há | K73: =IFERROR((VLOOKUP(C73,Dados!B:AW,44,0)),0) -> 0 | L73: =IFERROR((VLOOKUP(C73,Dados!B:AW,45,0)),0) -> 0 | M73: =IFERROR((VLOOKUP(C73,Dados!B:AW,43,0)),0) -> 0 | N73: =IFERROR((VLOOKUP(C73,Dados!B:AW,47,0)),0) -> 0 | O73: =IF(AND(J73="Parcial",N73>0,H73>1),-1,IF(AND(J73="Parcial",N73>0,H73<1.1),1,IF(AND(J73="Parcial",N73<0,H73>1.09),-1,IF(J73="Total",-1,IF(H73>1.09,1,2))))) -> 1 | P73: =IF(G73="",0,IF(H73>G73,-1,1)) -> 0 | AC73: 2 | AD73: 2 | AE73: 2 | AH73: CEN030 | AI73: =CONCATENATE(AH73,"*") -> CEN030*
B74: 200 | C74: CEN092 | D74: UMG | E74: CARTL4 | F74: CEN092-CENTRO DE USINAGEM | G74: =IFERROR(VLOOKUP(C74,#REF!,4,FALSE),"") | H74: =VLOOKUP(C74,Dados!B:AW,11,0) -> 0.95 | I74: =(VLOOKUP(C74,Dados!B:AW,48,0)) -> Confiabilidade em Crescimento | J74: Não há | K74: =IFERROR((VLOOKUP(C74,Dados!B:AW,44,0)),0) -> 0 | L74: =IFERROR((VLOOKUP(C74,Dados!B:AW,45,0)),0) -> 0 | M74: =IFERROR((VLOOKUP(C74,Dados!B:AW,43,0)),0) -> 0 | N74: =IFERROR((VLOOKUP(C74,Dados!B:AW,47,0)),0) -> 0 | O74: =IF(AND(J74="Parcial",N74>0,H74>1),-1,IF(AND(J74="Parcial",N74>0,H74<1.1),1,IF(AND(J74="Parcial",N74<0,H74>1.09),-1,IF(J74="Total",-1,IF(H74>1.09,1,2))))) -> 2 | P74: =IF(G74="",0,IF(H74>G74,-1,1)) -> 0
B75: 202 | C75: CEN094 | D75: UMG | E75: CARTL4 | F75: CEN094-CENTRO DE USINAGEM | G75: =IFERROR(VLOOKUP(C75,#REF!,4,FALSE),"") | H75: =VLOOKUP(C75,Dados!B:AW,11,0) -> 1.84 | I75: =(VLOOKUP(C75,Dados!B:AW,48,0)) -> Fase de Degradação | J75: Não há | K75: =IFERROR((VLOOKUP(C75,Dados!B:AW,44,0)),0) -> 0 | L75: =IFERROR((VLOOKUP(C75,Dados!B:AW,45,0)),0) -> 0 | M75: =IFERROR((VLOOKUP(C75,Dados!B:AW,43,0)),0) -> 0 | N75: =IFERROR((VLOOKUP(C75,Dados!B:AW,47,0)),0) -> 0 | O75: =IF(AND(J75="Parcial",N75>0,H75>1),-1,IF(AND(J75="Parcial",N75>0,H75<1.1),1,IF(AND(J75="Parcial",N75<0,H75>1.09),-1,IF(J75="Total",-1,IF(H75>1.09,1,2))))) -> 1 | P75: =IF(G75="",0,IF(H75>G75,-1,1)) -> 0 | AC75: 2 | AD75: 2 | AE75: 2 | AH75: CEN074 | AI75: =CONCATENATE(AH75,"*") -> CEN074*
B76: 203 | C76: CEN095 | D76: UMG | E76: CARTL4 | F76: CEN095-CENTRO DE USINAGEM | G76: =IFERROR(VLOOKUP(C76,#REF!,4,FALSE),"") | H76: =VLOOKUP(C76,Dados!B:AW,11,0) -> 1.42 | I76: =(VLOOKUP(C76,Dados!B:AW,48,0)) -> Fase de Degradação | J76: Não há | K76: =IFERROR((VLOOKUP(C76,Dados!B:AW,44,0)),0) -> 0 | L76: =IFERROR((VLOOKUP(C76,Dados!B:AW,45,0)),0) -> 0 | M76: =IFERROR((VLOOKUP(C76,Dados!B:AW,43,0)),0) -> 0 | N76: =IFERROR((VLOOKUP(C76,Dados!B:AW,47,0)),0) -> 0 | O76: =IF(AND(J76="Parcial",N76>0,H76>1),-1,IF(AND(J76="Parcial",N76>0,H76<1.1),1,IF(AND(J76="Parcial",N76<0,H76>1.09),-1,IF(J76="Total",-1,IF(H76>1.09,1,2))))) -> 1 | P76: =IF(G76="",0,IF(H76>G76,-1,1)) -> 0 | AC76: 2 | AD76: 2 | AE76: 2 | AH76: ELE014 | AI76: =CONCATENATE(AH76,"*") -> ELE014*
B77: 204 | C77: CEN096 | D77: UMG | E77: CARTL4 | F77: CEN096-CENTRO DE USINAGEM | G77: =IFERROR(VLOOKUP(C77,#REF!,4,FALSE),"") | H77: =VLOOKUP(C77,Dados!B:AW,11,0) -> 1.53 | I77: =(VLOOKUP(C77,Dados!B:AW,48,0)) -> Fase de Degradação | J77: Não há | K77: =IFERROR((VLOOKUP(C77,Dados!B:AW,44,0)),0) -> 0 | L77: =IFERROR((VLOOKUP(C77,Dados!B:AW,45,0)),0) -> 0 | M77: =IFERROR((VLOOKUP(C77,Dados!B:AW,43,0)),0) -> 0 | N77: =IFERROR((VLOOKUP(C77,Dados!B:AW,47,0)),0) -> 0 | O77: =IF(AND(J77="Parcial",N77>0,H77>1),-1,IF(AND(J77="Parcial",N77>0,H77<1.1),1,IF(AND(J77="Parcial",N77<0,H77>1.09),-1,IF(J77="Total",-1,IF(H77>1.09,1,2))))) -> 1 | P77: =IF(G77="",0,IF(H77>G77,-1,1)) -> 0 | AC77: 2 | AD77: 2 | AE77: 2 | AH77: GRV009 | AI77: =CONCATENATE(AH77,"*") -> GRV009*
B78: 205 | C78: CEN097 | D78: UMG | E78: CARTL4 | F78: CEN097-CENTRO DE USINAGEM | G78: =IFERROR(VLOOKUP(C78,#REF!,4,FALSE),"") | H78: =VLOOKUP(C78,Dados!B:AW,11,0) -> 1.64 | I78: =(VLOOKUP(C78,Dados!B:AW,48,0)) -> Fase de Degradação | J78: Não há | K78: =IFERROR((VLOOKUP(C78,Dados!B:AW,44,0)),0) -> 0 | L78: =IFERROR((VLOOKUP(C78,Dados!B:AW,45,0)),0) -> 0 | M78: =IFERROR((VLOOKUP(C78,Dados!B:AW,43,0)),0) -> 0 | N78: =IFERROR((VLOOKUP(C78,Dados!B:AW,47,0)),0) -> 0 | O78: =IF(AND(J78="Parcial",N78>0,H78>1),-1,IF(AND(J78="Parcial",N78>0,H78<1.1),1,IF(AND(J78="Parcial",N78<0,H78>1.09),-1,IF(J78="Total",-1,IF(H78>1.09,1,2))))) -> 1 | P78: =IF(G78="",0,IF(H78>G78,-1,1)) -> 0 | AC78: 2 | AD78: 2 | AE78: 2 | AH78: ROB065 | AI78: =CONCATENATE(AH78,"*") -> ROB065*
B79: 227 | C79: CEN130 | D79: UMG | E79: CARTL4 | F79: CEN130-CENTRO DE USINAGEM | G79: =IFERROR(VLOOKUP(C79,#REF!,4,FALSE),"") | H79: =VLOOKUP(C79,Dados!B:AW,11,0) -> 0.72 | I79: =(VLOOKUP(C79,Dados!B:AW,48,0)) -> Confiabilidade em Crescimento | J79: Não há | K79: =IFERROR((VLOOKUP(C79,Dados!B:AW,44,0)),0) -> 0 | L79: =IFERROR((VLOOKUP(C79,Dados!B:AW,45,0)),0) -> 0 | M79: =IFERROR((VLOOKUP(C79,Dados!B:AW,43,0)),0) -> 0 | N79: =IFERROR((VLOOKUP(C79,Dados!B:AW,47,0)),0) -> 0 | O79: =IF(AND(J79="Parcial",N79>0,H79>1),-1,IF(AND(J79="Parcial",N79>0,H79<1.1),1,IF(AND(J79="Parcial",N79<0,H79>1.09),-1,IF(J79="Total",-1,IF(H79>1.09,1,2))))) -> 2 | P79: =IF(G79="",0,IF(H79>G79,-1,1)) -> 0 | AC79: 2 | AD79: 2 | AE79: 1 | AH79: RET023 | AI79: =CONCATENATE(AH79,"*") -> RET023*
B80: 228 | C80: CEN131 | D80: UMG | E80: CARTL4 | F80: CEN131-CENTRO DE USINAGEM | G80: =IFERROR(VLOOKUP(C80,#REF!,4,FALSE),"") | H80: =VLOOKUP(C80,Dados!B:AW,11,0) -> 1.34 | I80: =(VLOOKUP(C80,Dados!B:AW,48,0)) -> Fase de Degradação | J80: Não há | K80: =IFERROR((VLOOKUP(C80,Dados!B:AW,44,0)),0) -> 0 | L80: =IFERROR((VLOOKUP(C80,Dados!B:AW,45,0)),0) -> 0 | M80: =IFERROR((VLOOKUP(C80,Dados!B:AW,43,0)),0) -> 0 | N80: =IFERROR((VLOOKUP(C80,Dados!B:AW,47,0)),0) -> 0 | O80: =IF(AND(J80="Parcial",N80>0,H80>1),-1,IF(AND(J80="Parcial",N80>0,H80<1.1),1,IF(AND(J80="Parcial",N80<0,H80>1.09),-1,IF(J80="Total",-1,IF(H80>1.09,1,2))))) -> 1 | P80: =IF(G80="",0,IF(H80>G80,-1,1)) -> 0 | AC80: 2 | AD80: 2 | AE80: 1 | AH80: ROB075 | AI80: =CONCATENATE(AH80,"*") -> ROB075*
B81: 229 | C81: CEN132 | D81: UMG | E81: CARTL4 | F81: CEN132-CENTRO DE USINAGEM | G81: =IFERROR(VLOOKUP(C81,#REF!,4,FALSE),"") | H81: =VLOOKUP(C81,Dados!B:AW,11,0) -> 0.55 | I81: =(VLOOKUP(C81,Dados!B:AW,48,0)) -> Confiabilidade em Crescimento | J81: Não há | K81: =IFERROR((VLOOKUP(C81,Dados!B:AW,44,0)),0) -> 0 | L81: =IFERROR((VLOOKUP(C81,Dados!B:AW,45,0)),0) -> 0 | M81: =IFERROR((VLOOKUP(C81,Dados!B:AW,43,0)),0) -> 0 | N81: =IFERROR((VLOOKUP(C81,Dados!B:AW,47,0)),0) -> 0 | O81: =IF(AND(J81="Parcial",N81>0,H81>1),-1,IF(AND(J81="Parcial",N81>0,H81<1.1),1,IF(AND(J81="Parcial",N81<0,H81>1.09),-1,IF(J81="Total",-1,IF(H81>1.09,1,2))))) -> 2 | P81: =IF(G81="",0,IF(H81>G81,-1,1)) -> 0 | AC81: 2 | AD81: 2 | AE81: 1 | AH81: CEN028 | AI81: =CONCATENATE(AH81,"*") -> CEN028*
B82: 230 | C82: CEN133 | D82: UMG | E82: CARTL4 | F82: CEN133-CENTRO DE USINAGEM | G82: =IFERROR(VLOOKUP(C82,#REF!,4,FALSE),"") | H82: =VLOOKUP(C82,Dados!B:AW,11,0) -> 0.75 | I82: =(VLOOKUP(C82,Dados!B:AW,48,0)) -> Confiabilidade em Crescimento | J82: Não há | K82: =IFERROR((VLOOKUP(C82,Dados!B:AW,44,0)),0) -> 0 | L82: =IFERROR((VLOOKUP(C82,Dados!B:AW,45,0)),0) -> 0 | M82: =IFERROR((VLOOKUP(C82,Dados!B:AW,43,0)),0) -> 0 | N82: =IFERROR((VLOOKUP(C82,Dados!B:AW,47,0)),0) -> 0 | O82: =IF(AND(J82="Parcial",N82>0,H82>1),-1,IF(AND(J82="Parcial",N82>0,H82<1.1),1,IF(AND(J82="Parcial",N82<0,H82>1.09),-1,IF(J82="Total",-1,IF(H82>1.09,1,2))))) -> 2 | P82: =IF(G82="",0,IF(H82>G82,-1,1)) -> 0 | AC82: 2 | AD82: 2 | AE82: 1 | AH82: CEN029 | AI82: =CONCATENATE(AH82,"*") -> CEN029*
B83: 231 | C83: CEN134 | D83: UMG | E83: CARTL4 | F83: CEN134-CENTRO DE USINAGEM | G83: =IFERROR(VLOOKUP(C83,#REF!,4,FALSE),"") | H83: =VLOOKUP(C83,Dados!B:AW,11,0) -> 0.9 | I83: =(VLOOKUP(C83,Dados!B:AW,48,0)) -> Confiabilidade em Crescimento | J83: Não há | K83: =IFERROR((VLOOKUP(C83,Dados!B:AW,44,0)),0) -> 0 | L83: =IFERROR((VLOOKUP(C83,Dados!B:AW,45,0)),0) -> 0 | M83: =IFERROR((VLOOKUP(C83,Dados!B:AW,43,0)),0) -> 0 | N83: =IFERROR((VLOOKUP(C83,Dados!B:AW,47,0)),0) -> 0 | O83: =IF(AND(J83="Parcial",N83>0,H83>1),-1,IF(AND(J83="Parcial",N83>0,H83<1.1),1,IF(AND(J83="Parcial",N83<0,H83>1.09),-1,IF(J83="Total",-1,IF(H83>1.09,1,2))))) -> 2 | P83: =IF(G83="",0,IF(H83>G83,-1,1)) -> 0 | AC83: 2 | AD83: 2 | AE83: 1 | AH83: RET033 | AI83: =CONCATENATE(AH83,"*") -> RET033*
B84: 232 | C84: CEN135 | D84: UMG | E84: CARTL4 | F84: CEN135-CENTRO DE USINAGEM | G84: =IFERROR(VLOOKUP(C84,#REF!,4,FALSE),"") | H84: =VLOOKUP(C84,Dados!B:AW,11,0) -> 0 | I84: =(VLOOKUP(C84,Dados!B:AW,48,0)) -> 0 | J84: Não há | K84: =IFERROR((VLOOKUP(C84,Dados!B:AW,44,0)),0) -> 0 | L84: =IFERROR((VLOOKUP(C84,Dados!B:AW,45,0)),0) -> 0 | M84: =IFERROR((VLOOKUP(C84,Dados!B:AW,43,0)),0) -> 0 | N84: =IFERROR((VLOOKUP(C84,Dados!B:AW,47,0)),0) -> 0 | O84: =IF(AND(J84="Parcial",N84>0,H84>1),-1,IF(AND(J84="Parcial",N84>0,H84<1.1),1,IF(AND(J84="Parcial",N84<0,H84>1.09),-1,IF(J84="Total",-1,IF(H84>1.09,1,2))))) -> 2 | P84: =IF(G84="",0,IF(H84>G84,-1,1)) -> 0 | AC84: 2 | AD84: 2 | AE84: 1 | AH84: BRU030 | AI84: =CONCATENATE(AH84,"*") -> BRU030*
B85: 233 | C85: CEN136 | D85: UMG | E85: CARTL4 | F85: CEN136-CENTRO DE USINAGEM | G85: =IFERROR(VLOOKUP(C85,#REF!,4,FALSE),"") | H85: =VLOOKUP(C85,Dados!B:AW,11,0) -> 0 | I85: =(VLOOKUP(C85,Dados!B:AW,48,0)) -> 0 | J85: Não há | K85: =IFERROR((VLOOKUP(C85,Dados!B:AW,44,0)),0) -> 0 | L85: =IFERROR((VLOOKUP(C85,Dados!B:AW,45,0)),0) -> 0 | M85: =IFERROR((VLOOKUP(C85,Dados!B:AW,43,0)),0) -> 0 | N85: =IFERROR((VLOOKUP(C85,Dados!B:AW,47,0)),0) -> 0 | O85: =IF(AND(J85="Parcial",N85>0,H85>1),-1,IF(AND(J85="Parcial",N85>0,H85<1.1),1,IF(AND(J85="Parcial",N85<0,H85>1.09),-1,IF(J85="Total",-1,IF(H85>1.09,1,2))))) -> 2 | P85: =IF(G85="",0,IF(H85>G85,-1,1)) -> 0 | AC85: 2 | AD85: 2 | AE85: 2 | AH85: FOR001 | AI85: =CONCATENATE(AH85,"*") -> FOR001*
B86: 128 | C86: CEN017 | D86: ZCH | E86: CEN017 | F86: =VLOOKUP(C86,[9]Dados!B:C,2,0) -> CEN017-CENTRO DE USINAGEM | G86: =IFERROR(VLOOKUP(C86,#REF!,4,FALSE),"") | H86: =VLOOKUP(C86,Dados!B:AW,11,0) -> 1.42 | I86: =(VLOOKUP(C86,Dados!B:AW,48,0)) -> Fase de Degradação | J86: Não há | K86: =IFERROR((VLOOKUP(C86,Dados!B:AW,44,0)),0) -> 0 | L86: =IFERROR((VLOOKUP(C86,Dados!B:AW,45,0)),0) -> 0 | M86: =IFERROR((VLOOKUP(C86,Dados!B:AW,43,0)),0) -> 0 | N86: =IFERROR((VLOOKUP(C86,Dados!B:AW,47,0)),0) -> 0 | O86: =IF(AND(J86="Parcial",N86>0,H86>1),-1,IF(AND(J86="Parcial",N86>0,H86<1.1),1,IF(AND(J86="Parcial",N86<0,H86>1.09),-1,IF(J86="Total",-1,IF(H86>1.09,1,2))))) -> 1 | P86: =IF(G86="",0,IF(H86>G86,-1,1)) -> 0 | AC86: 2 | AD86: 2 | AE86: 2 | AH86: MOD022 | AI86: =CONCATENATE(AH86,"*") -> MOD022*
B87: 129 | C87: CEN018 | D87: ZCH | E87: CEN018 | F87: =VLOOKUP(C87,[9]Dados!B:C,2,0) -> CEN018-CENTRO DE USINAGEM | G87: =IFERROR(VLOOKUP(C87,#REF!,4,FALSE),"") | H87: =VLOOKUP(C87,Dados!B:AW,11,0) -> 1.45 | I87: =(VLOOKUP(C87,Dados!B:AW,48,0)) -> Fase de Degradação | J87: Não há | K87: =IFERROR((VLOOKUP(C87,Dados!B:AW,44,0)),0) -> 0 | L87: =IFERROR((VLOOKUP(C87,Dados!B:AW,45,0)),0) -> 0 | M87: =IFERROR((VLOOKUP(C87,Dados!B:AW,43,0)),0) -> 0 | N87: =IFERROR((VLOOKUP(C87,Dados!B:AW,47,0)),0) -> 0 | O87: =IF(AND(J87="Parcial",N87>0,H87>1),-1,IF(AND(J87="Parcial",N87>0,H87<1.1),1,IF(AND(J87="Parcial",N87<0,H87>1.09),-1,IF(J87="Total",-1,IF(H87>1.09,1,2))))) -> 1 | P87: =IF(G87="",0,IF(H87>G87,-1,1)) -> 0 | AC87: 2 | AD87: 2 | AE87: 1 | AH87: INJ002 | AI87: =CONCATENATE(AH87,"*") -> INJ002*
B88: 130 | C88: CEN019 | D88: ZCH | E88: CEN019 | F88: =VLOOKUP(C88,[9]Dados!B:C,2,0) -> CEN019-CENTRO DE USINAGEM | G88: =IFERROR(VLOOKUP(C88,#REF!,4,FALSE),"") | H88: =VLOOKUP(C88,Dados!B:AW,11,0) -> 1.93 | I88: =(VLOOKUP(C88,Dados!B:AW,48,0)) -> Fase de Degradação | J88: Não há | K88: =IFERROR((VLOOKUP(C88,Dados!B:AW,44,0)),0) -> 0 | L88: =IFERROR((VLOOKUP(C88,Dados!B:AW,45,0)),0) -> 0 | M88: =IFERROR((VLOOKUP(C88,Dados!B:AW,43,0)),0) -> 0 | N88: =IFERROR((VLOOKUP(C88,Dados!B:AW,47,0)),0) -> 0 | O88: =IF(AND(J88="Parcial",N88>0,H88>1),-1,IF(AND(J88="Parcial",N88>0,H88<1.1),1,IF(AND(J88="Parcial",N88<0,H88>1.09),-1,IF(J88="Total",-1,IF(H88>1.09,1,2))))) -> 1 | P88: =IF(G88="",0,IF(H88>G88,-1,1)) -> 0 | AC88: 2 | AD88: 2 | AE88: 2 | AH88: INJ017 | AI88: =CONCATENATE(AH88,"*") -> INJ017*
B89: 132 | C89: CEN022 | D89: ZCH | E89: CEN022 | F89: CEN022-CENTRO DE USINAGEM | G89: =IFERROR(VLOOKUP(C89,#REF!,4,FALSE),"") | H89: =VLOOKUP(C89,Dados!B:AW,11,0) -> 1.23 | I89: =(VLOOKUP(C89,Dados!B:AW,48,0)) -> Fase de Degradação | J89: Não há | K89: =IFERROR((VLOOKUP(C89,Dados!B:AW,44,0)),0) -> 0 | L89: =IFERROR((VLOOKUP(C89,Dados!B:AW,45,0)),0) -> 0 | M89: =IFERROR((VLOOKUP(C89,Dados!B:AW,43,0)),0) -> 0 | N89: =IFERROR((VLOOKUP(C89,Dados!B:AW,47,0)),0) -> 0 | O89: =IF(AND(J89="Parcial",N89>0,H89>1),-1,IF(AND(J89="Parcial",N89>0,H89<1.1),1,IF(AND(J89="Parcial",N89<0,H89>1.09),-1,IF(J89="Total",-1,IF(H89>1.09,1,2))))) -> 1 | P89: =IF(G89="",0,IF(H89>G89,-1,1)) -> 0 | AC89: 2 | AD89: 2 | AE89: 2 | AH89: INJ034 | AI89: =CONCATENATE(AH89,"*") -> INJ034*
B90: 133 | C90: CEN023 | D90: ZCH | E90: CEN023 | F90: CEN023-CENTRO DE USINAGEM | G90: =IFERROR(VLOOKUP(C90,#REF!,4,FALSE),"") | H90: =VLOOKUP(C90,Dados!B:AW,11,0) -> 1.41 | I90: =(VLOOKUP(C90,Dados!B:AW,48,0)) -> Fase de Degradação | J90: Não há | K90: =IFERROR((VLOOKUP(C90,Dados!B:AW,44,0)),0) -> 0 | L90: =IFERROR((VLOOKUP(C90,Dados!B:AW,45,0)),0) -> 0 | M90: =IFERROR((VLOOKUP(C90,Dados!B:AW,43,0)),0) -> 0 | N90: =IFERROR((VLOOKUP(C90,Dados!B:AW,47,0)),0) -> 0 | O90: =IF(AND(J90="Parcial",N90>0,H90>1),-1,IF(AND(J90="Parcial",N90>0,H90<1.1),1,IF(AND(J90="Parcial",N90<0,H90>1.09),-1,IF(J90="Total",-1,IF(H90>1.09,1,2))))) -> 1 | P90: =IF(G90="",0,IF(H90>G90,-1,1)) -> 0 | AC90: 2 | AD90: 2 | AE90: 2 | AH90: CEN045 | AI90: =CONCATENATE(AH90,"*") -> CEN045*
B91: 134 | C91: CEN024 | D91: ZCH | E91: CEN024 | F91: CEN024-CENTRO DE USINAGEM | G91: =IFERROR(VLOOKUP(C91,#REF!,4,FALSE),"") | H91: =VLOOKUP(C91,Dados!B:AW,11,0) -> 1.4 | I91: =(VLOOKUP(C91,Dados!B:AW,48,0)) -> Fase de Degradação | J91: Não há | K91: =IFERROR((VLOOKUP(C91,Dados!B:AW,44,0)),0) -> 0 | L91: =IFERROR((VLOOKUP(C91,Dados!B:AW,45,0)),0) -> 0 | M91: =IFERROR((VLOOKUP(C91,Dados!B:AW,43,0)),0) -> 0 | N91: =IFERROR((VLOOKUP(C91,Dados!B:AW,47,0)),0) -> 0 | O91: =IF(AND(J91="Parcial",N91>0,H91>1),-1,IF(AND(J91="Parcial",N91>0,H91<1.1),1,IF(AND(J91="Parcial",N91<0,H91>1.09),-1,IF(J91="Total",-1,IF(H91>1.09,1,2))))) -> 1 | P91: =IF(G91="",0,IF(H91>G91,-1,1)) -> 0 | AC91: 2 | AD91: 2 | AE91: 2 | AH91: ELE017 | AI91: =CONCATENATE(AH91,"*") -> ELE017*
B92: 135 | C92: CEN025 | D92: ZCH | E92: CEN025 | F92: CEN025-CENTRO DE USINAGEM | G92: =IFERROR(VLOOKUP(C92,#REF!,4,FALSE),"") | H92: =VLOOKUP(C92,Dados!B:AW,11,0) -> 1.52 | I92: =(VLOOKUP(C92,Dados!B:AW,48,0)) -> Fase de Degradação | J92: Não há | K92: =IFERROR((VLOOKUP(C92,Dados!B:AW,44,0)),0) -> 0 | L92: =IFERROR((VLOOKUP(C92,Dados!B:AW,45,0)),0) -> 0 | M92: =IFERROR((VLOOKUP(C92,Dados!B:AW,43,0)),0) -> 0 | N92: =IFERROR((VLOOKUP(C92,Dados!B:AW,47,0)),0) -> 0 | O92: =IF(AND(J92="Parcial",N92>0,H92>1),-1,IF(AND(J92="Parcial",N92>0,H92<1.1),1,IF(AND(J92="Parcial",N92<0,H92>1.09),-1,IF(J92="Total",-1,IF(H92>1.09,1,2))))) -> 1 | P92: =IF(G92="",0,IF(H92>G92,-1,1)) -> 0 | AC92: 2 | AD92: 2 | AE92: 2 | AH92: CEN042 | AI92: =CONCATENATE(AH92,"*") -> CEN042*
B93: 571 | C93: ROB045 | D93: ZCH | E93: CEN025 | F93: ROB045-ROBÔ | G93: =IFERROR(VLOOKUP(C93,#REF!,4,FALSE),"") | H93: =VLOOKUP(C93,Dados!B:AW,11,0) -> 1.21 | I93: =(VLOOKUP(C93,Dados!B:AW,48,0)) -> Fase de Degradação | J93: Em análise | K93: =IFERROR((VLOOKUP(C93,Dados!B:AW,44,0)),0) -> 0 | L93: =IFERROR((VLOOKUP(C93,Dados!B:AW,45,0)),0) -> 0 | M93: =IFERROR((VLOOKUP(C93,Dados!B:AW,43,0)),0) -> 0 | N93: =IFERROR((VLOOKUP(C93,Dados!B:AW,47,0)),0) -> 0 | O93: =IF(AND(J93="Parcial",N93>0,H93>1),-1,IF(AND(J93="Parcial",N93>0,H93<1.1),1,IF(AND(J93="Parcial",N93<0,H93>1.09),-1,IF(J93="Total",-1,IF(H93>1.09,1,2))))) -> 1 | P93: =IF(G93="",0,IF(H93>G93,-1,1)) -> 0 | AC93: 2 | AD93: 2 | AE93: 2 | AH93: CEN041 | AI93: =CONCATENATE(AH93,"*") -> CEN041*
B94: 136 | C94: CEN026 | D94: ZCH | E94: CEN026 | F94: CEN026-CENTRO DE USINAGEM | G94: =IFERROR(VLOOKUP(C94,#REF!,4,FALSE),"") | H94: =VLOOKUP(C94,Dados!B:AW,11,0) -> 1.53 | I94: =(VLOOKUP(C94,Dados!B:AW,48,0)) -> Fase de Degradação | J94: Não há | K94: =IFERROR((VLOOKUP(C94,Dados!B:AW,44,0)),0) -> 0 | L94: =IFERROR((VLOOKUP(C94,Dados!B:AW,45,0)),0) -> 0 | M94: =IFERROR((VLOOKUP(C94,Dados!B:AW,43,0)),0) -> 0 | N94: =IFERROR((VLOOKUP(C94,Dados!B:AW,47,0)),0) -> 0 | O94: =IF(AND(J94="Parcial",N94>0,H94>1),-1,IF(AND(J94="Parcial",N94>0,H94<1.1),1,IF(AND(J94="Parcial",N94<0,H94>1.09),-1,IF(J94="Total",-1,IF(H94>1.09,1,2))))) -> 1 | P94: =IF(G94="",0,IF(H94>G94,-1,1)) -> 0 | AC94: 2 | AD94: 2 | AE94: 2 | AH94: TOR014 | AI94: =CONCATENATE(AH94,"*") -> TOR014*
B95: 572 | C95: ROB046 | D95: ZCH | E95: CEN026 | F95: ROB046-ROBÔ | G95: =IFERROR(VLOOKUP(C95,#REF!,4,FALSE),"") | H95: =VLOOKUP(C95,Dados!B:AW,11,0) -> 1.29 | I95: =(VLOOKUP(C95,Dados!B:AW,48,0)) -> Fase de Degradação | J95: Em análise | K95: =IFERROR((VLOOKUP(C95,Dados!B:AW,44,0)),0) -> 0 | L95: =IFERROR((VLOOKUP(C95,Dados!B:AW,45,0)),0) -> 0 | M95: =IFERROR((VLOOKUP(C95,Dados!B:AW,43,0)),0) -> 0 | N95: =IFERROR((VLOOKUP(C95,Dados!B:AW,47,0)),0) -> 0 | O95: =IF(AND(J95="Parcial",N95>0,H95>1),-1,IF(AND(J95="Parcial",N95>0,H95<1.1),1,IF(AND(J95="Parcial",N95<0,H95>1.09),-1,IF(J95="Total",-1,IF(H95>1.09,1,2))))) -> 1 | P95: =IF(G95="",0,IF(H95>G95,-1,1)) -> 0 | AC95: 2 | AD95: 2 | AE95: 2 | AH95: MAC002 | AI95: =CONCATENATE(AH95,"*") -> MAC002*
B96: 137 | C96: CEN027 | D96: ZCH | E96: CEN027 | F96: CEN027-CENTRO DE USINAGEM | G96: =IFERROR(VLOOKUP(C96,#REF!,4,FALSE),"") | H96: =VLOOKUP(C96,Dados!B:AW,11,0) -> 1.56 | I96: =(VLOOKUP(C96,Dados!B:AW,48,0)) -> Fase de Degradação | J96: Não há | K96: =IFERROR((VLOOKUP(C96,Dados!B:AW,44,0)),0) -> 0 | L96: =IFERROR((VLOOKUP(C96,Dados!B:AW,45,0)),0) -> 0 | M96: =IFERROR((VLOOKUP(C96,Dados!B:AW,43,0)),0) -> 0 | N96: =IFERROR((VLOOKUP(C96,Dados!B:AW,47,0)),0) -> 0 | O96: =IF(AND(J96="Parcial",N96>0,H96>1),-1,IF(AND(J96="Parcial",N96>0,H96<1.1),1,IF(AND(J96="Parcial",N96<0,H96>1.09),-1,IF(J96="Total",-1,IF(H96>1.09,1,2))))) -> 1 | P96: =IF(G96="",0,IF(H96>G96,-1,1)) -> 0 | AC96: 2 | AD96: 2 | AE96: 1 | AH96: ROB027 | AI96: =CONCATENATE(AH96,"*") -> ROB027*
B97: 138 | C97: CEN028 | D97: ZCH | E97: CEN028 | F97: CEN028-CENTRO DE USINAGEM | G97: =IFERROR(VLOOKUP(C97,#REF!,4,FALSE),"") | H97: =VLOOKUP(C97,Dados!B:AW,11,0) -> 1.64 | I97: =(VLOOKUP(C97,Dados!B:AW,48,0)) -> Fase de Degradação | J97: Não há | K97: =IFERROR((VLOOKUP(C97,Dados!B:AW,44,0)),0) -> 0 | L97: =IFERROR((VLOOKUP(C97,Dados!B:AW,45,0)),0) -> 0 | M97: =IFERROR((VLOOKUP(C97,Dados!B:AW,43,0)),0) -> 0 | N97: =IFERROR((VLOOKUP(C97,Dados!B:AW,47,0)),0) -> 0 | O97: =IF(AND(J97="Parcial",N97>0,H97>1),-1,IF(AND(J97="Parcial",N97>0,H97<1.1),1,IF(AND(J97="Parcial",N97<0,H97>1.09),-1,IF(J97="Total",-1,IF(H97>1.09,1,2))))) -> 1 | P97: =IF(G97="",0,IF(H97>G97,-1,1)) -> 0 | AC97: 2 | AD97: 2 | AE97: 1 | AH97: ROB047 | AI97: =CONCATENATE(AH97,"*") -> ROB047*
B98: 139 | C98: CEN029 | D98: ZCH | E98: CEN029 | F98: CEN029-CENTRO DE USINAGEM | G98: =IFERROR(VLOOKUP(C98,#REF!,4,FALSE),"") | H98: =VLOOKUP(C98,Dados!B:AW,11,0) -> 1.66 | I98: =(VLOOKUP(C98,Dados!B:AW,48,0)) -> Fase de Degradação | J98: Não há | K98: =IFERROR((VLOOKUP(C98,Dados!B:AW,44,0)),0) -> 0 | L98: =IFERROR((VLOOKUP(C98,Dados!B:AW,45,0)),0) -> 0 | M98: =IFERROR((VLOOKUP(C98,Dados!B:AW,43,0)),0) -> 0 | N98: =IFERROR((VLOOKUP(C98,Dados!B:AW,47,0)),0) -> 0 | O98: =IF(AND(J98="Parcial",N98>0,H98>1),-1,IF(AND(J98="Parcial",N98>0,H98<1.1),1,IF(AND(J98="Parcial",N98<0,H98>1.09),-1,IF(J98="Total",-1,IF(H98>1.09,1,2))))) -> 1 | P98: =IF(G98="",0,IF(H98>G98,-1,1)) -> 0 | AC98: -1 | AD98: -1 | AE98: -1 | AH98: ROB074 | AI98: =CONCATENATE(AH98,"*") -> ROB074*
B99: 140 | C99: CEN030 | D99: ZCH | E99: CEN030 | F99: CEN030-CENTRO DE USINAGEM | G99: =IFERROR(VLOOKUP(C99,#REF!,4,FALSE),"") | H99: =VLOOKUP(C99,Dados!B:AW,11,0) -> 1.71 | I99: =(VLOOKUP(C99,Dados!B:AW,48,0)) -> Fase de Degradação | J99: Não há | K99: =IFERROR((VLOOKUP(C99,Dados!B:AW,44,0)),0) -> 0 | L99: =IFERROR((VLOOKUP(C99,Dados!B:AW,45,0)),0) -> 0 | M99: =IFERROR((VLOOKUP(C99,Dados!B:AW,43,0)),0) -> 0 | N99: =IFERROR((VLOOKUP(C99,Dados!B:AW,47,0)),0) -> 0 | O99: =IF(AND(J99="Parcial",N99>0,H99>1),-1,IF(AND(J99="Parcial",N99>0,H99<1.1),1,IF(AND(J99="Parcial",N99<0,H99>1.09),-1,IF(J99="Total",-1,IF(H99>1.09,1,2))))) -> 1 | P99: =IF(G99="",0,IF(H99>G99,-1,1)) -> 0 | AC99: -1 | AD99: -1 | AE99: -1 | AH99: BRU057 | AI99: =CONCATENATE(AH99,"*") -> BRU057*
B100: 141 | C100: CEN031 | D100: ZCH | E100: CEN031 | F100: CEN031-CENTRO DE USINAGEM | G100: =IFERROR(VLOOKUP(C100,#REF!,4,FALSE),"") | H100: =VLOOKUP(C100,Dados!B:AW,11,0) -> 1.57 | I100: =(VLOOKUP(C100,Dados!B:AW,48,0)) -> Fase de Degradação | J100: Não há | K100: =IFERROR((VLOOKUP(C100,Dados!B:AW,44,0)),0) -> 0 | L100: =IFERROR((VLOOKUP(C100,Dados!B:AW,45,0)),0) -> 0 | M100: =IFERROR((VLOOKUP(C100,Dados!B:AW,43,0)),0) -> 0 | N100: =IFERROR((VLOOKUP(C100,Dados!B:AW,47,0)),0) -> 0 | O100: =IF(AND(J100="Parcial",N100>0,H100>1),-1,IF(AND(J100="Parcial",N100>0,H100<1.1),1,IF(AND(J100="Parcial",N100<0,H100>1.09),-1,IF(J100="Total",-1,IF(H100>1.09,1,2))))) -> 1 | P100: =IF(G100="",0,IF(H100>G100,-1,1)) -> 0 | AC100: -1 | AD100: -1 | AE100: -1 | AH100: BRU041 | AI100: =CONCATENATE(AH100,"*") -> BRU041*
... B177: 237 | C177: COQ004 | D177: ZFG | E177: COQC02 | F177: COQ004-COQUILHADEIRA | G177: =IFERROR(VLOOKUP(C177,#REF!,4,FALSE),"") | H177: =VLOOKUP(C177,Dados!B:AW,11,0) -> 0.6 | I177: =(VLOOKUP(C177,Dados!B:AW,48,0)) -> Confiabilidade em Crescimento | J177: Parcial | K177: =IFERROR((VLOOKUP(C177,Dados!B:AW,44,0)),0) -> 0 | L177: =IFERROR((VLOOKUP(C177,Dados!B:AW,45,0)),0) -> 0 | M177: =IFERROR((VLOOKUP(C177,Dados!B:AW,43,0)),0) -> 0 | N177: =IFERROR((VLOOKUP(C177,Dados!B:AW,47,0)),0) -> 0 | O177: =IF(AND(J177="Parcial",N177>0,H177>1),-1,IF(AND(J177="Parcial",N177>0,H177<1.1),1,IF(AND(J177="Parcial",N177<0,H177>1.09),-1,IF(J177="Total",-1,IF(H177>1.09,1,2))))) -> 2 | P177: =IF(G177="",0,IF(H177>G177,-1,1)) -> 0 | AC177: 2 | AD177: 2 | AE177: 1 | AH177: MAQ243 | AI177: =CONCATENATE(AH177,"*") -> MAQ243*
...

Sheet Dados
A1: ID | B1: TAG | C1: Denominação | D1: Nº SAP | E1: Local Instalação | F1: Centro Custo | G1: Imobilizado | H1: Ano Aquisição | I1: Valor de Aquisição Atual | J1: Valor Residual Atual | K1: Custo de Manut. Total | L1: Beta | M1: Tempo de Missão (Horas Trab Ano) | N1: Tempo Total | O1: Qtd Falhas Totais | P1: Falha Ano 1 | Q1: Falha Ano 2 | R1: Falha Ano 3 | S1: Falha Ano 4 | T1: Falha Ano 5 | U1: Falha Ano 6 | V1: Falha Ano 7 | W1: Custo Esperado por Corretiva | X1: Custo Esperado Preventiva Mensal | Y1: Taxa | Z1: Acréscimo Aquisição | AA1: Red. Custo Manut. | AB1: 0 - Atual | AC1: 1 | AD1: 2 | AE1: 3 | AF1: 4 | AG1: 5 | AH1: 6 | AI1: 7 | AJ1: 0 - Novo | AK1: 12 | AL1: 23 | AM1: 34 | AN1: 45 | AO1: 56 | AP1: 67 | AQ1: 78 | AR1: POTENCIAL GANHO | AS1: Custo Esperado Atual | AT1: Custo Esperado Novo | AU1: Profit | AV1: ROI | AW1: Fase | AX1: Mini Fab | AY1: OBS | AZ1: OK | BE1: Realizado LCC | BF1: =(COUNTIF($AZ:$AZ,"X")/COUNT(Tabela1[ID])) -> 0.93704246
A2: 1 | B2: APL001 | C2: APL001-APLAINADORA MAXITEC | D2: 10000457 | E2: BR01-MOT-SAB-TRTTRM-APL001 | F2: 2511 | G2: 2200100100 | H2: 2004 | I2: 70007.01 | J2: 0 | K2: 811304.92 | L2: 1.27 | M2: 5020 | N2: 195391 | O2: 420 | P2: =IFERROR(VLOOKUP(Tabela1[[#This Row],[TAG]],#REF!,14,FALSE),"") | Q2: =P2+P2 -> #VALUE! | R2: =Q2+P2 -> #VALUE! | S2: =R2+P2 -> #VALUE! | T2: =S2+P2 -> #VALUE! | U2: =T2+P2 -> #VALUE! | V2: =U2+P2 -> #VALUE! | W2: 966.83 | X2: 4873.49 | Y2: 0.1 | Z2: =IF(Tabela1[[#This Row],[Ano Aquisição]]=2023,0,IFERROR(VLOOKUP(H2,inflação!$F:$H,3,FALSE),"")) -> 1.1001 | AA2: 0.8 | AB2: =I2*-1 -> -70007.01 | AC2: =-(((P2*$W2)+($X2*12))*((1+$Y2)^AC$1)) -> #VALUE! | AD2: =-((((Q2-P2)*$W2)+($X2*12))*((1+$Y2)^AD$1)) -> #VALUE! | AE2: =-((((R2-Q2)*$W2)+($X2*12))*((1+$Y2)^AE$1)) -> #VALUE! | AF2: =-((((S2-R2)*$W2)+($X2*12))*((1+$Y2)^AF$1)) -> #VALUE! | AG2: =-((((T2-S2)*$W2)+($X2*12))*((1+$Y2)^AG$1)) -> #VALUE! | AH2: =-((((U2-T2)*$W2)+($X2*12))*((1+$Y2)^AH$1)) -> #VALUE! | AI2: =-((((V2-U2)*$W2)+($X2*12))*((1+$Y2)^AI$1)) -> #VALUE! | AJ2: =-(I2*(1+Z2)) -> -147021.72 | AK2: =AC2*(1-$AA2) -> #VALUE! | AL2: =AD2*(1-$AA2) -> #VALUE! | AM2: =AE2*(1-$AA2) -> #VALUE! | AN2: =AF2*(1-$AA2) -> #VALUE! | AO2: =AG2*(1-$AA2) -> #VALUE! | AP2: =AH2*(1-$AA2) -> #VALUE! | AQ2: =AI2*(1-$AA2) -> #VALUE! | AR2: =(NPV(Y2,AK2,AL2,AM2,AN2,AO2,AP2,AQ2)+(SUM(AJ2,(J2*-1))))-(NPV(Y2,AC2,AD2,AE2,AF2,AG2,AH2,AI2)) -> #VALUE! | AS2: =SUM(AC2:AI2) -> #VALUE! | AT2: =SUM(AK2:AQ2) -> #VALUE! | AU2: =(((AVERAGE(AC2:AI2)/1000)-(AVERAGE(AK2:AQ2)/1000))+(((AJ2/1000)*-1)/7)+((J2/1000)/7))*-1 -> #VALUE! | AV2: =AU2/(((J2/1000)+((AJ2*-1)/1000))) -> #VALUE! | AW2: =IF(L2>1.1,"Fase de Degradação",IF(L2<1,"Confiabilidade em Crescimento","Fase de Vida Útil")) -> Fase de Degradação | AX2: =VLOOKUP(D2,#REF!,5,FALSE) -> #REF! | AZ2: X | BB2: =IFERROR(VLOOKUP(Tabela1[[#This Row],[Denominação]],[10]Planilha1!$A:$B,2,FALSE),"") -> 811304.92
A3: 2 | B3: BAL003 | C3: BAL003-BALANCEADORA | D3: 10003740 | E3: BR01-CIL-UCI-VOLANT-BAL003 | F3: 4548 | G3: - | H3: 2008 | I3: 184344.2 | J3: 0 | K3: 135505.04 | L3: 0.75 | M3: 4433 | N3: 116075 | O3: 175 | P3: =IFERROR(VLOOKUP(Tabela1[[#This Row],[TAG]],#REF!,14,FALSE),"") | Q3: =P3+P3 -> #VALUE! | R3: =Q3+P3 -> #VALUE! | S3: =R3+P3 -> #VALUE! | T3: =S3+P3 -> #VALUE! | U3: =T3+P3 -> #VALUE! | V3: =U3+P3 -> #VALUE! | W3: 257.32 | X3: 312.04 | Y3: 0.1 | Z3: =IF(Tabela1[[#This Row],[Ano Aquisição]]=2023,0,IFERROR(VLOOKUP(H3,inflação!$F:$H,3,FALSE),"")) -> 0.8912 | AA3: 0.8 | AB3: =I3*-1 -> -184344.2 | AC3: =-(((P3*$W3)+($X3*12))*((1+$Y3)^AC$1)) -> #VALUE! | AD3: =-((((Q3-P3)*$W3)+($X3*12))*((1+$Y3)^AD$1)) -> #VALUE! | AE3: =-((((R3-Q3)*$W3)+($X3*12))*((1+$Y3)^AE$1)) -> #VALUE! | AF3: =-((((S3-R3)*$W3)+($X3*12))*((1+$Y3)^AF$1)) -> #VALUE! | AG3: =-((((T3-S3)*$W3)+($X3*12))*((1+$Y3)^AG$1)) -> #VALUE! | AH3: =-((((U3-T3)*$W3)+($X3*12))*((1+$Y3)^AH$1)) -> #VALUE! | AI3: =-((((V3-U3)*$W3)+($X3*12))*((1+$Y3)^AI$1)) -> #VALUE! | AJ3: =-(I3*(1+Z3)) -> -348631.75 | AK3: =AC3*(1-$AA3) -> #VALUE! | AL3: =AD3*(1-$AA3) -> #VALUE! | AM3: =AE3*(1-$AA3) -> #VALUE! | AN3: =AF3*(1-$AA3) -> #VALUE! | AO3: =AG3*(1-$AA3) -> #VALUE! | AP3: =AH3*(1-$AA3) -> #VALUE! | AQ3: =AI3*(1-$AA3) -> #VALUE! | AR3: =(NPV(Y3,AK3,AL3,AM3,AN3,AO3,AP3,AQ3)+(SUM(AJ3,(J3*-1))))-(NPV(Y3,AC3,AD3,AE3,AF3,AG3,AH3,AI3)) -> #VALUE! | AS3: =SUM(AC3:AI3) -> #VALUE! | AT3: =SUM(AK3:AQ3) -> #VALUE! | AU3: =(((AVERAGE(AC3:AI3)/1000)-(AVERAGE(AK3:AQ3)/1000))+(((AJ3/1000)*-1)/7)+((J3/1000)/7))*-1 -> #VALUE! | AV3: =AU3/(((J3/1000)+((AJ3*-1)/1000))) -> #VALUE! | AW3: =IF(L3>1.1,"Fase de Degradação",IF(L3<1,"Confiabilidade em Crescimento","Fase de Vida Útil")) -> Confiabilidade em Crescimento | AX3: =VLOOKUP(D3,#REF!,5,FALSE) -> #REF! | AZ3: X | BB3: =IFERROR(VLOOKUP(Tabela1[[#This Row],[Denominação]],[10]Planilha1!$A:$B,2,FALSE),"") -> 135505.04
A4: 3 | B4: BAL004 | C4: BAL004-BALANCEADORA | D4: 10006290 | E4: BR01-CIL-UCI-VOLANT-BAL004 | F4: 4548 | G4: 36407 | H4: 2009 | I4: 184344.2 | J4: 0 | K4: 284121.64 | L4: 1.12 | M4: 4433 | N4: 71239 | O4: 253 | P4: =IFERROR(VLOOKUP(Tabela1[[#This Row],[TAG]],#REF!,14,FALSE),"") | Q4: =P4+P4 -> #VALUE! | R4: =Q4+P4 -> #VALUE! | S4: =R4+P4 -> #VALUE! | T4: =S4+P4 -> #VALUE! | U4: =T4+P4 -> #VALUE! | V4: =U4+P4 -> #VALUE! | W4: 412.47 | X4: 831.28 | Y4: 0.1 | Z4: =IF(Tabela1[[#This Row],[Ano Aquisição]]=2023,0,IFERROR(VLOOKUP(H4,inflação!$F:$H,3,FALSE),"")) -> 0.8322 | AA4: 0.8 | AB4: =I4*-1 -> -184344.2 | AC4: =-(((P4*$W4)+($X4*12))*((1+$Y4)^AC$1)) -> #VALUE! | AD4: =-((((Q4-P4)*$W4)+($X4*12))*((1+$Y4)^AD$1)) -> #VALUE! | AE4: =-((((R4-Q4)*$W4)+($X4*12))*((1+$Y4)^AE$1)) -> #VALUE! | AF4: =-((((S4-R4)*$W4)+($X4*12))*((1+$Y4)^AF$1)) -> #VALUE! | AG4: =-((((T4-S4)*$W4)+($X4*12))*((1+$Y4)^AG$1)) -> #VALUE! | AH4: =-((((U4-T4)*$W4)+($X4*12))*((1+$Y4)^AH$1)) -> #VALUE! | AI4: =-((((V4-U4)*$W4)+($X4*12))*((1+$Y4)^AI$1)) -> #VALUE! | AJ4: =-(I4*(1+Z4)) -> -337755.44 | AK4: =AC4*(1-$AA4) -> #VALUE! | AL4: =AD4*(1-$AA4) -> #VALUE! | AM4: =AE4*(1-$AA4) -> #VALUE! | AN4: =AF4*(1-$AA4) -> #VALUE! | AO4: =AG4*(1-$AA4) -> #VALUE! | AP4: =AH4*(1-$AA4) -> #VALUE! | AQ4: =AI4*(1-$AA4) -> #VALUE! | AR4: =(NPV(Y4,AK4,AL4,AM4,AN4,AO4,AP4,AQ4)+(SUM(AJ4,(J4*-1))))-(NPV(Y4,AC4,AD4,AE4,AF4,AG4,AH4,AI4)) -> #VALUE! | AS4: =SUM(AC4:AI4) -> #VALUE! | AT4: =SUM(AK4:AQ4) -> #VALUE! | AU4: =(((AVERAGE(AC4:AI4)/1000)-(AVERAGE(AK4:AQ4)/1000))+(((AJ4/1000)*-1)/7)+((J4/1000)/7))*-1 -> #VALUE! | AV4: =AU4/(((J4/1000)+((AJ4*-1)/1000))) -> #VALUE! | AW4: =IF(L4>1.1,"Fase de Degradação",IF(L4<1,"Confiabilidade em Crescimento","Fase de Vida Útil")) -> Fase de Degradação | AX4: =VLOOKUP(D4,#REF!,5,FALSE) -> #REF! | AZ4: X | BB4: =IFERROR(VLOOKUP(Tabela1[[#This Row],[Denominação]],[10]Planilha1!$A:$B,2,FALSE),"") -> 284121.64
A5: 4 | B5: BAL006 | C5: BAL006-BALANCEADORA | D5: 10006845 | E5: BR01-CIL-UCI-VOLANT-BAL006 | F5: 4548 | G5: 46611 | H5: 2016 | I5: 560982.64 | J5: 206356 | K5: 2171.91 | L5: 1.12 | M5: 4433 | N5: 39853 | O5: 146 | P5: =IFERROR(VLOOKUP(Tabela1[[#This Row],[TAG]],#REF!,14,FALSE),"") | Q5: =P5+P5 -> #VALUE! | R5: =Q5+P5 -> #VALUE! | S5: =R5+P5 -> #VALUE! | T5: =S5+P5 -> #VALUE! | U5: =T5+P5 -> #VALUE! | V5: =U5+P5 -> #VALUE! | W5: 513.03 | X5: 433.37 | Y5: 0.1 | Z5: =IF(Tabela1[[#This Row],[Ano Aquisição]]=2023,0,IFERROR(VLOOKUP(H5,inflação!$F:$H,3,FALSE),"")) -> 0.3767 | AA5: 0.8 | AB5: =I5*-1 -> -560982.64 | AC5: =-(((P5*$W5)+($X5*12))*((1+$Y5)^AC$1)) -> #VALUE! | AD5: =-((((Q5-P5)*$W5)+($X5*12))*((1+$Y5)^AD$1)) -> #VALUE! | AE5: =-((((R5-Q5)*$W5)+($X5*12))*((1+$Y5)^AE$1)) -> #VALUE! | AF5: =-((((S5-R5)*$W5)+($X5*12))*((1+$Y5)^AF$1)) -> #VALUE! | AG5: =-((((T5-S5)*$W5)+($X5*12))*((1+$Y5)^AG$1)) -> #VALUE! | AH5: =-((((U5-T5)*$W5)+($X5*12))*((1+$Y5)^AH$1)) -> #VALUE! | AI5: =-((((V5-U5)*$W5)+($X5*12))*((1+$Y5)^AI$1)) -> #VALUE! | AJ5: =-(I5*(1+Z5)) -> -772304.8 | AK5: =AC5*(1-$AA5) -> #VALUE! | AL5: =AD5*(1-$AA5) -> #VALUE! | AM5: =AE5*(1-$AA5) -> #VALUE! | AN5: =AF5*(1-$AA5) -> #VALUE! | AO5: =AG5*(1-$AA5) -> #VALUE! | AP5: =AH5*(1-$AA5) -> #VALUE! | AQ5: =AI5*(1-$AA5) -> #VALUE! | AR5: =(NPV(Y5,AK5,AL5,AM5,AN5,AO5,AP5,AQ5)+(SUM(AJ5,(J5*-1))))-(NPV(Y5,AC5,AD5,AE5,AF5,AG5,AH5,AI5)) -> #VALUE! | AS5: =SUM(AC5:AI5) -> #VALUE! | AT5: =SUM(AK5:AQ5) -> #VALUE! | AU5: =(((AVERAGE(AC5:AI5)/1000)-(AVERAGE(AK5:AQ5)/1000))+(((AJ5/1000)*-1)/7)+((J5/1000)/7))*-1 -> #VALUE! | AV5: =AU5/(((J5/1000)+((AJ5*-1)/1000))) -> #VALUE! | AW5: =IF(L5>1.1,"Fase de Degradação",IF(L5<1,"Confiabilidade em Crescimento","Fase de Vida Útil")) -> Fase de Degradação | AX5: =VLOOKUP(D5,#REF!,5,FALSE) -> #REF! | AZ5: X | BB5: =IFERROR(VLOOKUP(Tabela1[[#This Row],[Denominação]],[10]Planilha1!$A:$B,2,FALSE),"") -> 2171.91
A6: 5 | B6: BAL007 | C6: BAL007-BALANCEADORA | D6: 10006406 | E6: BR01-CIL-UCI-VOLANT-BAL007 | F6: 4548 | G6: 53931 | H6: 2021 | I6: 792392.34 | J6: 690145 | K6: 144168.47 | L6: 0.89 | M6: 4433 | N6: 57501 | O6: 169 | P6: =IFERROR(VLOOKUP(Tabela1[[#This Row],[TAG]],#REF!,14,FALSE),"") | Q6: =P6+P6 -> #VALUE! | R6: =Q6+P6 -> #VALUE! | S6: =R6+P6 -> #VALUE! | T6: =S6+P6 -> #VALUE! | U6: =T6+P6 -> #VALUE! | V6: =U6+P6 -> #VALUE! | W6: 217.83 | X6: 490.13 | Y6: 0.1 | Z6: =IF(Tabela1[[#This Row],[Ano Aquisição]]=2023,0,IFERROR(VLOOKUP(H6,inflação!$F:$H,3,FALSE),"")) -> 0.1585 | AA6: 0.8 | AB6: =I6*-1 -> -792392.34 | AC6: =-(((P6*$W6)+($X6*12))*((1+$Y6)^AC$1)) -> #VALUE! | AD6: =-((((Q6-P6)*$W6)+($X6*12))*((1+$Y6)^AD$1)) -> #VALUE! | AE6: =-((((R6-Q6)*$W6)+($X6*12))*((1+$Y6)^AE$1)) -> #VALUE! | AF6: =-((((S6-R6)*$W6)+($X6*12))*((1+$Y6)^AF$1)) -> #VALUE! | AG6: =-((((T6-S6)*$W6)+($X6*12))*((1+$Y6)^AG$1)) -> #VALUE! | AH6: =-((((U6-T6)*$W6)+($X6*12))*((1+$Y6)^AH$1)) -> #VALUE! | AI6: =-((((V6-U6)*$W6)+($X6*12))*((1+$Y6)^AI$1)) -> #VALUE! | AJ6: =-(I6*(1+Z6)) -> -917986.53 | AK6: =AC6*(1-$AA6) -> #VALUE! | AL6: =AD6*(1-$AA6) -> #VALUE! | AM6: =AE6*(1-$AA6) -> #VALUE! | AN6: =AF6*(1-$AA6) -> #VALUE! | AO6: =AG6*(1-$AA6) -> #VALUE! | AP6: =AH6*(1-$AA6) -> #VALUE! | AQ6: =AI6*(1-$AA6) -> #VALUE! | AR6: =(NPV(Y6,AK6,AL6,AM6,AN6,AO6,AP6,AQ6)+(SUM(AJ6,(J6*-1))))-(NPV(Y6,AC6,AD6,AE6,AF6,AG6,AH6,AI6)) -> #VALUE! | AS6: =SUM(AC6:AI6) -> #VALUE! | AT6: =SUM(AK6:AQ6) -> #VALUE! | AU6: =(((AVERAGE(AC6:AI6)/1000)-(AVERAGE(AK6:AQ6)/1000))+(((AJ6/1000)*-1)/7)+((J6/1000)/7))*-1 -> #VALUE! | AV6: =AU6/(((J6/1000)+((AJ6*-1)/1000))) -> #VALUE! | AW6: =IF(L6>1.1,"Fase de Degradação",IF(L6<1,"Confiabilidade em Crescimento","Fase de Vida Útil")) -> Confiabilidade em Crescimento | AX6: =VLOOKUP(D6,#REF!,5,FALSE) -> #REF! | AZ6: X | BB6: =IFERROR(VLOOKUP(Tabela1[[#This Row],[Denominação]],[10]Planilha1!$A:$B,2,FALSE),"") -> 144168.47
A7: 6 | B7: BAL008 | C7: BAL008-BALANCEADORA | D7: 10006719 | E7: BR01-CIL-UCI-VOLANT-BAL008 | F7: 4548 | G7: 55614 | H7: 2021 | I7: 748548.06 | J7: 673691 | K7: 11740.33 | L7: 0.92 | M7: 4433 | N7: 10039 | O7: 18 | P7: =IFERROR(VLOOKUP(Tabela1[[#This Row],[TAG]],#REF!,14,FALSE),"") | Q7: =P7+P7 -> #VALUE! | R7: =Q7+P7 -> #VALUE! | S7: =R7+P7 -> #VALUE! | T7: =S7+P7 -> #VALUE! | U7: =T7+P7 -> #VALUE! | V7: =U7+P7 -> #VALUE! | W7: 354.77 | X7: 553.08 | Y7: 0.1 | Z7: =IF(Tabela1[[#This Row],[Ano Aquisição]]=2023,0,IFERROR(VLOOKUP(H7,inflação!$F:$H,3,FALSE),"")) -> 0.1585 | AA7: 0.8 | AB7: =I7*-1 -> -748548.06 | AC7: =-(((P7*$W7)+($X7*12))*((1+$Y7)^AC$1)) -> #VALUE! | AD7: =-((((Q7-P7)*$W7)+($X7*12))*((1+$Y7)^AD$1)) -> #VALUE! | AE7: =-((((R7-Q7)*$W7)+($X7*12))*((1+$Y7)^AE$1)) -> #VALUE! | AF7: =-((((S7-R7)*$W7)+($X7*12))*((1+$Y7)^AF$1)) -> #VALUE! | AG7: =-((((T7-S7)*$W7)+($X7*12))*((1+$Y7)^AG$1)) -> #VALUE! | AH7: =-((((U7-T7)*$W7)+($X7*12))*((1+$Y7)^AH$1)) -> #VALUE! | AI7: =-((((V7-U7)*$W7)+($X7*12))*((1+$Y7)^AI$1)) -> #VALUE! | AJ7: =-(I7*(1+Z7)) -> -867192.93 | AK7: =AC7*(1-$AA7) -> #VALUE! | AL7: =AD7*(1-$AA7) -> #VALUE! | AM7: =AE7*(1-$AA7) -> #VALUE! | AN7: =AF7*(1-$AA7) -> #VALUE! | AO7: =AG7*(1-$AA7) -> #VALUE! | AP7: =AH7*(1-$AA7) -> #VALUE! | AQ7: =AI7*(1-$AA7) -> #VALUE! | AR7: =(NPV(Y7,AK7,AL7,AM7,AN7,AO7,AP7,AQ7)+(SUM(AJ7,(J7*-1))))-(NPV(Y7,AC7,AD7,AE7,AF7,AG7,AH7,AI7)) -> #VALUE! | AS7: =SUM(AC7:AI7) -> #VALUE! | AT7: =SUM(AK7:AQ7) -> #VALUE! | AU7: =(((AVERAGE(AC7:AI7)/1000)-(AVERAGE(AK7:AQ7)/1000))+(((AJ7/1000)*-1)/7)+((J7/1000)/7))*-1 -> #VALUE! | AV7: =AU7/(((J7/1000)+((AJ7*-1)/1000))) -> #VALUE! | AW7: =IF(L7>1.1,"Fase de Degradação",IF(L7<1,"Confiabilidade em Crescimento","Fase de Vida Útil")) -> Confiabilidade em Crescimento | AX7: =VLOOKUP(D7,#REF!,5,FALSE) -> #REF! | AZ7: X | BB7: =IFERROR(VLOOKUP(Tabela1[[#This Row],[Denominação]],[10]Planilha1!$A:$B,2,FALSE),"") -> 11740.33
A8: 7 | B8: BAL009 | C8: BAL009-BALANCEADORA | D8: 10006732 | E8: BR01-MOT-UMG-MISCEL-BAL009 | F8: 2376 | G8: 55185 | H8: 2021 | I8: 315956.73 | J8: 278098 | K8: 2960.93 | L8: 0.93 | M8: 3854 | N8: 9849 | O8: 3 | P8: =IFERROR(VLOOKUP(Tabela1[[#This Row],[TAG]],#REF!,14,FALSE),"") | Q8: =P8+P8 -> #VALUE! | R8: =Q8+P8 -> #VALUE! | S8: =R8+P8 -> #VALUE! | T8: =S8+P8 -> #VALUE! | U8: =T8+P8 -> #VALUE! | V8: =U8+P8 -> #VALUE! | W8: 627.23 | X8: 467.39 | Y8: 0.1 | Z8: =IF(Tabela1[[#This Row],[Ano Aquisição]]=2023,0,IFERROR(VLOOKUP(H8,inflação!$F:$H,3,FALSE),"")) -> 0.1585 | AA8: 0.8 | AB8: =I8*-1 -> -315956.73 | AC8: =-(((P8*$W8)+($X8*12))*((1+$Y8)^AC$1)) -> #VALUE! | AD8: =-((((Q8-P8)*$W8)+($X8*12))*((1+$Y8)^AD$1)) -> #VALUE! | AE8: =-((((R8-Q8)*$W8)+($X8*12))*((1+$Y8)^AE$1)) -> #VALUE! | AF8: =-((((S8-R8)*$W8)+($X8*12))*((1+$Y8)^AF$1)) -> #VALUE! | AG8: =-((((T8-S8)*$W8)+($X8*12))*((1+$Y8)^AG$1)) -> #VALUE! | AH8: =-((((U8-T8)*$W8)+($X8*12))*((1+$Y8)^AH$1)) -> #VALUE! | AI8: =-((((V8-U8)*$W8)+($X8*12))*((1+$Y8)^AI$1)) -> #VALUE! | AJ8: =-(I8*(1+Z8)) -> -366035.87 | AK8: =AC8*(1-$AA8) -> #VALUE! | AL8: =AD8*(1-$AA8) -> #VALUE! | AM8: =AE8*(1-$AA8) -> #VALUE! | AN8: =AF8*(1-$AA8) -> #VALUE! | AO8: =AG8*(1-$AA8) -> #VALUE! | AP8: =AH8*(1-$AA8) -> #VALUE! | AQ8: =AI8*(1-$AA8) -> #VALUE! | AR8: =(NPV(Y8,AK8,AL8,AM8,AN8,AO8,AP8,AQ8)+(SUM(AJ8,(J8*-1))))-(NPV(Y8,AC8,AD8,AE8,AF8,AG8,AH8,AI8)) -> #VALUE! | AS8: =SUM(AC8:AI8) -> #VALUE! | AT8: =SUM(AK8:AQ8) -> #VALUE! | AU8: =(((AVERAGE(AC8:AI8)/1000)-(AVERAGE(AK8:AQ8)/1000))+(((AJ8/1000)*-1)/7)+((J8/1000)/7))*-1 -> #VALUE! | AV8: =AU8/(((J8/1000)+((AJ8*-1)/1000))) -> #VALUE! | AW8: =IF(L8>1.1,"Fase de Degradação",IF(L8<1,"Confiabilidade em Crescimento","Fase de Vida Útil")) -> Confiabilidade em Crescimento | AX8: =VLOOKUP(D8,#REF!,5,FALSE) -> #REF! | AZ8: X | BB8: =IFERROR(VLOOKUP(Tabela1[[#This Row],[Denominação]],[10]Planilha1!$A:$B,2,FALSE),"") -> 2960.93
A9: 8 | B9: BRU002 | C9: BRU002-BRUNIDORA | D9: 10000309 | E9: BR01-MOT-VIR-USIDUR-BRU002 | F9: 3316 | G9: 800200200 | H9: 1986 | I9: 230561.52 | J9: 0 | K9: 252551.51 | L9: 1.15 | M9: 4392 | N9: 197421 | O9: 309 | P9: =IFERROR(VLOOKUP(Tabela1[[#This Row],[TAG]],#REF!,14,FALSE),"") | Q9: =P9+P9 -> #VALUE! | R9: =Q9+P9 -> #VALUE! | S9: =R9+P9 -> #VALUE! | T9: =S9+P9 -> #VALUE! | U9: =T9+P9 -> #VALUE! | V9: =U9+P9 -> #VALUE! | W9: 692.35 | X9: 1510.85 | Y9: 0.1 | Z9: =IF(Tabela1[[#This Row],[Ano Aquisição]]=2023,0,IFERROR(VLOOKUP(H9,inflação!$F:$H,3,FALSE),"")) -> 2.3433462 | AA9: 0.8 | AB9: =I9*-1 -> -230561.52 | AC9: =-(((P9*$W9)+($X9*12))*((1+$Y9)^AC$1)) -> #VALUE! | AD9: =-((((Q9-P9)*$W9)+($X9*12))*((1+$Y9)^AD$1)) -> #VALUE! | AE9: =-((((R9-Q9)*$W9)+($X9*12))*((1+$Y9)^AE$1)) -> #VALUE! | AF9: =-((((S9-R9)*$W9)+($X9*12))*((1+$Y9)^AF$1)) -> #VALUE! | AG9: =-((((T9-S9)*$W9)+($X9*12))*((1+$Y9)^AG$1)) -> #VALUE! | AH9: =-((((U9-T9)*$W9)+($X9*12))*((1+$Y9)^AH$1)) -> #VALUE! | AI9: =-((((V9-U9)*$W9)+($X9*12))*((1+$Y9)^AI$1)) -> #VALUE! | AJ9: =-(I9*(1+Z9)) -> -770846.97 | AK9: =AC9*(1-$AA9) -> #VALUE! | AL9: =AD9*(1-$AA9) -> #VALUE! | AM9: =AE9*(1-$AA9) -> #VALUE! | AN9: =AF9*(1-$AA9) -> #VALUE! | AO9: =AG9*(1-$AA9) -> #VALUE! | AP9: =AH9*(1-$AA9) -> #VALUE! | AQ9: =AI9*(1-$AA9) -> #VALUE! | AR9: =(NPV(Y9,AK9,AL9,AM9,AN9,AO9,AP9,AQ9)+(SUM(AJ9,(J9*-1))))-(NPV(Y9,AC9,AD9,AE9,AF9,AG9,AH9,AI9)) -> #VALUE! | AS9: =SUM(AC9:AI9) -> #VALUE! | AT9: =SUM(AK9:AQ9) -> #VALUE! | AU9: =(((AVERAGE(AC9:AI9)/1000)-(AVERAGE(AK9:AQ9)/1000))+(((AJ9/1000)*-1)/7)+((J9/1000)/7))*-1 -> #VALUE! | AV9: =AU9/(((J9/1000)+((AJ9*-1)/1000))) -> #VALUE! | AW9: =IF(L9>1.1,"Fase de Degradação",IF(L9<1,"Confiabilidade em Crescimento","Fase de Vida Útil")) -> Fase de Degradação | AX9: =VLOOKUP(D9,#REF!,5,FALSE) -> #REF! | AZ9: X | BB9: =IFERROR(VLOOKUP(Tabela1[[#This Row],[Denominação]],[10]Planilha1!$A:$B,2,FALSE),"") -> 252551.51
A10: 9 | B10: BRU003 | C10: BRU003-BRUNIDORA | D10: 10000313 | E10: BR01-MOT-VIR-LBIELA-BRU003 | F10: 3337 | G10: 800100200 | H10: 1977 | I10: 151187.09 | J10: 0 | K10: 276100.33 | L10: 1.11 | M10: 4392 | N10: 198333 | O10: 353 | P10: =IFERROR(VLOOKUP(Tabela1[[#This Row],[TAG]],#REF!,14,FALSE),"") | Q10: =P10+P10 -> #VALUE! | R10: =Q10+P10 -> #VALUE! | S10: =R10+P10 -> #VALUE! | T10: =S10+P10 -> #VALUE! | U10: =T10+P10 -> #VALUE! | V10: =U10+P10 -> #VALUE! | W10: 594.92 | X10: 1515.77 | Y10: 0.1 | Z10: =IF(Tabela1[[#This Row],[Ano Aquisição]]=2023,0,IFERROR(VLOOKUP(H10,inflação!$F:$H,3,FALSE),"")) -> 2.9147077 | AA10: 0.8 | AB10: =I10*-1 -> -151187.09 | AC10: =-(((P10*$W10)+($X10*12))*((1+$Y10)^AC$1)) -> #VALUE! | AD10: =-((((Q10-P10)*$W10)+($X10*12))*((1+$Y10)^AD$1)) -> #VALUE! | AE10: =-((((R10-Q10)*$W10)+($X10*12))*((1+$Y10)^AE$1)) -> #VALUE! | AF10: =-((((S10-R10)*$W10)+($X10*12))*((1+$Y10)^AF$1)) -> #VALUE! | AG10: =-((((T10-S10)*$W10)+($X10*12))*((1+$Y10)^AG$1)) -> #VALUE! | AH10: =-((((U10-T10)*$W10)+($X10*12))*((1+$Y10)^AH$1)) -> #VALUE! | AI10: =-((((V10-U10)*$W10)+($X10*12))*((1+$Y10)^AI$1)) -> #VALUE! | AJ10: =-(I10*(1+Z10)) -> -591853.26 | AK10: =AC10*(1-$AA10) -> #VALUE! | AL10: =AD10*(1-$AA10) -> #VALUE! | AM10: =AE10*(1-$AA10) -> #VALUE! | AN10: =AF10*(1-$AA10) -> #VALUE! | AO10: =AG10*(1-$AA10) -> #VALUE! | AP10: =AH10*(1-$AA10) -> #VALUE! | AQ10: =AI10*(1-$AA10) -> #VALUE! | AR10: =(NPV(Y10,AK10,AL10,AM10,AN10,AO10,AP10,AQ10)+(SUM(AJ10,(J10*-1))))-(NPV(Y10,AC10,AD10,AE10,AF10,AG10,AH10,AI10)) -> #VALUE! | AS10: =SUM(AC10:AI10) -> #VALUE! | AT10: =SUM(AK10:AQ10) -> #VALUE! | AU10: =(((AVERAGE(AC10:AI10)/1000)-(AVERAGE(AK10:AQ10)/1000))+(((AJ10/1000)*-1)/7)+((J10/1000)/7))*-1 -> #VALUE! | AV10: =AU10/(((J10/1000)+((AJ10*-1)/1000))) -> #VALUE! | AW10: =IF(L10>1.1,"Fase de Degradação",IF(L10<1,"Confiabilidade em Crescimento","Fase de Vida Útil")) -> Fase de Degradação | AX10: =VLOOKUP(D10,#REF!,5,FALSE) -> #REF! | AZ10: X | BB10: =IFERROR(VLOOKUP(Tabela1[[#This Row],[Denominação]],[10]Planilha1!$A:$B,2,FALSE),"") -> 276100.33
A11: 10 | B11: BRU004 | C11: BRU004-BRUNIDORA | D11: 10000317 | E11: BR01-MOT-VIR-LBIELA-BRU004 | F11: 3336 | G11: 800100100 | H11: 1985 | I11: 230561.52 | J11: 0 | K11: 1133969.9 | L11: 1.35 | M11: 4392 | N11: 198895 | O11: 1336 | P11: =IFERROR(VLOOKUP(Tabela1[[#This Row],[TAG]],#REF!,14,FALSE),"") | Q11: =P11+P11 -> #VALUE! | R11: =Q11+P11 -> #VALUE! | S11: =R11+P11 -> #VALUE! | T11: =S11+P11 -> #VALUE! | U11: =T11+P11 -> #VALUE! | V11: =U11+P11 -> #VALUE! | W11: 555.67 | X11: 5146.48 | Y11: 0.1 | Z11: =IF(Tabela1[[#This Row],[Ano Aquisição]]=2023,0,IFERROR(VLOOKUP(H11,inflação!$F:$H,3,FALSE),"")) -> 2.4068308 | AA11: 0.8 | AB11: =I11*-1 -> -230561.52 | AC11: =-(((P11*$W11)+($X11*12))*((1+$Y11)^AC$1)) -> #VALUE! | AD11: =-((((Q11-P11)*$W11)+($X11*12))*((1+$Y11)^AD$1)) -> #VALUE! | AE11: =-((((R11-Q11)*$W11)+($X11*12))*((1+$Y11)^AE$1)) -> #VALUE! | AF11: =-((((S11-R11)*$W11)+($X11*12))*((1+$Y11)^AF$1)) -> #VALUE! | AG11: =-((((T11-S11)*$W11)+($X11*12))*((1+$Y11)^AG$1)) -> #VALUE! | AH11: =-((((U11-T11)*$W11)+($X11*12))*((1+$Y11)^AH$1)) -> #VALUE! | AI11: =-((((V11-U11)*$W11)+($X11*12))*((1+$Y11)^AI$1)) -> #VALUE! | AJ11: =-(I11*(1+Z11)) -> -785484.08 | AK11: =AC11*(1-$AA11) -> #VALUE! | AL11: =AD11*(1-$AA11) -> #VALUE! | AM11: =AE11*(1-$AA11) -> #VALUE! | AN11: =AF11*(1-$AA11) -> #VALUE! | AO11: =AG11*(1-$AA11) -> #VALUE! | AP11: =AH11*(1-$AA11) -> #VALUE! | AQ11: =AI11*(1-$AA11) -> #VALUE! | AR11: =(NPV(Y11,AK11,AL11,AM11,AN11,AO11,AP11,AQ11)+(SUM(AJ11,(J11*-1))))-(NPV(Y11,AC11,AD11,AE11,AF11,AG11,AH11,AI11)) -> #VALUE! | AS11: =SUM(AC11:AI11) -> #VALUE! | AT11: =SUM(AK11:AQ11) -> #VALUE! | AU11: =(((AVERAGE(AC11:AI11)/1000)-(AVERAGE(AK11:AQ11)/1000))+(((AJ11/1000)*-1)/7)+((J11/1000)/7))*-1 -> #VALUE! | AV11: =AU11/(((J11/1000)+((AJ11*-1)/1000))) -> #VALUE! | AW11: =IF(L11>1.1,"Fase de Degradação",IF(L11<1,"Confiabilidade em Crescimento","Fase de Vida Útil")) -> Fase de Degradação | AX11: =VLOOKUP(D11,#REF!,5,FALSE) -> #REF! | AZ11: X | BB11: =IFERROR(VLOOKUP(Tabela1[[#This Row],[Denominação]],[10]Planilha1!$A:$B,2,FALSE),"") -> 1133969.9
A12: 11 | B12: BRU008 | C12: BRU008-BRUNIDORA | D12: 10000155 | E12: BR01-CIL-UCI-BRUNI1-BRUC02 | F12: 4529 | G12: Não encontrado | H12: 1997 | I12: 93300.55 | J12: 0 | K12: 225074.07 | L12: 0.95 | M12: 4464 | N12: 195980 | O12: 338 | P12: =IFERROR(VLOOKUP(Tabela1[[#This Row],[TAG]],#REF!,14,FALSE),"") | Q12: =P12+P12 -> #VALUE! | R12: =Q12+P12 -> #VALUE! | S12: =R12+P12 -> #VALUE! | T12: =S12+P12 -> #VALUE! | U12: =T12+P12 -> #VALUE! | V12: =U12+P12 -> #VALUE! | W12: 259.8 | X12: 397.37 | Y12: 0.1 | Z12: =IF(Tabela1[[#This Row],[Ano Aquisição]]=2023,0,IFERROR(VLOOKUP(H12,inflação!$F:$H,3,FALSE),"")) -> 1.6129 | AA12: 0.8 | AB12: =I12*-1 -> -93300.55 | AC12: =-(((P12*$W12)+($X12*12))*((1+$Y12)^AC$1)) -> #VALUE! | AD12: =-((((Q12-P12)*$W12)+($X12*12))*((1+$Y12)^AD$1)) -> #VALUE! | AE12: =-((((R12-Q12)*$W12)+($X12*12))*((1+$Y12)^AE$1)) -> #VALUE! | AF12: =-((((S12-R12)*$W12)+($X12*12))*((1+$Y12)^AF$1)) -> #VALUE! | AG12: =-((((T12-S12)*$W12)+($X12*12))*((1+$Y12)^AG$1)) -> #VALUE! | AH12: =-((((U12-T12)*$W12)+($X12*12))*((1+$Y12)^AH$1)) -> #VALUE! | AI12: =-((((V12-U12)*$W12)+($X12*12))*((1+$Y12)^AI$1)) -> #VALUE! | AJ12: =-(I12*(1+Z12)) -> -243785.01 | AK12: =AC12*(1-$AA12) -> #VALUE! | AL12: =AD12*(1-$AA12) -> #VALUE! | AM12: =AE12*(1-$AA12) -> #VALUE! | AN12: =AF12*(1-$AA12) -> #VALUE! | AO12: =AG12*(1-$AA12) -> #VALUE! | AP12: =AH12*(1-$AA12) -> #VALUE! | AQ12: =AI12*(1-$AA12) -> #VALUE! | AR12: =(NPV(Y12,AK12,AL12,AM12,AN12,AO12,AP12,AQ12)+(SUM(AJ12,(J12*-1))))-(NPV(Y12,AC12,AD12,AE12,AF12,AG12,AH12,AI12)) -> #VALUE! | AS12: =SUM(AC12:AI12) -> #VALUE! | AT12: =SUM(AK12:AQ12) -> #VALUE! | AU12: =(((AVERAGE(AC12:AI12)/1000)-(AVERAGE(AK12:AQ12)/1000))+(((AJ12/1000)*-1)/7)+((J12/1000)/7))*-1 -> #VALUE! | AV12: =AU12/(((J12/1000)+((AJ12*-1)/1000))) -> #VALUE! | AW12: =IF(L12>1.1,"Fase de Degradação",IF(L12<1,"Confiabilidade em Crescimento","Fase de Vida Útil")) -> Confiabilidade em Crescimento | AX12: =VLOOKUP(D12,#REF!,5,FALSE) -> #REF! | AZ12: X | BB12: =IFERROR(VLOOKUP(Tabela1[[#This Row],[Denominação]],[10]Planilha1!$A:$B,2,FALSE),"") -> 227581.53
A13: 12 | B13: BRU009 | C13: BRU009-BRUNIDORA | D13: 10000158 | E13: BR01-CIL-UCI-BRUNI1-BRUC14 | F13: 4529 | G13: 20272 | H13: 1997 | I13: 200514.41 | J13: 91692 | K13: 300158.14 | L13: 1.35 | M13: 4364 | N13: 193716 | O13: 360 | P13: =IFERROR(VLOOKUP(Tabela1[[#This Row],[TAG]],#REF!,14,FALSE),"") | Q13: =P13+P13 -> #VALUE! | R13: =Q13+P13 -> #VALUE! | S13: =R13+P13 -> #VALUE! | T13: =S13+P13 -> #VALUE! | U13: =T13+P13 -> #VALUE! | V13: =U13+P13 -> #VALUE! | W13: 729.83 | X13: 729.47 | Y13: 0.1 | Z13: =IF(Tabela1[[#This Row],[Ano Aquisição]]=2023,0,IFERROR(VLOOKUP(H13,inflação!$F:$H,3,FALSE),"")) -> 1.6129 | AA13: 0.8 | AB13: =I13*-1 -> -200514.41 | AC13: =-(((P13*$W13)+($X13*12))*((1+$Y13)^AC$1)) -> #VALUE! | AD13: =-((((Q13-P13)*$W13)+($X13*12))*((1+$Y13)^AD$1)) -> #VALUE! | AE13: =-((((R13-Q13)*$W13)+($X13*12))*((1+$Y13)^AE$1)) -> #VALUE! | AF13: =-((((S13-R13)*$W13)+($X13*12))*((1+$Y13)^AF$1)) -> #VALUE! | AG13: =-((((T13-S13)*$W13)+($X13*12))*((1+$Y13)^AG$1)) -> #VALUE! | AH13: =-((((U13-T13)*$W13)+($X13*12))*((1+$Y13)^AH$1)) -> #VALUE! | AI13: =-((((V13-U13)*$W13)+($X13*12))*((1+$Y13)^AI$1)) -> #VALUE! | AJ13: =-(I13*(1+Z13)) -> -523924.1 | AK13: =AC13*(1-$AA13) -> #VALUE! | AL13: =AD13*(1-$AA13) -> #VALUE! | AM13: =AE13*(1-$AA13) -> #VALUE! | AN13: =AF13*(1-$AA13) -> #VALUE! | AO13: =AG13*(1-$AA13) -> #VALUE! | AP13: =AH13*(1-$AA13) -> #VALUE! | AQ13: =AI13*(1-$AA13) -> #VALUE! | AR13: =(NPV(Y13,AK13,AL13,AM13,AN13,AO13,AP13,AQ13)+(SUM(AJ13,(J13*-1))))-(NPV(Y13,AC13,AD13,AE13,AF13,AG13,AH13,AI13)) -> #VALUE! | AS13: =SUM(AC13:AI13) -> #VALUE! | AT13: =SUM(AK13:AQ13) -> #VALUE! | AU13: =(((AVERAGE(AC13:AI13)/1000)-(AVERAGE(AK13:AQ13)/1000))+(((AJ13/1000)*-1)/7)+((J13/1000)/7))*-1 -> #VALUE! | AV13: =AU13/(((J13/1000)+((AJ13*-1)/1000))) -> #VALUE! | AW13: =IF(L13>1.1,"Fase de Degradação",IF(L13<1,"Confiabilidade em Crescimento","Fase de Vida Útil")) -> Fase de Degradação | AX13: =VLOOKUP(D13,#REF!,5,FALSE) -> #REF! | AZ13: X | BB13: =IFERROR(VLOOKUP(Tabela1[[#This Row],[Denominação]],[10]Planilha1!$A:$B,2,FALSE),"") -> 300158.14
A14: 13 | B14: BRU010 | C14: BRU010-BRUNIDORA | D14: 10000161 | E14: BR01-CIL-UCI-BRUNI2-BRUC12 | F14: 4529 | G14: 20137 | H14: 1997 | I14: 186725.04 | J14: 92275 | K14: 242532.76 | L14: 1.26 | M14: 4344 | N14: 197229 | O14: 383 | P14: =IFERROR(VLOOKUP(Tabela1[[#This Row],[TAG]],#REF!,14,FALSE),"") | Q14: =P14+P14 -> #VALUE! | R14: =Q14+P14 -> #VALUE! | S14: =R14+P14 -> #VALUE! | T14: =S14+P14 -> #VALUE! | U14: =T14+P14 -> #VALUE! | V14: =U14+P14 -> #VALUE! | W14: 212.67 | X14: 301.32 | Y14: 0.1 | Z14: =IF(Tabela1[[#This Row],[Ano Aquisição]]=2023,0,IFERROR(VLOOKUP(H14,inflação!$F:$H,3,FALSE),"")) -> 1.6129 | AA14: 0.8 | AB14: =I14*-1 -> -186725.04 | AC14: =-(((P14*$W14)+($X14*12))*((1+$Y14)^AC$1)) -> #VALUE! | AD14: =-((((Q14-P14)*$W14)+($X14*12))*((1+$Y14)^AD$1)) -> #VALUE! | AE14: =-((((R14-Q14)*$W14)+($X14*12))*((1+$Y14)^AE$1)) -> #VALUE! | AF14: =-((((S14-R14)*$W14)+($X14*12))*((1+$Y14)^AF$1)) -> #VALUE! | AG14: =-((((T14-S14)*$W14)+($X14*12))*((1+$Y14)^AG$1)) -> #VALUE! | AH14: =-((((U14-T14)*$W14)+($X14*12))*((1+$Y14)^AH$1)) -> #VALUE! | AI14: =-((((V14-U14)*$W14)+($X14*12))*((1+$Y14)^AI$1)) -> #VALUE! | AJ14: =-(I14*(1+Z14)) -> -487893.86 | AK14: =AC14*(1-$AA14) -> #VALUE! | AL14: =AD14*(1-$AA14) -> #VALUE! | AM14: =AE14*(1-$AA14) -> #VALUE! | AN14: =AF14*(1-$AA14) -> #VALUE! | AO14: =AG14*(1-$AA14) -> #VALUE! | AP14: =AH14*(1-$AA14) -> #VALUE! | AQ14: =AI14*(1-$AA14) -> #VALUE! | AR14: =(NPV(Y14,AK14,AL14,AM14,AN14,AO14,AP14,AQ14)+(SUM(AJ14,(J14*-1))))-(NPV(Y14,AC14,AD14,AE14,AF14,AG14,AH14,AI14)) -> #VALUE! | AS14: =SUM(AC14:AI14) -> #VALUE! | AT14: =SUM(AK14:AQ14) -> #VALUE! | AU14: =(((AVERAGE(AC14:AI14)/1000)-(AVERAGE(AK14:AQ14)/1000))+(((AJ14/1000)*-1)/7)+((J14/1000)/7))*-1 -> #VALUE! | AV14: =AU14/(((J14/1000)+((AJ14*-1)/1000))) -> #VALUE! | AW14: =IF(L14>1.1,"Fase de Degradação",IF(L14<1,"Confiabilidade em Crescimento","Fase de Vida Útil")) -> Fase de Degradação | AX14: =VLOOKUP(D14,#REF!,5,FALSE) -> #REF! | AZ14: X | BB14: =IFERROR(VLOOKUP(Tabela1[[#This Row],[Denominação]],[10]Planilha1!$A:$B,2,FALSE),"") -> 244315.57
A15: 14 | B15: BRU011 | C15: BRU011-BRUNIDORA | D15: 10000164 | E15: BR01-CIL-UCI-BRUNI2-BRUC12 | F15: 4529 | G15: 20289 | H15: 1997 | I15: 247380.04 | J15: 100505 | K15: 281713.41 | L15: 1.47 | M15: 4221 | N15: 198185 | O15: 532 | P15: =IFERROR(VLOOKUP(Tabela1[[#This Row],[TAG]],#REF!,14,FALSE),"") | Q15: =P15+P15 -> #VALUE! | R15: =Q15+P15 -> #VALUE! | S15: =R15+P15 -> #VALUE! | T15: =S15+P15 -> #VALUE! | U15: =T15+P15 -> #VALUE! | V15: =U15+P15 -> #VALUE! | W15: 721.72 | X15: 1016.82 | Y15: 0.1 | Z15: =IF(Tabela1[[#This Row],[Ano Aquisição]]=2023,0,IFERROR(VLOOKUP(H15,inflação!$F:$H,3,FALSE),"")) -> 1.6129 | AA15: 0.8 | AB15: =I15*-1 -> -247380.04 | AC15: =-(((P15*$W15)+($X15*12))*((1+$Y15)^AC$1)) -> #VALUE! | AD15: =-((((Q15-P15)*$W15)+($X15*12))*((1+$Y15)^AD$1)) -> #VALUE! | AE15: =-((((R15-Q15)*$W15)+($X15*12))*((1+$Y15)^AE$1)) -> #VALUE! | AF15: =-((((S15-R15)*$W15)+($X15*12))*((1+$Y15)^AF$1)) -> #VALUE! | AG15: =-((((T15-S15)*$W15)+($X15*12))*((1+$Y15)^AG$1)) -> #VALUE! | AH15: =-((((U15-T15)*$W15)+($X15*12))*((1+$Y15)^AH$1)) -> #VALUE! | AI15: =-((((V15-U15)*$W15)+($X15*12))*((1+$Y15)^AI$1)) -> #VALUE! | AJ15: =-(I15*(1+Z15)) -> -646379.31 | AK15: =AC15*(1-$AA15) -> #VALUE! | AL15: =AD15*(1-$AA15) -> #VALUE! | AM15: =AE15*(1-$AA15) -> #VALUE! | AN15: =AF15*(1-$AA15) -> #VALUE! | AO15: =AG15*(1-$AA15) -> #VALUE! | AP15: =AH15*(1-$AA15) -> #VALUE! | AQ15: =AI15*(1-$AA15) -> #VALUE! | AR15: =(NPV(Y15,AK15,AL15,AM15,AN15,AO15,AP15,AQ15)+(SUM(AJ15,(J15*-1))))-(NPV(Y15,AC15,AD15,AE15,AF15,AG15,AH15,AI15)) -> #VALUE! | AS15: =SUM(AC15:AI15) -> #VALUE! | AT15: =SUM(AK15:AQ15) -> #VALUE! | AU15: =(((AVERAGE(AC15:AI15)/1000)-(AVERAGE(AK15:AQ15)/1000))+(((AJ15/1000)*-1)/7)+((J15/1000)/7))*-1 -> #VALUE! | AV15: =AU15/(((J15/1000)+((AJ15*-1)/1000))) -> #VALUE! | AW15: =IF(L15>1.1,"Fase de Degradação",IF(L15<1,"Confiabilidade em Crescimento","Fase de Vida Útil")) -> Fase de Degradação | AX15: =VLOOKUP(D15,#REF!,5,FALSE) -> #REF! | AZ15: X | BB15: =IFERROR(VLOOKUP(Tabela1[[#This Row],[Denominação]],[10]Planilha1!$A:$B,2,FALSE),"") -> 281713.41
A16: 15 | B16: BRU012 | C16: BRU012-BRUNIDORA | D16: 10000167 | E16: BR01-CIL-UCI-BRUNI1-BRUC05 | F16: 4529 | G16: 20287 | H16: 1997 | I16: 85086.56 | J16: 6758 | K16: 169978.85 | L16: 1.36 | M16: 4464 | N16: 193826 | O16: 321 | P16: =IFERROR(VLOOKUP(Tabela1[[#This Row],[TAG]],#REF!,14,FALSE),"") | Q16: =P16+P16 -> #VALUE! | R16: =Q16+P16 -> #VALUE! | S16: =R16+P16 -> #VALUE! | T16: =S16+P16 -> #VALUE! | U16: =T16+P16 -> #VALUE! | V16: =U16+P16 -> #VALUE! | W16: 293.88 | X16: 532.11 | Y16: 0.1 | Z16: =IF(Tabela1[[#This Row],[Ano Aquisição]]=2023,0,IFERROR(VLOOKUP(H16,inflação!$F:$H,3,FALSE),"")) -> 1.6129 | AA16: 0.8 | AB16: =I16*-1 -> -85086.56 | AC16: =-(((P16*$W16)+($X16*12))*((1+$Y16)^AC$1)) -> #VALUE! | AD16: =-((((Q16-P16)*$W16)+($X16*12))*((1+$Y16)^AD$1)) -> #VALUE! | AE16: =-((((R16-Q16)*$W16)+($X16*12))*((1+$Y16)^AE$1)) -> #VALUE! | AF16: =-((((S16-R16)*$W16)+($X16*12))*((1+$Y16)^AF$1)) -> #VALUE! | AG16: =-((((T16-S16)*$W16)+($X16*12))*((1+$Y16)^AG$1)) -> #VALUE! | AH16: =-((((U16-T16)*$W16)+($X16*12))*((1+$Y16)^AH$1)) -> #VALUE! | AI16: =-((((V16-U16)*$W16)+($X16*12))*((1+$Y16)^AI$1)) -> #VALUE! | AJ16: =-(I16*(1+Z16)) -> -222322.67 | AK16: =AC16*(1-$AA16) -> #VALUE! | AL16: =AD16*(1-$AA16) -> #VALUE! | AM16: =AE16*(1-$AA16) -> #VALUE! | AN16: =AF16*(1-$AA16) -> #VALUE! | AO16: =AG16*(1-$AA16) -> #VALUE! | AP16: =AH16*(1-$AA16) -> #VALUE! | AQ16: =AI16*(1-$AA16) -> #VALUE! | AR16: =(NPV(Y16,AK16,AL16,AM16,AN16,AO16,AP16,AQ16)+(SUM(AJ16,(J16*-1))))-(NPV(Y16,AC16,AD16,AE16,AF16,AG16,AH16,AI16)) -> #VALUE! | AS16: =SUM(AC16:AI16) -> #VALUE! | AT16: =SUM(AK16:AQ16) -> #VALUE! | AU16: =(((AVERAGE(AC16:AI16)/1000)-(AVERAGE(AK16:AQ16)/1000))+(((AJ16/1000)*-1)/7)+((J16/1000)/7))*-1 -> #VALUE! | AV16: =AU16/(((J16/1000)+((AJ16*-1)/1000))) -> #VALUE! | AW16: =IF(L16>1.1,"Fase de Degradação",IF(L16<1,"Confiabilidade em Crescimento","Fase de Vida Útil")) -> Fase de Degradação | AX16: =VLOOKUP(D16,#REF!,5,FALSE) -> #REF! | AZ16: X | BB16: =IFERROR(VLOOKUP(Tabela1[[#This Row],[Denominação]],[10]Planilha1!$A:$B,2,FALSE),"") -> 169978.85
A17: 16 | B17: BRU014 | C17: BRU014-BRUNIDORA | D17: 10001685 | E17: BR01-CIL-UCI-BRUNI1-BRUC04 | F17: 4529 | G17: 20242 | H17: 1996 | I17: 226912.44 | J17: 90604 | K17: 188408.23 | L17: 1.39 | M17: 4114 | N17: 191458 | O17: 318 | P17: =IFERROR(VLOOKUP(Tabela1[[#This Row],[TAG]],#REF!,14,FALSE),"") | Q17: =P17+P17 -> #VALUE! | R17: =Q17+P17 -> #VALUE! | S17: =R17+P17 -> #VALUE! | T17: =S17+P17 -> #VALUE! | U17: =T17+P17 -> #VALUE! | V17: =U17+P17 -> #VALUE! | W17: 192.59 | X17: 281.29 | Y17: 0.1 | Z17: =IF(Tabela1[[#This Row],[Ano Aquisição]]=2023,0,IFERROR(VLOOKUP(H17,inflação!$F:$H,3,FALSE),"")) -> 1.7085 | AA17: 0.8 | AB17: =I17*-1 -> -226912.44 | AC17: =-(((P17*$W17)+($X17*12))*((1+$Y17)^AC$1)) -> #VALUE! | AD17: =-((((Q17-P17)*$W17)+($X17*12))*((1+$Y17)^AD$1)) -> #VALUE! | AE17: =-((((R17-Q17)*$W17)+($X17*12))*((1+$Y17)^AE$1)) -> #VALUE! | AF17: =-((((S17-R17)*$W17)+($X17*12))*((1+$Y17)^AF$1)) -> #VALUE! | AG17: =-((((T17-S17)*$W17)+($X17*12))*((1+$Y17)^AG$1)) -> #VALUE! | AH17: =-((((U17-T17)*$W17)+($X17*12))*((1+$Y17)^AH$1)) -> #VALUE! | AI17: =-((((V17-U17)*$W17)+($X17*12))*((1+$Y17)^AI$1)) -> #VALUE! | AJ17: =-(I17*(1+Z17)) -> -614592.34 | AK17: =AC17*(1-$AA17) -> #VALUE! | AL17: =AD17*(1-$AA17) -> #VALUE! | AM17: =AE17*(1-$AA17) -> #VALUE! | AN17: =AF17*(1-$AA17) -> #VALUE! | AO17: =AG17*(1-$AA17) -> #VALUE! | AP17: =AH17*(1-$AA17) -> #VALUE! | AQ17: =AI17*(1-$AA17) -> #VALUE! | AR17: =(NPV(Y17,AK17,AL17,AM17,AN17,AO17,AP17,AQ17)+(SUM(AJ17,(J17*-1))))-(NPV(Y17,AC17,AD17,AE17,AF17,AG17,AH17,AI17)) -> #VALUE! | AS17: =SUM(AC17:AI17) -> #VALUE! | AT17: =SUM(AK17:AQ17) -> #VALUE! | AU17: =(((AVERAGE(AC17:AI17)/1000)-(AVERAGE(AK17:AQ17)/1000))+(((AJ17/1000)*-1)/7)+((J17/1000)/7))*-1 -> #VALUE! | AV17: =AU17/(((J17/1000)+((AJ17*-1)/1000))) -> #VALUE! | AW17: =IF(L17>1.1,"Fase de Degradação",IF(L17<1,"Confiabilidade em Crescimento","Fase de Vida Útil")) -> Fase de Degradação | AX17: =VLOOKUP(D17,#REF!,5,FALSE) -> #REF! | AZ17: X | BB17: =IFERROR(VLOOKUP(Tabela1[[#This Row],[Denominação]],[10]Planilha1!$A:$B,2,FALSE),"") -> 188408.23
A18: 17 | B18: BRU024 | C18: BRU024-BRUNIDORA | D18: 10004194 | E18: BR01-CIL-UCI-BRUNI1-BRUC01 | F18: 4529 | G18: 34087 | H18: 2006 | I18: 389350.45 | J18: 0 | K18: 285408.28 | L18: 1.64 | M18: 4453 | N18: 146830 | O18: 554 | P18: =IFERROR(VLOOKUP(Tabela1[[#This Row],[TAG]],#REF!,14,FALSE),"") | Q18: =P18+P18 -> #VALUE! | R18: =Q18+P18 -> #VALUE! | S18: =R18+P18 -> #VALUE! | T18: =S18+P18 -> #VALUE! | U18: =T18+P18 -> #VALUE! | V18: =U18+P18 -> #VALUE! | W18: 353.53 | X18: 1407.9 | Y18: 0.1 | Z18: =IF(Tabela1[[#This Row],[Ano Aquisição]]=2023,0,IFERROR(VLOOKUP(H18,inflação!$F:$H,3,FALSE),"")) -> 0.9672 | AA18: 0.8 | AB18: =I18*-1 -> -389350.45 | AC18: =-(((P18*$W18)+($X18*12))*((1+$Y18)^AC$1)) -> #VALUE! | AD18: =-((((Q18-P18)*$W18)+($X18*12))*((1+$Y18)^AD$1)) -> #VALUE! | AE18: =-((((R18-Q18)*$W18)+($X18*12))*((1+$Y18)^AE$1)) -> #VALUE! | AF18: =-((((S18-R18)*$W18)+($X18*12))*((1+$Y18)^AF$1)) -> #VALUE! | AG18: =-((((T18-S18)*$W18)+($X18*12))*((1+$Y18)^AG$1)) -> #VALUE! | AH18: =-((((U18-T18)*$W18)+($X18*12))*((1+$Y18)^AH$1)) -> #VALUE! | AI18: =-((((V18-U18)*$W18)+($X18*12))*((1+$Y18)^AI$1)) -> #VALUE! | AJ18: =-(I18*(1+Z18)) -> -765930.21 | AK18: =AC18*(1-$AA18) -> #VALUE! | AL18: =AD18*(1-$AA18) -> #VALUE! | AM18: =AE18*(1-$AA18) -> #VALUE! | AN18: =AF18*(1-$AA18) -> #VALUE! | AO18: =AG18*(1-$AA18) -> #VALUE! | AP18: =AH18*(1-$AA18) -> #VALUE! | AQ18: =AI18*(1-$AA18) -> #VALUE! | AR18: =(NPV(Y18,AK18,AL18,AM18,AN18,AO18,AP18,AQ18)+(SUM(AJ18,(J18*-1))))-(NPV(Y18,AC18,AD18,AE18,AF18,AG18,AH18,AI18)) -> #VALUE! | AS18: =SUM(AC18:AI18) -> #VALUE! | AT18: =SUM(AK18:AQ18) -> #VALUE! | AU18: =(((AVERAGE(AC18:AI18)/1000)-(AVERAGE(AK18:AQ18)/1000))+(((AJ18/1000)*-1)/7)+((J18/1000)/7))*-1 -> #VALUE! | AV18: =AU18/(((J18/1000)+((AJ18*-1)/1000))) -> #VALUE! | AW18: =IF(L18>1.1,"Fase de Degradação",IF(L18<1,"Confiabilidade em Crescimento","Fase de Vida Útil")) -> Fase de Degradação | AX18: =VLOOKUP(D18,#REF!,5,FALSE) -> #REF! | AZ18: X | BB18: =IFERROR(VLOOKUP(Tabela1[[#This Row],[Denominação]],[10]Planilha1!$A:$B,2,FALSE),"") -> 285408.28
A19: 18 | B19: BRU025 | C19: BRU025-BRUNIDORA | D19: 10004195 | E19: BR01-CIL-UCI-BRUNI1-BRUC03 | F19: 4529 | G19: 34519 | H19: 2006 | I19: 434615.76 | J19: 101994 | K19: 101310.55 | L19: 0.93 | M19: 4464 | N19: 143533 | O19: 263 | P19: =IFERROR(VLOOKUP(Tabela1[[#This Row],[TAG]],#REF!,14,FALSE),"") | Q19: =P19+P19 -> #VALUE! | R19: =Q19+P19 -> #VALUE! | S19: =R19+P19 -> #VALUE! | T19: =S19+P19 -> #VALUE! | U19: =T19+P19 -> #VALUE! | V19: =U19+P19 -> #VALUE! | W19: 198.64 | X19: 246.27 | Y19: 0.1 | Z19: =IF(Tabela1[[#This Row],[Ano Aquisição]]=2023,0,IFERROR(VLOOKUP(H19,inflação!$F:$H,3,FALSE),"")) -> 0.9672 | AA19: 0.8 | AB19: =I19*-1 -> -434615.76 | AC19: =-(((P19*$W19)+($X19*12))*((1+$Y19)^AC$1)) -> #VALUE! | AD19: =-((((Q19-P19)*$W19)+($X19*12))*((1+$Y19)^AD$1)) -> #VALUE! | AE19: =-((((R19-Q19)*$W19)+($X19*12))*((1+$Y19)^AE$1)) -> #VALUE! | AF19: =-((((S19-R19)*$W19)+($X19*12))*((1+$Y19)^AF$1)) -> #VALUE! | AG19: =-((((T19-S19)*$W19)+($X19*12))*((1+$Y19)^AG$1)) -> #VALUE! | AH19: =-((((U19-T19)*$W19)+($X19*12))*((1+$Y19)^AH$1)) -> #VALUE! | AI19: =-((((V19-U19)*$W19)+($X19*12))*((1+$Y19)^AI$1)) -> #VALUE! | AJ19: =-(I19*(1+Z19)) -> -854976.12 | AK19: =AC19*(1-$AA19) -> #VALUE! | AL19: =AD19*(1-$AA19) -> #VALUE! | AM19: =AE19*(1-$AA19) -> #VALUE! | AN19: =AF19*(1-$AA19) -> #VALUE! | AO19: =AG19*(1-$AA19) -> #VALUE! | AP19: =AH19*(1-$AA19) -> #VALUE! | AQ19: =AI19*(1-$AA19) -> #VALUE! | AR19: =(NPV(Y19,AK19,AL19,AM19,AN19,AO19,AP19,AQ19)+(SUM(AJ19,(J19*-1))))-(NPV(Y19,AC19,AD19,AE19,AF19,AG19,AH19,AI19)) -> #VALUE! | AS19: =SUM(AC19:AI19) -> #VALUE! | AT19: =SUM(AK19:AQ19) -> #VALUE! | AU19: =(((AVERAGE(AC19:AI19)/1000)-(AVERAGE(AK19:AQ19)/1000))+(((AJ19/1000)*-1)/7)+((J19/1000)/7))*-1 -> #VALUE! | AV19: =AU19/(((J19/1000)+((AJ19*-1)/1000))) -> #VALUE! | AW19: =IF(L19>1.1,"Fase de Degradação",IF(L19<1,"Confiabilidade em Crescimento","Fase de Vida Útil")) -> Confiabilidade em Crescimento | AX19: =VLOOKUP(D19,#REF!,5,FALSE) -> #REF! | AZ19: X | BB19: =IFERROR(VLOOKUP(Tabela1[[#This Row],[Denominação]],[10]Planilha1!$A:$B,2,FALSE),"") -> 101310.55
A20: 19 | B20: BRU026 | C20: BRU026-BRUNIDORA | D20: 10004196 | E20: BR01-CIL-UCI-BRUNI1-BRUC01 | F20: 4529 | G20: 34518 | H20: 2006 | I20: 226304.29 | J20: 0 | K20: 162526.92 | L20: 1.19 | M20: 4453 | N20: 144394 | O20: 339 | P20: =IFERROR(VLOOKUP(Tabela1[[#This Row],[TAG]],#REF!,14,FALSE),"") | Q20: =P20+P20 -> #VALUE! | R20: =Q20+P20 -> #VALUE! | S20: =R20+P20 -> #VALUE! | T20: =S20+P20 -> #VALUE! | U20: =T20+P20 -> #VALUE! | V20: =U20+P20 -> #VALUE! | W20: 333.39 | X20: 641.31 | Y20: 0.1 | Z20: =IF(Tabela1[[#This Row],[Ano Aquisição]]=2023,0,IFERROR(VLOOKUP(H20,inflação!$F:$H,3,FALSE),"")) -> 0.9672 | AA20: 0.8 | AB20: =I20*-1 -> -226304.29 | AC20: =-(((P20*$W20)+($X20*12))*((1+$Y20)^AC$1)) -> #VALUE! | AD20: =-((((Q20-P20)*$W20)+($X20*12))*((1+$Y20)^AD$1)) -> #VALUE! | AE20: =-((((R20-Q20)*$W20)+($X20*12))*((1+$Y20)^AE$1)) -> #VALUE! | AF20: =-((((S20-R20)*$W20)+($X20*12))*((1+$Y20)^AF$1)) -> #VALUE! | AG20: =-((((T20-S20)*$W20)+($X20*12))*((1+$Y20)^AG$1)) -> #VALUE! | AH20: =-((((U20-T20)*$W20)+($X20*12))*((1+$Y20)^AH$1)) -> #VALUE! | AI20: =-((((V20-U20)*$W20)+($X20*12))*((1+$Y20)^AI$1)) -> #VALUE! | AJ20: =-(I20*(1+Z20)) -> -445185.8 | AK20: =AC20*(1-$AA20) -> #VALUE! | AL20: =AD20*(1-$AA20) -> #VALUE! | AM20: =AE20*(1-$AA20) -> #VALUE! | AN20: =AF20*(1-$AA20) -> #VALUE! | AO20: =AG20*(1-$AA20) -> #VALUE! | AP20: =AH20*(1-$AA20) -> #VALUE! | AQ20: =AI20*(1-$AA20) -> #VALUE! | AR20: =(NPV(Y20,AK20,AL20,AM20,AN20,AO20,AP20,AQ20)+(SUM(AJ20,(J20*-1))))-(NPV(Y20,AC20,AD20,AE20,AF20,AG20,AH20,AI20)) -> #VALUE! | AS20: =SUM(AC20:AI20) -> #VALUE! | AT20: =SUM(AK20:AQ20) -> #VALUE! | AU20: =(((AVERAGE(AC20:AI20)/1000)-(AVERAGE(AK20:AQ20)/1000))+(((AJ20/1000)*-1)/7)+((J20/1000)/7))*-1 -> #VALUE! | AV20: =AU20/(((J20/1000)+((AJ20*-1)/1000))) -> #VALUE! | AW20: =IF(L20>1.1,"Fase de Degradação",IF(L20<1,"Confiabilidade em Crescimento","Fase de Vida Útil")) -> Fase de Degradação | AX20: =VLOOKUP(D20,#REF!,5,FALSE) -> #REF! | AZ20: X | BB20: =IFERROR(VLOOKUP(Tabela1[[#This Row],[Denominação]],[10]Planilha1!$A:$B,2,FALSE),"") -> 162526.92
A21: 20 | B21: BRU027 | C21: BRU027-BRUNIDORA | D21: 10004197 | E21: BR01-CIL-UCI-BRUNI1-BRUC08 | F21: 4529 | G21: 34517 | H21: 2006 | I21: 223343.06 | J21: 0 | K21: 215121.62 | L21: 1.62 | M21: 4073 | N21: 142548 | O21: 361 | P21: =IFERROR(VLOOKUP(Tabela1[[#This Row],[TAG]],#REF!,14,FALSE),"") | Q21: =P21+P21 -> #VALUE! | R21: =Q21+P21 -> #VALUE! | S21: =R21+P21 -> #VALUE! | T21: =S21+P21 -> #VALUE! | U21: =T21+P21 -> #VALUE! | V21: =U21+P21 -> #VALUE! | W21: 329.38 | X21: 820.22 | Y21: 0.1 | Z21: =IF(Tabela1[[#This Row],[Ano Aquisição]]=2023,0,IFERROR(VLOOKUP(H21,inflação!$F:$H,3,FALSE),"")) -> 0.9672 | AA21: 0.8 | AB21: =I21*-1 -> -223343.06 | AC21: =-(((P21*$W21)+($X21*12))*((1+$Y21)^AC$1)) -> #VALUE! | AD21: =-((((Q21-P21)*$W21)+($X21*12))*((1+$Y21)^AD$1)) -> #VALUE! | AE21: =-((((R21-Q21)*$W21)+($X21*12))*((1+$Y21)^AE$1)) -> #VALUE! | AF21: =-((((S21-R21)*$W21)+($X21*12))*((1+$Y21)^AF$1)) -> #VALUE! | AG21: =-((((T21-S21)*$W21)+($X21*12))*((1+$Y21)^AG$1)) -> #VALUE! | AH21: =-((((U21-T21)*$W21)+($X21*12))*((1+$Y21)^AH$1)) -> #VALUE! | AI21: =-((((V21-U21)*$W21)+($X21*12))*((1+$Y21)^AI$1)) -> #VALUE! | AJ21: =-(I21*(1+Z21)) -> -439360.47 | AK21: =AC21*(1-$AA21) -> #VALUE! | AL21: =AD21*(1-$AA21) -> #VALUE! | AM21: =AE21*(1-$AA21) -> #VALUE! | AN21: =AF21*(1-$AA21) -> #VALUE! | AO21: =AG21*(1-$AA21) -> #VALUE! | AP21: =AH21*(1-$AA21) -> #VALUE! | AQ21: =AI21*(1-$AA21) -> #VALUE! | AR21: =(NPV(Y21,AK21,AL21,AM21,AN21,AO21,AP21,AQ21)+(SUM(AJ21,(J21*-1))))-(NPV(Y21,AC21,AD21,AE21,AF21,AG21,AH21,AI21)) -> #VALUE! | AS21: =SUM(AC21:AI21) -> #VALUE! | AT21: =SUM(AK21:AQ21) -> #VALUE! | AU21: =(((AVERAGE(AC21:AI21)/1000)-(AVERAGE(AK21:AQ21)/1000))+(((AJ21/1000)*-1)/7)+((J21/1000)/7))*-1 -> #VALUE! | AV21: =AU21/(((J21/1000)+((AJ21*-1)/1000))) -> #VALUE! | AW21: =IF(L21>1.1,"Fase de Degradação",IF(L21<1,"Confiabilidade em Crescimento","Fase de Vida Útil")) -> Fase de Degradação | AX21: =VLOOKUP(D21,#REF!,5,FALSE) -> #REF! | AZ21: X | BB21: =IFERROR(VLOOKUP(Tabela1[[#This Row],[Denominação]],[10]Planilha1!$A:$B,2,FALSE),"") -> 215121.62
A22: 21 | B22: BRU028 | C22: BRU028-BRUNIDORA | D22: 10004198 | E22: BR01-CIL-UCI-BRUNI1-BRUC08 | F22: 4529 | G22: 34521 | H22: 2006 | I22: 378425.24 | J22: 0 | K22: 296544.75 | L22: 1.43 | M22: 4073 | N22: 144668 | O22: 367 | P22: =IFERROR(VLOOKUP(Tabela1[[#This Row],[TAG]],#REF!,14,FALSE),"") | Q22: =P22+P22 -> #VALUE! | R22: =Q22+P22 -> #VALUE! | S22: =R22+P22 -> #VALUE! | T22: =S22+P22 -> #VALUE! | U22: =T22+P22 -> #VALUE! | V22: =U22+P22 -> #VALUE! | W22: 340.53 | X22: 891.41 | Y22: 0.1 | Z22: =IF(Tabela1[[#This Row],[Ano Aquisição]]=2023,0,IFERROR(VLOOKUP(H22,inflação!$F:$H,3,FALSE),"")) -> 0.9672 | AA22: 0.8 | AB22: =I22*-1 -> -378425.24 | AC22: =-(((P22*$W22)+($X22*12))*((1+$Y22)^AC$1)) -> #VALUE! | AD22: =-((((Q22-P22)*$W22)+($X22*12))*((1+$Y22)^AD$1)) -> #VALUE! | AE22: =-((((R22-Q22)*$W22)+($X22*12))*((1+$Y22)^AE$1)) -> #VALUE! | AF22: =-((((S22-R22)*$W22)+($X22*12))*((1+$Y22)^AF$1)) -> #VALUE! | AG22: =-((((T22-S22)*$W22)+($X22*12))*((1+$Y22)^AG$1)) -> #VALUE! | AH22: =-((((U22-T22)*$W22)+($X22*12))*((1+$Y22)^AH$1)) -> #VALUE! | AI22: =-((((V22-U22)*$W22)+($X22*12))*((1+$Y22)^AI$1)) -> #VALUE! | AJ22: =-(I22*(1+Z22)) -> -744438.13 | AK22: =AC22*(1-$AA22) -> #VALUE! | AL22: =AD22*(1-$AA22) -> #VALUE! | AM22: =AE22*(1-$AA22) -> #VALUE! | AN22: =AF22*(1-$AA22) -> #VALUE! | AO22: =AG22*(1-$AA22) -> #VALUE! | AP22: =AH22*(1-$AA22) -> #VALUE! | AQ22: =AI22*(1-$AA22) -> #VALUE! | AR22: =(NPV(Y22,AK22,AL22,AM22,AN22,AO22,AP22,AQ22)+(SUM(AJ22,(J22*-1))))-(NPV(Y22,AC22,AD22,AE22,AF22,AG22,AH22,AI22)) -> #VALUE! | AS22: =SUM(AC22:AI22) -> #VALUE! | AT22: =SUM(AK22:AQ22) -> #VALUE! | AU22: =(((AVERAGE(AC22:AI22)/1000)-(AVERAGE(AK22:AQ22)/1000))+(((AJ22/1000)*-1)/7)+((J22/1000)/7))*-1 -> #VALUE! | AV22: =AU22/(((J22/1000)+((AJ22*-1)/1000))) -> #VALUE! | AW22: =IF(L22>1.1,"Fase de Degradação",IF(L22<1,"Confiabilidade em Crescimento","Fase de Vida Útil")) -> Fase de Degradação | AX22: =VLOOKUP(D22,#REF!,5,FALSE) -> #REF! | AZ22: X | BB22: =IFERROR(VLOOKUP(Tabela1[[#This Row],[Denominação]],[10]Planilha1!$A:$B,2,FALSE),"") -> 296544.75
A23: 22 | B23: BRU029 | C23: BRU029-BRUNIDORA | D23: 10004199 | E23: BR01-CIL-UCI-BRUNI1-BRUC10 | F23: 4529 | G23: 34516 | H23: 2006 | I23: 220629.35 | J23: 0 | K23: 228075.13 | L23: 1.23 | M23: 4597 | N23: 142016 | O23: 311 | P23: =IFERROR(VLOOKUP(Tabela1[[#This Row],[TAG]],#REF!,14,FALSE),"") | Q23: =P23+P23 -> #VALUE! | R23: =Q23+P23 -> #VALUE! | S23: =R23+P23 -> #VALUE! | T23: =S23+P23 -> #VALUE! | U23: =T23+P23 -> #VALUE! | V23: =U23+P23 -> #VALUE! | W23: 356.88 | X23: 1048.25 | Y23: 0.1 | Z23: =IF(Tabela1[[#This Row],[Ano Aquisição]]=2023,0,IFERROR(VLOOKUP(H23,inflação!$F:$H,3,FALSE),"")) -> 0.9672 | AA23: 0.8 | AB23: =I23*-1 -> -220629.35 | AC23: =-(((P23*$W23)+($X23*12))*((1+$Y23)^AC$1)) -> #VALUE! | AD23: =-((((Q23-P23)*$W23)+($X23*12))*((1+$Y23)^AD$1)) -> #VALUE! | AE23: =-((((R23-Q23)*$W23)+($X23*12))*((1+$Y23)^AE$1)) -> #VALUE! | AF23: =-((((S23-R23)*$W23)+($X23*12))*((1+$Y23)^AF$1)) -> #VALUE! | AG23: =-((((T23-S23)*$W23)+($X23*12))*((1+$Y23)^AG$1)) -> #VALUE! | AH23: =-((((U23-T23)*$W23)+($X23*12))*((1+$Y23)^AH$1)) -> #VALUE! | AI23: =-((((V23-U23)*$W23)+($X23*12))*((1+$Y23)^AI$1)) -> #VALUE! | AJ23: =-(I23*(1+Z23)) -> -434022.06 | AK23: =AC23*(1-$AA23) -> #VALUE! | AL23: =AD23*(1-$AA23) -> #VALUE! | AM23: =AE23*(1-$AA23) -> #VALUE! | AN23: =AF23*(1-$AA23) -> #VALUE! | AO23: =AG23*(1-$AA23) -> #VALUE! | AP23: =AH23*(1-$AA23) -> #VALUE! | AQ23: =AI23*(1-$AA23) -> #VALUE! | AR23: =(NPV(Y23,AK23,AL23,AM23,AN23,AO23,AP23,AQ23)+(SUM(AJ23,(J23*-1))))-(NPV(Y23,AC23,AD23,AE23,AF23,AG23,AH23,AI23)) -> #VALUE! | AS23: =SUM(AC23:AI23) -> #VALUE! | AT23: =SUM(AK23:AQ23) -> #VALUE! | AU23: =(((AVERAGE(AC23:AI23)/1000)-(AVERAGE(AK23:AQ23)/1000))+(((AJ23/1000)*-1)/7)+((J23/1000)/7))*-1 -> #VALUE! | AV23: =AU23/(((J23/1000)+((AJ23*-1)/1000))) -> #VALUE! | AW23: =IF(L23>1.1,"Fase de Degradação",IF(L23<1,"Confiabilidade em Crescimento","Fase de Vida Útil")) -> Fase de Degradação | AX23: =VLOOKUP(D23,#REF!,5,FALSE) -> #REF! | AZ23: X | BB23: =IFERROR(VLOOKUP(Tabela1[[#This Row],[Denominação]],[10]Planilha1!$A:$B,2,FALSE),"") -> 228075.13
A24: 23 | B24: BRU030 | C24: BRU030-BRUNIDORA | D24: 10004200 | E24: BR01-CIL-UCI-BRUNI1-BRUC10 | F24: 4529 | G24: 34520 | H24: 2006 | I24: 386263.37 | J24: 0 | K24: 286543.54 | L24: 1.71 | M24: 4597 | N24: 143739 | O24: 429 | P24: =IFERROR(VLOOKUP(Tabela1[[#This Row],[TAG]],#REF!,14,FALSE),"") | Q24: =P24+P24 -> #VALUE! | R24: =Q24+P24 -> #VALUE! | S24: =R24+P24 -> #VALUE! | T24: =S24+P24 -> #VALUE! | U24: =T24+P24 -> #VALUE! | V24: =U24+P24 -> #VALUE! | W24: 339.05 | X24: 1686.76 | Y24: 0.1 | Z24: =IF(Tabela1[[#This Row],[Ano Aquisição]]=2023,0,IFERROR(VLOOKUP(H24,inflação!$F:$H,3,FALSE),"")) -> 0.9672 | AA24: 0.8 | AB24: =I24*-1 -> -386263.37 | AC24: =-(((P24*$W24)+($X24*12))*((1+$Y24)^AC$1)) -> #VALUE! | AD24: =-((((Q24-P24)*$W24)+($X24*12))*((1+$Y24)^AD$1)) -> #VALUE! | AE24: =-((((R24-Q24)*$W24)+($X24*12))*((1+$Y24)^AE$1)) -> #VALUE! | AF24: =-((((S24-R24)*$W24)+($X24*12))*((1+$Y24)^AF$1)) -> #VALUE! | AG24: =-((((T24-S24)*$W24)+($X24*12))*((1+$Y24)^AG$1)) -> #VALUE! | AH24: =-((((U24-T24)*$W24)+($X24*12))*((1+$Y24)^AH$1)) -> #VALUE! | AI24: =-((((V24-U24)*$W24)+($X24*12))*((1+$Y24)^AI$1)) -> #VALUE! | AJ24: =-(I24*(1+Z24)) -> -759857.3 | AK24: =AC24*(1-$AA24) -> #VALUE! | AL24: =AD24*(1-$AA24) -> #VALUE! | AM24: =AE24*(1-$AA24) -> #VALUE! | AN24: =AF24*(1-$AA24) -> #VALUE! | AO24: =AG24*(1-$AA24) -> #VALUE! | AP24: =AH24*(1-$AA24) -> #VALUE! | AQ24: =AI24*(1-$AA24) -> #VALUE! | AR24: =(NPV(Y24,AK24,AL24,AM24,AN24,AO24,AP24,AQ24)+(SUM(AJ24,(J24*-1))))-(NPV(Y24,AC24,AD24,AE24,AF24,AG24,AH24,AI24)) -> #VALUE! | AS24: =SUM(AC24:AI24) -> #VALUE! | AT24: =SUM(AK24:AQ24) -> #VALUE! | AU24: =(((AVERAGE(AC24:AI24)/1000)-(AVERAGE(AK24:AQ24)/1000))+(((AJ24/1000)*-1)/7)+((J24/1000)/7))*-1 -> #VALUE! | AV24: =AU24/(((J24/1000)+((AJ24*-1)/1000))) -> #VALUE! | AW24: =IF(L24>1.1,"Fase de Degradação",IF(L24<1,"Confiabilidade em Crescimento","Fase de Vida Útil")) -> Fase de Degradação | AX24: =VLOOKUP(D24,#REF!,5,FALSE) -> #REF! | AZ24: X | BB24: =IFERROR(VLOOKUP(Tabela1[[#This Row],[Denominação]],[10]Planilha1!$A:$B,2,FALSE),"") -> 286543.54
... A57: 56 | B57: BRU063 | C57: BRU063-BRUNIDORA | D57: 10006697 | E57: BR01-CIL-UCI-BRUNI2-BRUC29 | F57: 4529 | G57: 55196 | H57: 2021 | I57: 867358.81 | J57: 757761 | K57: 3980.88 | L57: 0.48 | M57: 5030 | N57: 13606 | O57: 15 | P57: =IFERROR(VLOOKUP(Tabela1[[#This Row],[TAG]],#REF!,14,FALSE),"") | Q57: =P57+P57 -> #VALUE! | R57: =Q57+P57 -> #VALUE! | S57: =R57+P57 -> #VALUE! | T57: =S57+P57 -> #VALUE! | U57: =T57+P57 -> #VALUE! | V57: =U57+P57 -> #VALUE! | W57: 463.26 | X57: 516.58 | Y57: 0.1 | Z57: =IF(Tabela1[[#This Row],[Ano Aquisição]]=2023,0,IFERROR(VLOOKUP(H57,inflação!$F:$H,3,FALSE),"")) -> 0.1585 | AA57: 0.8 | AB57: =I57*-1 -> -867358.81 | AC57: =-(((P57*$W57)+($X57*12))*((1+$Y57)^AC$1)) -> #VALUE! | AD57: =-((((Q57-P57)*$W57)+($X57*12))*((1+$Y57)^AD$1)) -> #VALUE! | AE57: =-((((R57-Q57)*$W57)+($X57*12))*((1+$Y57)^AE$1)) -> #VALUE! | AF57: =-((((S57-R57)*$W57)+($X57*12))*((1+$Y57)^AF$1)) -> #VALUE! | AG57: =-((((T57-S57)*$W57)+($X57*12))*((1+$Y57)^AG$1)) -> #VALUE! | AH57: =-((((U57-T57)*$W57)+($X57*12))*((1+$Y57)^AH$1)) -> #VALUE! | AI57: =-((((V57-U57)*$W57)+($X57*12))*((1+$Y57)^AI$1)) -> #VALUE! | AJ57: =-(I57*(1+Z57)) -> -1004835.2 | AK57: =AC57*(1-$AA57) -> #VALUE! | AL57: =AD57*(1-$AA57) -> #VALUE! | AM57: =AE57*(1-$AA57) -> #VALUE! | AN57: =AF57*(1-$AA57) -> #VALUE! | AO57: =AG57*(1-$AA57) -> #VALUE! | AP57: =AH57*(1-$AA57) -> #VALUE! | AQ57: =AI57*(1-$AA57) -> #VALUE! | AR57: =(NPV(Y57,AK57,AL57,AM57,AN57,AO57,AP57,AQ57)+(SUM(AJ57,(J57*-1))))-(NPV(Y57,AC57,AD57,AE57,AF57,AG57,AH57,AI57)) -> #VALUE! | AS57: =SUM(AC57:AI57) -> #VALUE! | AT57: =SUM(AK57:AQ57) -> #VALUE! | AU57: =(((AVERAGE(AC57:AI57)/1000)-(AVERAGE(AK57:AQ57)/1000))+(((AJ57/1000)*-1)/7)+((J57/1000)/7))*-1 -> #VALUE! | AV57: =AU57/(((J57/1000)+((AJ57*-1)/1000))) -> #VALUE! | AW57: =IF(L57>1.1,"Fase de Degradação",IF(L57<1,"Confiabilidade em Crescimento","Fase de Vida Útil")) -> Confiabilidade em Crescimento | AX57: =VLOOKUP(D57,#REF!,5,FALSE) -> #REF! | AZ57: X | BB57: =IFERROR(VLOOKUP(Tabela1[[#This Row],[Denominação]],[10]Planilha1!$A:$B,2,FALSE),"") -> 3980.88
A58: 57 | B58: BRU064 | C58: BRU064-BRUNIDORA | D58: 10006699 | E58: BR01-CIL-UCI-BRUNI2-BRUC29 | F58: 4529 | G58: 55195 | H58: 2021 | I58: 674489.51 | J58: 589263 | K58: 0 | L58: 0.7 | M58: 5030 | N58: 8209 | O58: 6 | P58: =IFERROR(VLOOKUP(Tabela1[[#This Row],[TAG]],#REF!,14,FALSE),"") | Q58: =P58+P58 -> #VALUE! | R58: =Q58+P58 -> #VALUE! | S58: =R58+P58 -> #VALUE! | T58: =S58+P58 -> #VALUE! | U58: =T58+P58 -> #VALUE! | V58: =U58+P58 -> #VALUE! | Y58: 0.1 | Z58: =IF(Tabela1[[#This Row],[Ano Aquisição]]=2023,0,IFERROR(VLOOKUP(H58,inflação!$F:$H,3,FALSE),"")) -> 0.1585 | AA58: 0.8 | AB58: =I58*-1 -> -674489.51 | AC58: =-(((P58*$W58)+($X58*12))*((1+$Y58)^AC$1)) -> #VALUE! | AD58: =-((((Q58-P58)*$W58)+($X58*12))*((1+$Y58)^AD$1)) -> #VALUE! | AE58: =-((((R58-Q58)*$W58)+($X58*12))*((1+$Y58)^AE$1)) -> #VALUE! | AF58: =-((((S58-R58)*$W58)+($X58*12))*((1+$Y58)^AF$1)) -> #VALUE! | AG58: =-((((T58-S58)*$W58)+($X58*12))*((1+$Y58)^AG$1)) -> #VALUE! | AH58: =-((((U58-T58)*$W58)+($X58*12))*((1+$Y58)^AH$1)) -> #VALUE! | AI58: =-((((V58-U58)*$W58)+($X58*12))*((1+$Y58)^AI$1)) -> #VALUE! | AJ58: =-(I58*(1+Z58)) -> -781396.1 | AK58: =AC58*(1-$AA58) -> #VALUE! | AL58: =AD58*(1-$AA58) -> #VALUE! | AM58: =AE58*(1-$AA58) -> #VALUE! | AN58: =AF58*(1-$AA58) -> #VALUE! | AO58: =AG58*(1-$AA58) -> #VALUE! | AP58: =AH58*(1-$AA58) -> #VALUE! | AQ58: =AI58*(1-$AA58) -> #VALUE! | AR58: =(NPV(Y58,AK58,AL58,AM58,AN58,AO58,AP58,AQ58)+(SUM(AJ58,(J58*-1))))-(NPV(Y58,AC58,AD58,AE58,AF58,AG58,AH58,AI58)) -> #VALUE! | AS58: =SUM(AC58:AI58) -> #VALUE! | AT58: =SUM(AK58:AQ58) -> #VALUE! | AU58: =(((AVERAGE(AC58:AI58)/1000)-(AVERAGE(AK58:AQ58)/1000))+(((AJ58/1000)*-1)/7)+((J58/1000)/7))*-1 -> #VALUE! | AV58: =AU58/(((J58/1000)+((AJ58*-1)/1000))) -> #VALUE! | AW58: =IF(L58>1.1,"Fase de Degradação",IF(L58<1,"Confiabilidade em Crescimento","Fase de Vida Útil")) -> Confiabilidade em Crescimento | AX58: =VLOOKUP(D58,#REF!,5,FALSE) -> #REF! | AZ58: X | BB58: =IFERROR(VLOOKUP(Tabela1[[#This Row],[Denominação]],[10]Planilha1!$A:$B,2,FALSE),"") -> 0
A59: 58 | B59: BRU065 | C59: BRU065-BRUNIDORA | D59: 10006698 | E59: BR01-CIL-UCI-BRUNI2-BRUC30 | F59: 4529 | G59: 55197 | H59: 2021 | I59: 867357.48 | J59: 757759 | K59: 13232.26 | L59: 0.52 | M59: 4475 | N59: 13342 | O59: 17 | P59: =IFERROR(VLOOKUP(Tabela1[[#This Row],[TAG]],#REF!,14,FALSE),"") | Q59: =P59+P59 -> #VALUE! | R59: =Q59+P59 -> #VALUE! | S59: =R59+P59 -> #VALUE! | T59: =S59+P59 -> #VALUE! | U59: =T59+P59 -> #VALUE! | V59: =U59+P59 -> #VALUE! | W59: 234.1 | X59: 246.01 | Y59: 0.1 | Z59: =IF(Tabela1[[#This Row],[Ano Aquisição]]=2023,0,IFERROR(VLOOKUP(H59,inflação!$F:$H,3,FALSE),"")) -> 0.1585 | AA59: 0.8 | AB59: =I59*-1 -> -867357.48 | AC59: =-(((P59*$W59)+($X59*12))*((1+$Y59)^AC$1)) -> #VALUE! | AD59: =-((((Q59-P59)*$W59)+($X59*12))*((1+$Y59)^AD$1)) -> #VALUE! | AE59: =-((((R59-Q59)*$W59)+($X59*12))*((1+$Y59)^AE$1)) -> #VALUE! | AF59: =-((((S59-R59)*$W59)+($X59*12))*((1+$Y59)^AF$1)) -> #VALUE! | AG59: =-((((T59-S59)*$W59)+($X59*12))*((1+$Y59)^AG$1)) -> #VALUE! | AH59: =-((((U59-T59)*$W59)+($X59*12))*((1+$Y59)^AH$1)) -> #VALUE! | AI59: =-((((V59-U59)*$W59)+($X59*12))*((1+$Y59)^AI$1)) -> #VALUE! | AJ59: =-(I59*(1+Z59)) -> -1004833.6 | AK59: =AC59*(1-$AA59) -> #VALUE! | AL59: =AD59*(1-$AA59) -> #VALUE! | AM59: =AE59*(1-$AA59) -> #VALUE! | AN59: =AF59*(1-$AA59) -> #VALUE! | AO59: =AG59*(1-$AA59) -> #VALUE! | AP59: =AH59*(1-$AA59) -> #VALUE! | AQ59: =AI59*(1-$AA59) -> #VALUE! | AR59: =(NPV(Y59,AK59,AL59,AM59,AN59,AO59,AP59,AQ59)+(SUM(AJ59,(J59*-1))))-(NPV(Y59,AC59,AD59,AE59,AF59,AG59,AH59,AI59)) -> #VALUE! | AS59: =SUM(AC59:AI59) -> #VALUE! | AT59: =SUM(AK59:AQ59) -> #VALUE! | AU59: =(((AVERAGE(AC59:AI59)/1000)-(AVERAGE(AK59:AQ59)/1000))+(((AJ59/1000)*-1)/7)+((J59/1000)/7))*-1 -> #VALUE! | AV59: =AU59/(((J59/1000)+((AJ59*-1)/1000))) -> #VALUE! | AW59: =IF(L59>1.1,"Fase de Degradação",IF(L59<1,"Confiabilidade em Crescimento","Fase de Vida Útil")) -> Confiabilidade em Crescimento | AX59: =VLOOKUP(D59,#REF!,5,FALSE) -> #REF! | AZ59: X | BB59: =IFERROR(VLOOKUP(Tabela1[[#This Row],[Denominação]],[10]Planilha1!$A:$B,2,FALSE),"") -> 13232.26
A60: 59 | B60: BRU066 | C60: BRU066-BRUNIDORA | D60: 10006700 | E60: BR01-CIL-UCI-BRUNI2-BRUC30 | F60: 4529 | G60: 55194 | H60: 2021 | I60: 674489.45 | J60: 589262 | K60: 18904.18 | L60: 1.29 | M60: 4475 | N60: 6511 | O60: 7 | P60: =IFERROR(VLOOKUP(Tabela1[[#This Row],[TAG]],#REF!,14,FALSE),"") | Q60: =P60+P60 -> #VALUE! | R60: =Q60+P60 -> #VALUE! | S60: =R60+P60 -> #VALUE! | T60: =S60+P60 -> #VALUE! | U60: =T60+P60 -> #VALUE! | V60: =U60+P60 -> #VALUE! | W60: 468.57 | X60: 594.16 | Y60: 0.1 | Z60: =IF(Tabela1[[#This Row],[Ano Aquisição]]=2023,0,IFERROR(VLOOKUP(H60,inflação!$F:$H,3,FALSE),"")) -> 0.1585 | AA60: 0.8 | AB60: =I60*-1 -> -674489.45 | AC60: =-(((P60*$W60)+($X60*12))*((1+$Y60)^AC$1)) -> #VALUE! | AD60: =-((((Q60-P60)*$W60)+($X60*12))*((1+$Y60)^AD$1)) -> #VALUE! | AE60: =-((((R60-Q60)*$W60)+($X60*12))*((1+$Y60)^AE$1)) -> #VALUE! | AF60: =-((((S60-R60)*$W60)+($X60*12))*((1+$Y60)^AF$1)) -> #VALUE! | AG60: =-((((T60-S60)*$W60)+($X60*12))*((1+$Y60)^AG$1)) -> #VALUE! | AH60: =-((((U60-T60)*$W60)+($X60*12))*((1+$Y60)^AH$1)) -> #VALUE! | AI60: =-((((V60-U60)*$W60)+($X60*12))*((1+$Y60)^AI$1)) -> #VALUE! | AJ60: =-(I60*(1+Z60)) -> -781396.03 | AK60: =AC60*(1-$AA60) -> #VALUE! | AL60: =AD60*(1-$AA60) -> #VALUE! | AM60: =AE60*(1-$AA60) -> #VALUE! | AN60: =AF60*(1-$AA60) -> #VALUE! | AO60: =AG60*(1-$AA60) -> #VALUE! | AP60: =AH60*(1-$AA60) -> #VALUE! | AQ60: =AI60*(1-$AA60) -> #VALUE! | AR60: =(NPV(Y60,AK60,AL60,AM60,AN60,AO60,AP60,AQ60)+(SUM(AJ60,(J60*-1))))-(NPV(Y60,AC60,AD60,AE60,AF60,AG60,AH60,AI60)) -> #VALUE! | AS60: =SUM(AC60:AI60) -> #VALUE! | AT60: =SUM(AK60:AQ60) -> #VALUE! | AU60: =(((AVERAGE(AC60:AI60)/1000)-(AVERAGE(AK60:AQ60)/1000))+(((AJ60/1000)*-1)/7)+((J60/1000)/7))*-1 -> #VALUE! | AV60: =AU60/(((J60/1000)+((AJ60*-1)/1000))) -> #VALUE! | AW60: =IF(L60>1.1,"Fase de Degradação",IF(L60<1,"Confiabilidade em Crescimento","Fase de Vida Útil")) -> Fase de Degradação | AX60: =VLOOKUP(D60,#REF!,5,FALSE) -> #REF! | AZ60: X | BB60: =IFERROR(VLOOKUP(Tabela1[[#This Row],[Denominação]],[10]Planilha1!$A:$B,2,FALSE),"") -> 18904.18
A61: 60 | B61: BRU067 | C61: BRU067-BRUNIDORA | D61: 10006701 | E61: BR01-CIL-UCI-BRUNI2-BRUC26 | F61: 4529 | G61: 55624 | H61: 2021 | I61: 681253.62 | J61: 606155 | K61: 1760.24 | L61: 0.85 | M61: 5094 | N61: 9886 | O61: 5 | P61: =IFERROR(VLOOKUP(Tabela1[[#This Row],[TAG]],#REF!,14,FALSE),"") | Q61: =P61+P61 -> #VALUE! | R61: =Q61+P61 -> #VALUE! | S61: =R61+P61 -> #VALUE! | T61: =S61+P61 -> #VALUE! | U61: =T61+P61 -> #VALUE! | V61: =U61+P61 -> #VALUE! | W61: 229.76 | X61: 316.41 | Y61: 0.1 | Z61: =IF(Tabela1[[#This Row],[Ano Aquisição]]=2023,0,IFERROR(VLOOKUP(H61,inflação!$F:$H,3,FALSE),"")) -> 0.1585 | AA61: 0.8 | AB61: =I61*-1 -> -681253.62 | AC61: =-(((P61*$W61)+($X61*12))*((1+$Y61)^AC$1)) -> #VALUE! | AD61: =-((((Q61-P61)*$W61)+($X61*12))*((1+$Y61)^AD$1)) -> #VALUE! | AE61: =-((((R61-Q61)*$W61)+($X61*12))*((1+$Y61)^AE$1)) -> #VALUE! | AF61: =-((((S61-R61)*$W61)+($X61*12))*((1+$Y61)^AF$1)) -> #VALUE! | AG61: =-((((T61-S61)*$W61)+($X61*12))*((1+$Y61)^AG$1)) -> #VALUE! | AH61: =-((((U61-T61)*$W61)+($X61*12))*((1+$Y61)^AH$1)) -> #VALUE! | AI61: =-((((V61-U61)*$W61)+($X61*12))*((1+$Y61)^AI$1)) -> #VALUE! | AJ61: =-(I61*(1+Z61)) -> -789232.32 | AK61: =AC61*(1-$AA61) -> #VALUE! | AL61: =AD61*(1-$AA61) -> #VALUE! | AM61: =AE61*(1-$AA61) -> #VALUE! | AN61: =AF61*(1-$AA61) -> #VALUE! | AO61: =AG61*(1-$AA61) -> #VALUE! | AP61: =AH61*(1-$AA61) -> #VALUE! | AQ61: =AI61*(1-$AA61) -> #VALUE! | AR61: =(NPV(Y61,AK61,AL61,AM61,AN61,AO61,AP61,AQ61)+(SUM(AJ61,(J61*-1))))-(NPV(Y61,AC61,AD61,AE61,AF61,AG61,AH61,AI61)) -> #VALUE! | AS61: =SUM(AC61:AI61) -> #VALUE! | AT61: =SUM(AK61:AQ61) -> #VALUE! | AU61: =(((AVERAGE(AC61:AI61)/1000)-(AVERAGE(AK61:AQ61)/1000))+(((AJ61/1000)*-1)/7)+((J61/1000)/7))*-1 -> #VALUE! | AV61: =AU61/(((J61/1000)+((AJ61*-1)/1000))) -> #VALUE! | AW61: =IF(L61>1.1,"Fase de Degradação",IF(L61<1,"Confiabilidade em Crescimento","Fase de Vida Útil")) -> Confiabilidade em Crescimento | AX61: =VLOOKUP(D61,#REF!,5,FALSE) -> #REF! | AZ61: X | BB61: =IFERROR(VLOOKUP(Tabela1[[#This Row],[Denominação]],[10]Planilha1!$A:$B,2,FALSE),"") -> 1760.24
A62: 61 | B62: BRU068 | C62: BRU068-BRUNIDORA | D62: 10006765 | E62: BR01-CIL-UCI-BRUNI1-BRUC31 | F62: 4529 | G62: 56675 | H62: 2021 | I62: 890786.1 | J62: 827534 | K62: 6595.03 | L62: 1 | M62: 4132 | N62: 8573 | O62: 14 | P62: =IFERROR(VLOOKUP(Tabela1[[#This Row],[TAG]],#REF!,14,FALSE),"") | Q62: =P62+P62 -> #VALUE! | R62: =Q62+P62 -> #VALUE! | S62: =R62+P62 -> #VALUE! | T62: =S62+P62 -> #VALUE! | U62: =T62+P62 -> #VALUE! | V62: =U62+P62 -> #VALUE! | W62: 561.68 | X62: 741.63 | Y62: 0.1 | Z62: =IF(Tabela1[[#This Row],[Ano Aquisição]]=2023,0,IFERROR(VLOOKUP(H62,inflação!$F:$H,3,FALSE),"")) -> 0.1585 | AA62: 0.8 | AB62: =I62*-1 -> -890786.1 | AC62: =-(((P62*$W62)+($X62*12))*((1+$Y62)^AC$1)) -> #VALUE! | AD62: =-((((Q62-P62)*$W62)+($X62*12))*((1+$Y62)^AD$1)) -> #VALUE! | AE62: =-((((R62-Q62)*$W62)+($X62*12))*((1+$Y62)^AE$1)) -> #VALUE! | AF62: =-((((S62-R62)*$W62)+($X62*12))*((1+$Y62)^AF$1)) -> #VALUE! | AG62: =-((((T62-S62)*$W62)+($X62*12))*((1+$Y62)^AG$1)) -> #VALUE! | AH62: =-((((U62-T62)*$W62)+($X62*12))*((1+$Y62)^AH$1)) -> #VALUE! | AI62: =-((((V62-U62)*$W62)+($X62*12))*((1+$Y62)^AI$1)) -> #VALUE! | AJ62: =-(I62*(1+Z62)) -> -1031975.7 | AK62: =AC62*(1-$AA62) -> #VALUE! | AL62: =AD62*(1-$AA62) -> #VALUE! | AM62: =AE62*(1-$AA62) -> #VALUE! | AN62: =AF62*(1-$AA62) -> #VALUE! | AO62: =AG62*(1-$AA62) -> #VALUE! | AP62: =AH62*(1-$AA62) -> #VALUE! | AQ62: =AI62*(1-$AA62) -> #VALUE! | AR62: =(NPV(Y62,AK62,AL62,AM62,AN62,AO62,AP62,AQ62)+(SUM(AJ62,(J62*-1))))-(NPV(Y62,AC62,AD62,AE62,AF62,AG62,AH62,AI62)) -> #VALUE! | AS62: =SUM(AC62:AI62) -> #VALUE! | AT62: =SUM(AK62:AQ62) -> #VALUE! | AU62: =(((AVERAGE(AC62:AI62)/1000)-(AVERAGE(AK62:AQ62)/1000))+(((AJ62/1000)*-1)/7)+((J62/1000)/7))*-1 -> #VALUE! | AV62: =AU62/(((J62/1000)+((AJ62*-1)/1000))) -> #VALUE! | AW62: =IF(L62>1.1,"Fase de Degradação",IF(L62<1,"Confiabilidade em Crescimento","Fase de Vida Útil")) -> Fase de Vida Útil | AX62: =VLOOKUP(D62,#REF!,5,FALSE) -> #REF! | AZ62: X | BB62: =IFERROR(VLOOKUP(Tabela1[[#This Row],[Denominação]],[10]Planilha1!$A:$B,2,FALSE),"") -> 6595.03
A63: 62 | B63: BRU069 | C63: BRU069-BRUNIDORA | D63: 10006766 | E63: BR01-CIL-UCI-BRUNI1-BRUC32 | F63: 4529 | G63: 56680 | H63: 2021 | I63: 893080.09 | J63: 829666 | K63: 3039.23 | L63: 1.01 | M63: 3800 | N63: 8816 | O63: 15 | P63: =IFERROR(VLOOKUP(Tabela1[[#This Row],[TAG]],#REF!,14,FALSE),"") | Q63: =P63+P63 -> #VALUE! | R63: =Q63+P63 -> #VALUE! | S63: =R63+P63 -> #VALUE! | T63: =S63+P63 -> #VALUE! | U63: =T63+P63 -> #VALUE! | V63: =U63+P63 -> #VALUE! | W63: 378.46 | X63: 450.22 | Y63: 0.1 | Z63: =IF(Tabela1[[#This Row],[Ano Aquisição]]=2023,0,IFERROR(VLOOKUP(H63,inflação!$F:$H,3,FALSE),"")) -> 0.1585 | AA63: 0.8 | AB63: =I63*-1 -> -893080.09 | AC63: =-(((P63*$W63)+($X63*12))*((1+$Y63)^AC$1)) -> #VALUE! | AD63: =-((((Q63-P63)*$W63)+($X63*12))*((1+$Y63)^AD$1)) -> #VALUE! | AE63: =-((((R63-Q63)*$W63)+($X63*12))*((1+$Y63)^AE$1)) -> #VALUE! | AF63: =-((((S63-R63)*$W63)+($X63*12))*((1+$Y63)^AF$1)) -> #VALUE! | AG63: =-((((T63-S63)*$W63)+($X63*12))*((1+$Y63)^AG$1)) -> #VALUE! | AH63: =-((((U63-T63)*$W63)+($X63*12))*((1+$Y63)^AH$1)) -> #VALUE! | AI63: =-((((V63-U63)*$W63)+($X63*12))*((1+$Y63)^AI$1)) -> #VALUE! | AJ63: =-(I63*(1+Z63)) -> -1034633.3 | AK63: =AC63*(1-$AA63) -> #VALUE! | AL63: =AD63*(1-$AA63) -> #VALUE! | AM63: =AE63*(1-$AA63) -> #VALUE! | AN63: =AF63*(1-$AA63) -> #VALUE! | AO63: =AG63*(1-$AA63) -> #VALUE! | AP63: =AH63*(1-$AA63) -> #VALUE! | AQ63: =AI63*(1-$AA63) -> #VALUE! | AR63: =(NPV(Y63,AK63,AL63,AM63,AN63,AO63,AP63,AQ63)+(SUM(AJ63,(J63*-1))))-(NPV(Y63,AC63,AD63,AE63,AF63,AG63,AH63,AI63)) -> #VALUE! | AS63: =SUM(AC63:AI63) -> #VALUE! | AT63: =SUM(AK63:AQ63) -> #VALUE! | AU63: =(((AVERAGE(AC63:AI63)/1000)-(AVERAGE(AK63:AQ63)/1000))+(((AJ63/1000)*-1)/7)+((J63/1000)/7))*-1 -> #VALUE! | AV63: =AU63/(((J63/1000)+((AJ63*-1)/1000))) -> #VALUE! | AW63: =IF(L63>1.1,"Fase de Degradação",IF(L63<1,"Confiabilidade em Crescimento","Fase de Vida Útil")) -> Fase de Vida Útil | AX63: =VLOOKUP(D63,#REF!,5,FALSE) -> #REF! | AZ63: X | BB63: =IFERROR(VLOOKUP(Tabela1[[#This Row],[Denominação]],[10]Planilha1!$A:$B,2,FALSE),"") -> 3039.23
A64: 63 | B64: BRU070 | C64: BRU070-BRUNIDORA | D64: 10006767 | E64: BR01-CIL-UCI-BRUNI1-BRUC31 | F64: 4529 | G64: 56676 | H64: 2021 | I64: 640938.73 | J64: 595427 | K64: 1301.37 | L64: 0.95 | M64: 4132 | N64: 5907 | O64: 11 | P64: =IFERROR(VLOOKUP(Tabela1[[#This Row],[TAG]],#REF!,14,FALSE),"") | Q64: =P64+P64 -> #VALUE! | R64: =Q64+P64 -> #VALUE! | S64: =R64+P64 -> #VALUE! | T64: =S64+P64 -> #VALUE! | U64: =T64+P64 -> #VALUE! | V64: =U64+P64 -> #VALUE! | W64: 1060.9 | X64: 751.79 | Y64: 0.1 | Z64: =IF(Tabela1[[#This Row],[Ano Aquisição]]=2023,0,IFERROR(VLOOKUP(H64,inflação!$F:$H,3,FALSE),"")) -> 0.1585 | AA64: 0.8 | AB64: =I64*-1 -> -640938.73 | AC64: =-(((P64*$W64)+($X64*12))*((1+$Y64)^AC$1)) -> #VALUE! | AD64: =-((((Q64-P64)*$W64)+($X64*12))*((1+$Y64)^AD$1)) -> #VALUE! | AE64: =-((((R64-Q64)*$W64)+($X64*12))*((1+$Y64)^AE$1)) -> #VALUE! | AF64: =-((((S64-R64)*$W64)+($X64*12))*((1+$Y64)^AF$1)) -> #VALUE! | AG64: =-((((T64-S64)*$W64)+($X64*12))*((1+$Y64)^AG$1)) -> #VALUE! | AH64: =-((((U64-T64)*$W64)+($X64*12))*((1+$Y64)^AH$1)) -> #VALUE! | AI64: =-((((V64-U64)*$W64)+($X64*12))*((1+$Y64)^AI$1)) -> #VALUE! | AJ64: =-(I64*(1+Z64)) -> -742527.52 | AK64: =AC64*(1-$AA64) -> #VALUE! | AL64: =AD64*(1-$AA64) -> #VALUE! | AM64: =AE64*(1-$AA64) -> #VALUE! | AN64: =AF64*(1-$AA64) -> #VALUE! | AO64: =AG64*(1-$AA64) -> #VALUE! | AP64: =AH64*(1-$AA64) -> #VALUE! | AQ64: =AI64*(1-$AA64) -> #VALUE! | AR64: =(NPV(Y64,AK64,AL64,AM64,AN64,AO64,AP64,AQ64)+(SUM(AJ64,(J64*-1))))-(NPV(Y64,AC64,AD64,AE64,AF64,AG64,AH64,AI64)) -> #VALUE! | AS64: =SUM(AC64:AI64) -> #VALUE! | AT64: =SUM(AK64:AQ64) -> #VALUE! | AU64: =(((AVERAGE(AC64:AI64)/1000)-(AVERAGE(AK64:AQ64)/1000))+(((AJ64/1000)*-1)/7)+((J64/1000)/7))*-1 -> #VALUE! | AV64: =AU64/(((J64/1000)+((AJ64*-1)/1000))) -> #VALUE! | AW64: =IF(L64>1.1,"Fase de Degradação",IF(L64<1,"Confiabilidade em Crescimento","Fase de Vida Útil")) -> Confiabilidade em Crescimento | AX64: =VLOOKUP(D64,#REF!,5,FALSE) -> #REF! | AZ64: X | BB64: =IFERROR(VLOOKUP(Tabela1[[#This Row],[Denominação]],[10]Planilha1!$A:$B,2,FALSE),"") -> 1301.37
A65: 64 | B65: BRU071 | C65: BRU071-BRUNIDORA | D65: 10006768 | E65: BR01-CIL-UCI-BRUNI1-BRUC32 | F65: 4529 | G65: 56681 | H65: 2021 | I65: 643232.25 | J65: 597558 | K65: 738.45 | L65: 1.03 | M65: 3800 | N65: 4941 | O65: 15 | P65: =IFERROR(VLOOKUP(Tabela1[[#This Row],[TAG]],#REF!,14,FALSE),"") | Q65: =P65+P65 -> #VALUE! | R65: =Q65+P65 -> #VALUE! | S65: =R65+P65 -> #VALUE! | T65: =S65+P65 -> #VALUE! | U65: =T65+P65 -> #VALUE! | V65: =U65+P65 -> #VALUE! | W65: 440.83 | X65: 428.91 | Y65: 0.1 | Z65: =IF(Tabela1[[#This Row],[Ano Aquisição]]=2023,0,IFERROR(VLOOKUP(H65,inflação!$F:$H,3,FALSE),"")) -> 0.1585 | AA65: 0.8 | AB65: =I65*-1 -> -643232.25 | AC65: =-(((P65*$W65)+($X65*12))*((1+$Y65)^AC$1)) -> #VALUE! | AD65: =-((((Q65-P65)*$W65)+($X65*12))*((1+$Y65)^AD$1)) -> #VALUE! | AE65: =-((((R65-Q65)*$W65)+($X65*12))*((1+$Y65)^AE$1)) -> #VALUE! | AF65: =-((((S65-R65)*$W65)+($X65*12))*((1+$Y65)^AF$1)) -> #VALUE! | AG65: =-((((T65-S65)*$W65)+($X65*12))*((1+$Y65)^AG$1)) -> #VALUE! | AH65: =-((((U65-T65)*$W65)+($X65*12))*((1+$Y65)^AH$1)) -> #VALUE! | AI65: =-((((V65-U65)*$W65)+($X65*12))*((1+$Y65)^AI$1)) -> #VALUE! | AJ65: =-(I65*(1+Z65)) -> -745184.56 | AK65: =AC65*(1-$AA65) -> #VALUE! | AL65: =AD65*(1-$AA65) -> #VALUE! | AM65: =AE65*(1-$AA65) -> #VALUE! | AN65: =AF65*(1-$AA65) -> #VALUE! | AO65: =AG65*(1-$AA65) -> #VALUE! | AP65: =AH65*(1-$AA65) -> #VALUE! | AQ65: =AI65*(1-$AA65) -> #VALUE! | AR65: =(NPV(Y65,AK65,AL65,AM65,AN65,AO65,AP65,AQ65)+(SUM(AJ65,(J65*-1))))-(NPV(Y65,AC65,AD65,AE65,AF65,AG65,AH65,AI65)) -> #VALUE! | AS65: =SUM(AC65:AI65) -> #VALUE! | AT65: =SUM(AK65:AQ65) -> #VALUE! | AU65: =(((AVERAGE(AC65:AI65)/1000)-(AVERAGE(AK65:AQ65)/1000))+(((AJ65/1000)*-1)/7)+((J65/1000)/7))*-1 -> #VALUE! | AV65: =AU65/(((J65/1000)+((AJ65*-1)/1000))) -> #VALUE! | AW65: =IF(L65>1.1,"Fase de Degradação",IF(L65<1,"Confiabilidade em Crescimento","Fase de Vida Útil")) -> Fase de Vida Útil | AX65: =VLOOKUP(D65,#REF!,5,FALSE) -> #REF! | AZ65: X | BB65: =IFERROR(VLOOKUP(Tabela1[[#This Row],[Denominação]],[10]Planilha1!$A:$B,2,FALSE),"") -> 738.45
A66: 65 | B66: BRU072 | C66: BRU072-BRUNIDORA | D66: 10006781 | E66: BR01-CIL-UCI-BRUNI1-BRUC02 | F66: 4529 | G66: 56703 | H66: 2022 | I66: 859093.25 | J66: 798091 | K66: 8253.86 | L66: 0.99 | M66: 4464 | N66: 9627 | O66: 23 | P66: =IFERROR(VLOOKUP(Tabela1[[#This Row],[TAG]],#REF!,14,FALSE),"") | Q66: =P66+P66 -> #VALUE! | R66: =Q66+P66 -> #VALUE! | S66: =R66+P66 -> #VALUE! | T66: =S66+P66 -> #VALUE! | U66: =T66+P66 -> #VALUE! | V66: =U66+P66 -> #VALUE! | W66: 450.93 | X66: 879.23 | Y66: 0.1 | Z66: =IF(Tabela1[[#This Row],[Ano Aquisição]]=2023,0,IFERROR(VLOOKUP(H66,inflação!$F:$H,3,FALSE),"")) -> 0.0579 | AA66: 0.8 | AB66: =I66*-1 -> -859093.25 | AC66: =-(((P66*$W66)+($X66*12))*((1+$Y66)^AC$1)) -> #VALUE! | AD66: =-((((Q66-P66)*$W66)+($X66*12))*((1+$Y66)^AD$1)) -> #VALUE! | AE66: =-((((R66-Q66)*$W66)+($X66*12))*((1+$Y66)^AE$1)) -> #VALUE! | AF66: =-((((S66-R66)*$W66)+($X66*12))*((1+$Y66)^AF$1)) -> #VALUE! | AG66: =-((((T66-S66)*$W66)+($X66*12))*((1+$Y66)^AG$1)) -> #VALUE! | AH66: =-((((U66-T66)*$W66)+($X66*12))*((1+$Y66)^AH$1)) -> #VALUE! | AI66: =-((((V66-U66)*$W66)+($X66*12))*((1+$Y66)^AI$1)) -> #VALUE! | AJ66: =-(I66*(1+Z66)) -> -908834.75 | AK66: =AC66*(1-$AA66) -> #VALUE! | AL66: =AD66*(1-$AA66) -> #VALUE! | AM66: =AE66*(1-$AA66) -> #VALUE! | AN66: =AF66*(1-$AA66) -> #VALUE! | AO66: =AG66*(1-$AA66) -> #VALUE! | AP66: =AH66*(1-$AA66) -> #VALUE! | AQ66: =AI66*(1-$AA66) -> #VALUE! | AR66: =(NPV(Y66,AK66,AL66,AM66,AN66,AO66,AP66,AQ66)+(SUM(AJ66,(J66*-1))))-(NPV(Y66,AC66,AD66,AE66,AF66,AG66,AH66,AI66)) -> #VALUE! | AS66: =SUM(AC66:AI66) -> #VALUE! | AT66: =SUM(AK66:AQ66) -> #VALUE! | AU66: =(((AVERAGE(AC66:AI66)/1000)-(AVERAGE(AK66:AQ66)/1000))+(((AJ66/1000)*-1)/7)+((J66/1000)/7))*-1 -> #VALUE! | AV66: =AU66/(((J66/1000)+((AJ66*-1)/1000))) -> #VALUE! | AW66: =IF(L66>1.1,"Fase de Degradação",IF(L66<1,"Confiabilidade em Crescimento","Fase de Vida Útil")) -> Confiabilidade em Crescimento | AX66: =VLOOKUP(D66,#REF!,5,FALSE) -> #REF! | AZ66: X | BB66: =IFERROR(VLOOKUP(Tabela1[[#This Row],[Denominação]],[10]Planilha1!$A:$B,2,FALSE),"") -> 19338.54
A67: 66 | B67: BRU073 | C67: BRU073-BRUNIDORA | D67: 10006831 | E67: BR01-CIL-UCI-BRUNI2-BRUC12 | F67: 4529 | G67: 56704 | H67: 2022 | I67: 859093.02 | J67: 798091 | K67: 1753.81 | L67: 1.07 | M67: 4344 | N67: 3590 | O67: 8 | P67: =IFERROR(VLOOKUP(Tabela1[[#This Row],[TAG]],#REF!,14,FALSE),"") | Q67: =P67+P67 -> #VALUE! | R67: =Q67+P67 -> #VALUE! | S67: =R67+P67 -> #VALUE! | T67: =S67+P67 -> #VALUE! | U67: =T67+P67 -> #VALUE! | V67: =U67+P67 -> #VALUE! | W67: 272.76 | X67: 351.79 | Y67: 0.1 | Z67: =IF(Tabela1[[#This Row],[Ano Aquisição]]=2023,0,IFERROR(VLOOKUP(H67,inflação!$F:$H,3,FALSE),"")) -> 0.0579 | AA67: 0.8 | AB67: =I67*-1 -> -859093.02 | AC67: =-(((P67*$W67)+($X67*12))*((1+$Y67)^AC$1)) -> #VALUE! | AD67: =-((((Q67-P67)*$W67)+($X67*12))*((1+$Y67)^AD$1)) -> #VALUE! | AE67: =-((((R67-Q67)*$W67)+($X67*12))*((1+$Y67)^AE$1)) -> #VALUE! | AF67: =-((((S67-R67)*$W67)+($X67*12))*((1+$Y67)^AF$1)) -> #VALUE! | AG67: =-((((T67-S67)*$W67)+($X67*12))*((1+$Y67)^AG$1)) -> #VALUE! | AH67: =-((((U67-T67)*$W67)+($X67*12))*((1+$Y67)^AH$1)) -> #VALUE! | AI67: =-((((V67-U67)*$W67)+($X67*12))*((1+$Y67)^AI$1)) -> #VALUE! | AJ67: =-(I67*(1+Z67)) -> -908834.51 | AK67: =AC67*(1-$AA67) -> #VALUE! | AL67: =AD67*(1-$AA67) -> #VALUE! | AM67: =AE67*(1-$AA67) -> #VALUE! | AN67: =AF67*(1-$AA67) -> #VALUE! | AO67: =AG67*(1-$AA67) -> #VALUE! | AP67: =AH67*(1-$AA67) -> #VALUE! | AQ67: =AI67*(1-$AA67) -> #VALUE! | AR67: =(NPV(Y67,AK67,AL67,AM67,AN67,AO67,AP67,AQ67)+(SUM(AJ67,(J67*-1))))-(NPV(Y67,AC67,AD67,AE67,AF67,AG67,AH67,AI67)) -> #VALUE! | AS67: =SUM(AC67:AI67) -> #VALUE! | AT67: =SUM(AK67:AQ67) -> #VALUE! | AU67: =(((AVERAGE(AC67:AI67)/1000)-(AVERAGE(AK67:AQ67)/1000))+(((AJ67/1000)*-1)/7)+((J67/1000)/7))*-1 -> #VALUE! | AV67: =AU67/(((J67/1000)+((AJ67*-1)/1000))) -> #VALUE! | AW67: =IF(L67>1.1,"Fase de Degradação",IF(L67<1,"Confiabilidade em Crescimento","Fase de Vida Útil")) -> Fase de Vida Útil | AX67: =VLOOKUP(D67,#REF!,5,FALSE) -> #REF! | AZ67: X | BB67: =IFERROR(VLOOKUP(Tabela1[[#This Row],[Denominação]],[10]Planilha1!$A:$B,2,FALSE),"") -> 5898.29
A68: 67 | B68: BRU090 | C68: BRU090-BRUNIDORA SUNNEN SV - 2015 - 2 | D68: 10006931 | E68: BR01-MOT-VIR-LBIELA-BRU090 | F68: 3336 | H68: 2022 | P68: =IFERROR(VLOOKUP(Tabela1[[#This Row],[TAG]],#REF!,14,FALSE),"") | Z68: =IF(Tabela1[[#This Row],[Ano Aquisição]]=2023,0,IFERROR(VLOOKUP(H68,inflação!$F:$H,3,FALSE),"")) -> 0.0579 | AX68: =VLOOKUP(D68,#REF!,5,FALSE) -> #REF! | AZ68: X | BB68: =IFERROR(VLOOKUP(Tabela1[[#This Row],[Denominação]],[10]Planilha1!$A:$B,2,FALSE),"")
A69: 68 | B69: BRU091 | C69: BRU091-BRUNIDORA SUNNEN SV - 2015 - 3 | D69: 10006932 | E69: BR01-MOT-VIR-LBIELA-BRU091 | F69: 3336 | H69: 2022 | P69: =IFERROR(VLOOKUP(Tabela1[[#This Row],[TAG]],#REF!,14,FALSE),"") | Z69: =IF(Tabela1[[#This Row],[Ano Aquisição]]=2023,0,IFERROR(VLOOKUP(H69,inflação!$F:$H,3,FALSE),"")) -> 0.0579 | AX69: =VLOOKUP(D69,#REF!,5,FALSE) -> #REF! | AZ69: X | BB69: =IFERROR(VLOOKUP(Tabela1[[#This Row],[Denominação]],[10]Planilha1!$A:$B,2,FALSE),"")
A70: 69 | B70: CAB004 | C70: CAB004-CABINE DE PINTURA | D70: 10001567 | E70: BR01-MOT-SAB-LFACAS-CAB004 | F70: 2572 | G70: 8284 | H70: 1991 | I70: 4874.73 | J70: 0 | K70: 323153.06 | L70: 1.85 | M70: 4864 | N70: 195897 | O70: 508 | P70: 24 | Q70: =P70+P70 -> 48 | R70: =Q70+P70 -> 72 | S70: =R70+P70 -> 96 | T70: =S70+P70 -> 120 | U70: =T70+P70 -> 144 | V70: =U70+P70 -> 168 | W70: 497.44 | X70: 3538.25 | Y70: 0.1 | Z70: =IF(Tabela1[[#This Row],[Ano Aquisição]]=2023,0,IFERROR(VLOOKUP(H70,inflação!$F:$H,3,FALSE),"")) -> 2.0259231 | AA70: 0.8 | AB70: =I70*-1 -> -4874.73 | AC70: =-(((P70*$W70)+($X70*12))*((1+$Y70)^AC$1)) -> -59837.316 | AD70: =-((((Q70-P70)*$W70)+($X70*12))*((1+$Y70)^AD$1)) -> -65821.048 | AE70: =-((((R70-Q70)*$W70)+($X70*12))*((1+$Y70)^AE$1)) -> -72403.152 | AF70: =-((((S70-R70)*$W70)+($X70*12))*((1+$Y70)^AF$1)) -> -79643.468 | AG70: =-((((T70-S70)*$W70)+($X70*12))*((1+$Y70)^AG$1)) -> -87607.814 | AH70: =-((((U70-T70)*$W70)+($X70*12))*((1+$Y70)^AH$1)) -> -96368.596 | AI70: =-((((V70-U70)*$W70)+($X70*12))*((1+$Y70)^AI$1)) -> -106005.46 | AJ70: =-(I70*(1+Z70)) -> -14750.558 | AK70: =AC70*(1-$AA70) -> -11967.463 | AL70: =AD70*(1-$AA70) -> -13164.21 | AM70: =AE70*(1-$AA70) -> -14480.63 | AN70: =AF70*(1-$AA70) -> -15928.694 | AO70: =AG70*(1-$AA70) -> -17521.563 | AP70: =AH70*(1-$AA70) -> -19273.719 | AQ70: =AI70*(1-$AA70) -> -21201.091 | AR70: =(NPV(Y70,AK70,AL70,AM70,AN70,AO70,AP70,AQ70)+(SUM(AJ70,(J70*-1))))-(NPV(Y70,AC70,AD70,AE70,AF70,AG70,AH70,AI70)) -> 289875.78 | AS70: =SUM(AC70:AI70) -> -567686.85 | AT70: =SUM(AK70:AQ70) -> -113537.37 | AU70: =(((AVERAGE(AC70:AI70)/1000)-(AVERAGE(AK70:AQ70)/1000))+(((AJ70/1000)*-1)/7)+((J70/1000)/7))*-1 -> 62.771274 | AV70: =AU70/(((J70/1000)+((AJ70*-1)/1000))) -> 4.2555186 | AW70: =IF(L70>1.1,"Fase de Degradação",IF(L70<1,"Confiabilidade em Crescimento","Fase de Vida Útil")) -> Fase de Degradação | AX70: UMC | AZ70: X | BB70: =IFERROR(VLOOKUP(Tabela1[[#This Row],[Denominação]],[10]Planilha1!$A:$B,2,FALSE),"") -> 323153.06
A71: 70 | B71: CAB018 | C71: CAB018-CABINE DE PINTURA | D71: 10006361 | E71: BR01-MOT-UMG-PINTUR-CAB018 | F71: 2318 | G71: 900000013851 | H71: 2015 | I71: 50000 | J71: 0 | K71: 202377.45 | L71: 0.96 | M71: 3854 | N71: 67349 | O71: 207 | P71: =IFERROR(VLOOKUP(Tabela1[[#This Row],[TAG]],#REF!,14,FALSE),"") | Q71: =P71+P71 -> #VALUE! | R71: =Q71+P71 -> #VALUE! | S71: =R71+P71 -> #VALUE! | T71: =S71+P71 -> #VALUE! | U71: =T71+P71 -> #VALUE! | V71: =U71+P71 -> #VALUE! | W71: 465.44 | X71: 983.13 | Y71: 0.1 | Z71: =IF(Tabela1[[#This Row],[Ano Aquisição]]=2023,0,IFERROR(VLOOKUP(H71,inflação!$F:$H,3,FALSE),"")) -> 0.4834 | AA71: 0.8 | AB71: =I71*-1 -> -50000 | AC71: =-(((P71*$W71)+($X71*12))*((1+$Y71)^AC$1)) -> #VALUE! | AD71: =-((((Q71-P71)*$W71)+($X71*12))*((1+$Y71)^AD$1)) -> #VALUE! | AE71: =-((((R71-Q71)*$W71)+($X71*12))*((1+$Y71)^AE$1)) -> #VALUE! | AF71: =-((((S71-R71)*$W71)+($X71*12))*((1+$Y71)^AF$1)) -> #VALUE! | AG71: =-((((T71-S71)*$W71)+($X71*12))*((1+$Y71)^AG$1)) -> #VALUE! | AH71: =-((((U71-T71)*$W71)+($X71*12))*((1+$Y71)^AH$1)) -> #VALUE! | AI71: =-((((V71-U71)*$W71)+($X71*12))*((1+$Y71)^AI$1)) -> #VALUE! | AJ71: =-(I71*(1+Z71)) -> -74170 | AK71: =AC71*(1-$AA71) -> #VALUE! | AL71: =AD71*(1-$AA71) -> #VALUE! | AM71: =AE71*(1-$AA71) -> #VALUE! | AN71: =AF71*(1-$AA71) -> #VALUE! | AO71: =AG71*(1-$AA71) -> #VALUE! | AP71: =AH71*(1-$AA71) -> #VALUE! | AQ71: =AI71*(1-$AA71) -> #VALUE! | AR71: =(NPV(Y71,AK71,AL71,AM71,AN71,AO71,AP71,AQ71)+(SUM(AJ71,(J71*-1))))-(NPV(Y71,AC71,AD71,AE71,AF71,AG71,AH71,AI71)) -> #VALUE! | AS71: =SUM(AC71:AI71) -> #VALUE! | AT71: =SUM(AK71:AQ71) -> #VALUE! | AU71: =(((AVERAGE(AC71:AI71)/1000)-(AVERAGE(AK71:AQ71)/1000))+(((AJ71/1000)*-1)/7)+((J71/1000)/7))*-1 -> #VALUE! | AV71: =AU71/(((J71/1000)+((AJ71*-1)/1000))) -> #VALUE! | AW71: =IF(L71>1.1,"Fase de Degradação",IF(L71<1,"Confiabilidade em Crescimento","Fase de Vida Útil")) -> Confiabilidade em Crescimento | AX71: =VLOOKUP(D71,#REF!,5,FALSE) -> #REF! | AZ71: X | BB71: =IFERROR(VLOOKUP(Tabela1[[#This Row],[Denominação]],[10]Planilha1!$A:$B,2,FALSE),"") -> 202377.45
A72: 71 | B72: CAB028 | C72: CAB028-CABINE DE INSPEÇÃO DE TINTA | D72: 20001523 | E72: BR01-MOT-SAB-FINALL-CAB028 | F72: 2525 | G72: 43972 | H72: 2015 | I72: 1278.16 | J72: 340 | K72: 28360.95 | L72: 0.43 | M72: 5853.5532 | N72: 72045 | O72: 8 | P72: =IFERROR(VLOOKUP(Tabela1[[#This Row],[TAG]],#REF!,14,FALSE),"") | Q72: =P72+P72 -> #VALUE! | R72: =Q72+P72 -> #VALUE! | S72: =R72+P72 -> #VALUE! | T72: =S72+P72 -> #VALUE! | U72: =T72+P72 -> #VALUE! | V72: =U72+P72 -> #VALUE! | W72: 219.15 | X72: 185.47 | Y72: 0.1 | Z72: =IF(Tabela1[[#This Row],[Ano Aquisição]]=2023,0,IFERROR(VLOOKUP(H72,inflação!$F:$H,3,FALSE),"")) -> 0.4834 | AA72: 0.8 | AB72: =I72*-1 -> -1278.16 | AC72: =-(((P72*$W72)+($X72*12))*((1+$Y72)^AC$1)) -> #VALUE! | AD72: =-((((Q72-P72)*$W72)+($X72*12))*((1+$Y72)^AD$1)) -> #VALUE! | AE72: =-((((R72-Q72)*$W72)+($X72*12))*((1+$Y72)^AE$1)) -> #VALUE! | AF72: =-((((S72-R72)*$W72)+($X72*12))*((1+$Y72)^AF$1)) -> #VALUE! | AG72: =-((((T72-S72)*$W72)+($X72*12))*((1+$Y72)^AG$1)) -> #VALUE! | AH72: =-((((U72-T72)*$W72)+($X72*12))*((1+$Y72)^AH$1)) -> #VALUE! | AI72: =-((((V72-U72)*$W72)+($X72*12))*((1+$Y72)^AI$1)) -> #VALUE! | AJ72: =-(I72*(1+Z72)) -> -1896.0225 | AK72: =AC72*(1-$AA72) -> #VALUE! | AL72: =AD72*(1-$AA72) -> #VALUE! | AM72: =AE72*(1-$AA72) -> #VALUE! | AN72: =AF72*(1-$AA72) -> #VALUE! | AO72: =AG72*(1-$AA72) -> #VALUE! | AP72: =AH72*(1-$AA72) -> #VALUE! | AQ72: =AI72*(1-$AA72) -> #VALUE! | AR72: =(NPV(Y72,AK72,AL72,AM72,AN72,AO72,AP72,AQ72)+(SUM(AJ72,(J72*-1))))-(NPV(Y72,AC72,AD72,AE72,AF72,AG72,AH72,AI72)) -> #VALUE! | AS72: =SUM(AC72:AI72) -> #VALUE! | AT72: =SUM(AK72:AQ72) -> #VALUE! | AU72: =(((AVERAGE(AC72:AI72)/1000)-(AVERAGE(AK72:AQ72)/1000))+(((AJ72/1000)*-1)/7)+((J72/1000)/7))*-1 -> #VALUE! | AV72: =AU72/(((J72/1000)+((AJ72*-1)/1000))) -> #VALUE! | AW72: =IF(L72>1.1,"Fase de Degradação",IF(L72<1,"Confiabilidade em Crescimento","Fase de Vida Útil")) -> Confiabilidade em Crescimento | AX72: =VLOOKUP(D72,#REF!,5,FALSE) -> #REF! | AZ72: X | BB72: =IFERROR(VLOOKUP(Tabela1[[#This Row],[Denominação]],[10]Planilha1!$A:$B,2,FALSE),"") -> 28360.95
A73: 72 | B73: CAB029 | C73: CAB029-CABINE DE INSPEÇÃO | D73: 10006300 | E73: BR01-MOT-SAB-FINALL-CAB029 | F73: 2526 | G73: 43973 | H73: 2013 | I73: 799935.56 | J73: 130098 | K73: 251642.46 | L73: 1.13 | M73: 4795.2648 | N73: 70240 | O73: 198 | P73: =IFERROR(VLOOKUP(Tabela1[[#This Row],[TAG]],#REF!,14,FALSE),"") | Q73: =P73+P73 -> #VALUE! | R73: =Q73+P73 -> #VALUE! | S73: =R73+P73 -> #VALUE! | T73: =S73+P73 -> #VALUE! | U73: =T73+P73 -> #VALUE! | V73: =U73+P73 -> #VALUE! | W73: 1032.25 | X73: 3676.47 | Y73: 0.1 | Z73: =IF(Tabela1[[#This Row],[Ano Aquisição]]=2023,0,IFERROR(VLOOKUP(H73,inflação!$F:$H,3,FALSE),"")) -> 0.6066 | AA73: 0.8 | AB73: =I73*-1 -> -799935.56 | AC73: =-(((P73*$W73)+($X73*12))*((1+$Y73)^AC$1)) -> #VALUE! | AD73: =-((((Q73-P73)*$W73)+($X73*12))*((1+$Y73)^AD$1)) -> #VALUE! | AE73: =-((((R73-Q73)*$W73)+($X73*12))*((1+$Y73)^AE$1)) -> #VALUE! | AF73: =-((((S73-R73)*$W73)+($X73*12))*((1+$Y73)^AF$1)) -> #VALUE! | AG73: =-((((T73-S73)*$W73)+($X73*12))*((1+$Y73)^AG$1)) -> #VALUE! | AH73: =-((((U73-T73)*$W73)+($X73*12))*((1+$Y73)^AH$1)) -> #VALUE! | AI73: =-((((V73-U73)*$W73)+($X73*12))*((1+$Y73)^AI$1)) -> #VALUE! | AJ73: =-(I73*(1+Z73)) -> -1285176.5 | AK73: =AC73*(1-$AA73) -> #VALUE! | AL73: =AD73*(1-$AA73) -> #VALUE! | AM73: =AE73*(1-$AA73) -> #VALUE! | AN73: =AF73*(1-$AA73) -> #VALUE! | AO73: =AG73*(1-$AA73) -> #VALUE! | AP73: =AH73*(1-$AA73) -> #VALUE! | AQ73: =AI73*(1-$AA73) -> #VALUE! | AR73: =(NPV(Y73,AK73,AL73,AM73,AN73,AO73,AP73,AQ73)+(SUM(AJ73,(J73*-1))))-(NPV(Y73,AC73,AD73,AE73,AF73,AG73,AH73,AI73)) -> #VALUE! | AS73: =SUM(AC73:AI73) -> #VALUE! | AT73: =SUM(AK73:AQ73) -> #VALUE! | AU73: =(((AVERAGE(AC73:AI73)/1000)-(AVERAGE(AK73:AQ73)/1000))+(((AJ73/1000)*-1)/7)+((J73/1000)/7))*-1 -> #VALUE! | AV73: =AU73/(((J73/1000)+((AJ73*-1)/1000))) -> #VALUE! | AW73: =IF(L73>1.1,"Fase de Degradação",IF(L73<1,"Confiabilidade em Crescimento","Fase de Vida Útil")) -> Fase de Degradação | AX73: =VLOOKUP(D73,#REF!,5,FALSE) -> #REF! | AZ73: X | BB73: =IFERROR(VLOOKUP(Tabela1[[#This Row],[Denominação]],[10]Planilha1!$A:$B,2,FALSE),"") -> 251642.46
A74: 73 | B74: CAB030 | C74: CAB030-CABINE DE CURA UV | D74: 10006301 | E74: BR01-MOT-SAB-FINALL-CAB030 | F74: 2526 | G74: 44981 | H74: 2014 | I74: 117782.87 | J74: 49430 | K74: 260686.56 | L74: 0.87 | M74: 5853.5532 | N74: 72028 | O74: 176 | P74: =IFERROR(VLOOKUP(Tabela1[[#This Row],[TAG]],#REF!,14,FALSE),"") | Q74: =P74+P74 -> #VALUE! | R74: =Q74+P74 -> #VALUE! | S74: =R74+P74 -> #VALUE! | T74: =S74+P74 -> #VALUE! | U74: =T74+P74 -> #VALUE! | V74: =U74+P74 -> #VALUE! | W74: 404.06 | X74: 449.39 | Y74: 0.1 | Z74: =IF(Tabela1[[#This Row],[Ano Aquisição]]=2023,0,IFERROR(VLOOKUP(H74,inflação!$F:$H,3,FALSE),"")) -> 0.5475 | AA74: 0.8 | AB74: =I74*-1 -> -117782.87 | AC74: =-(((P74*$W74)+($X74*12))*((1+$Y74)^AC$1)) -> #VALUE! | AD74: =-((((Q74-P74)*$W74)+($X74*12))*((1+$Y74)^AD$1)) -> #VALUE! | AE74: =-((((R74-Q74)*$W74)+($X74*12))*((1+$Y74)^AE$1)) -> #VALUE! | AF74: =-((((S74-R74)*$W74)+($X74*12))*((1+$Y74)^AF$1)) -> #VALUE! | AG74: =-((((T74-S74)*$W74)+($X74*12))*((1+$Y74)^AG$1)) -> #VALUE! | AH74: =-((((U74-T74)*$W74)+($X74*12))*((1+$Y74)^AH$1)) -> #VALUE! | AI74: =-((((V74-U74)*$W74)+($X74*12))*((1+$Y74)^AI$1)) -> #VALUE! | AJ74: =-(I74*(1+Z74)) -> -182268.99 | AK74: =AC74*(1-$AA74) -> #VALUE! | AL74: =AD74*(1-$AA74) -> #VALUE! | AM74: =AE74*(1-$AA74) -> #VALUE! | AN74: =AF74*(1-$AA74) -> #VALUE! | AO74: =AG74*(1-$AA74) -> #VALUE! | AP74: =AH74*(1-$AA74) -> #VALUE! | AQ74: =AI74*(1-$AA74) -> #VALUE! | AR74: =(NPV(Y74,AK74,AL74,AM74,AN74,AO74,AP74,AQ74)+(SUM(AJ74,(J74*-1))))-(NPV(Y74,AC74,AD74,AE74,AF74,AG74,AH74,AI74)) -> #VALUE! | AS74: =SUM(AC74:AI74) -> #VALUE! | AT74: =SUM(AK74:AQ74) -> #VALUE! | AU74: =(((AVERAGE(AC74:AI74)/1000)-(AVERAGE(AK74:AQ74)/1000))+(((AJ74/1000)*-1)/7)+((J74/1000)/7))*-1 -> #VALUE! | AV74: =AU74/(((J74/1000)+((AJ74*-1)/1000))) -> #VALUE! | AW74: =IF(L74>1.1,"Fase de Degradação",IF(L74<1,"Confiabilidade em Crescimento","Fase de Vida Útil")) -> Confiabilidade em Crescimento | AX74: =VLOOKUP(D74,#REF!,5,FALSE) -> #REF! | AZ74: X | BB74: =IFERROR(VLOOKUP(Tabela1[[#This Row],[Denominação]],[10]Planilha1!$A:$B,2,FALSE),"") -> 260686.56
A75: 74 | B75: CAB031 | C75: CAB031-CABINE DE FLAMBAGEM | D75: 20001610 | E75: BR01-MOT-SAB-FINALL-CAB031 | F75: 2525 | G75: 45008 | H75: 2014 | I75: 98309.82 | J75: 24368 | K75: 76068.68 | L75: 0.97 | M75: 5853.5532 | N75: 69682 | O75: 77 | P75: =IFERROR(VLOOKUP(Tabela1[[#This Row],[TAG]],#REF!,14,FALSE),"") | Q75: =P75+P75 -> #VALUE! | R75: =Q75+P75 -> #VALUE! | S75: =R75+P75 -> #VALUE! | T75: =S75+P75 -> #VALUE! | U75: =T75+P75 -> #VALUE! | V75: =U75+P75 -> #VALUE! | W75: 334.27 | X75: 683.30815 | Y75: 0.1 | Z75: =IF(Tabela1[[#This Row],[Ano Aquisição]]=2023,0,IFERROR(VLOOKUP(H75,inflação!$F:$H,3,FALSE),"")) -> 0.5475 | AA75: 0.8 | AB75: =I75*-1 -> -98309.82 | AC75: =-(((P75*$W75)+($X75*12))*((1+$Y75)^AC$1)) -> #VALUE! | AD75: =-((((Q75-P75)*$W75)+($X75*12))*((1+$Y75)^AD$1)) -> #VALUE! | AE75: =-((((R75-Q75)*$W75)+($X75*12))*((1+$Y75)^AE$1)) -> #VALUE! | AF75: =-((((S75-R75)*$W75)+($X75*12))*((1+$Y75)^AF$1)) -> #VALUE! | AG75: =-((((T75-S75)*$W75)+($X75*12))*((1+$Y75)^AG$1)) -> #VALUE! | AH75: =-((((U75-T75)*$W75)+($X75*12))*((1+$Y75)^AH$1)) -> #VALUE! | AI75: =-((((V75-U75)*$W75)+($X75*12))*((1+$Y75)^AI$1)) -> #VALUE! | AJ75: =-(I75*(1+Z75)) -> -152134.45 | AK75: =AC75*(1-$AA75) -> #VALUE! | AL75: =AD75*(1-$AA75) -> #VALUE! | AM75: =AE75*(1-$AA75) -> #VALUE! | AN75: =AF75*(1-$AA75) -> #VALUE! | AO75: =AG75*(1-$AA75) -> #VALUE! | AP75: =AH75*(1-$AA75) -> #VALUE! | AQ75: =AI75*(1-$AA75) -> #VALUE! | AR75: =(NPV(Y75,AK75,AL75,AM75,AN75,AO75,AP75,AQ75)+(SUM(AJ75,(J75*-1))))-(NPV(Y75,AC75,AD75,AE75,AF75,AG75,AH75,AI75)) -> #VALUE! | AS75: =SUM(AC75:AI75) -> #VALUE! | AT75: =SUM(AK75:AQ75) -> #VALUE! | AU75: =(((AVERAGE(AC75:AI75)/1000)-(AVERAGE(AK75:AQ75)/1000))+(((AJ75/1000)*-1)/7)+((J75/1000)/7))*-1 -> #VALUE! | AV75: =AU75/(((J75/1000)+((AJ75*-1)/1000))) -> #VALUE! | AW75: =IF(L75>1.1,"Fase de Degradação",IF(L75<1,"Confiabilidade em Crescimento","Fase de Vida Útil")) -> Confiabilidade em Crescimento | AX75: =VLOOKUP(D75,#REF!,5,FALSE) -> #REF! | AZ75: X | BB75: =IFERROR(VLOOKUP(Tabela1[[#This Row],[Denominação]],[10]Planilha1!$A:$B,2,FALSE),"") -> 76068.68
A76: 75 | B76: CAB032 | C76: CAB032-CABINE DE SECAGEM | D76: 10006371 | E76: BR01-MOT-SAB-FINALL-CAB032 | F76: 2525 | G76: 46368 | H76: 2015 | I76: 716413.01 | J76: 253040 | K76: 1855986.5 | L76: 0.88 | M76: 5406 | N76: 64994 | O76: 552 | P76: =IFERROR(VLOOKUP(Tabela1[[#This Row],[TAG]],#REF!,14,FALSE),"") | Q76: =P76+P76 -> #VALUE! | R76: =Q76+P76 -> #VALUE! | S76: =R76+P76 -> #VALUE! | T76: =S76+P76 -> #VALUE! | U76: =T76+P76 -> #VALUE! | V76: =U76+P76 -> #VALUE! | W76: 1301.84 | X76: 12485.47 | Y76: 0.1 | Z76: =IF(Tabela1[[#This Row],[Ano Aquisição]]=2023,0,IFERROR(VLOOKUP(H76,inflação!$F:$H,3,FALSE),"")) -> 0.4834 | AA76: 0.8 | AB76: =I76*-1 -> -716413.01 | AC76: =-(((P76*$W76)+($X76*12))*((1+$Y76)^AC$1)) -> #VALUE! | AD76: =-((((Q76-P76)*$W76)+($X76*12))*((1+$Y76)^AD$1)) -> #VALUE! | AE76: =-((((R76-Q76)*$W76)+($X76*12))*((1+$Y76)^AE$1)) -> #VALUE! | AF76: =-((((S76-R76)*$W76)+($X76*12))*((1+$Y76)^AF$1)) -> #VALUE! | AG76: =-((((T76-S76)*$W76)+($X76*12))*((1+$Y76)^AG$1)) -> #VALUE! | AH76: =-((((U76-T76)*$W76)+($X76*12))*((1+$Y76)^AH$1)) -> #VALUE! | AI76: =-((((V76-U76)*$W76)+($X76*12))*((1+$Y76)^AI$1)) -> #VALUE! | AJ76: =-(I76*(1+Z76)) -> -1062727.1 | AK76: =AC76*(1-$AA76) -> #VALUE! | AL76: =AD76*(1-$AA76) -> #VALUE! | AM76: =AE76*(1-$AA76) -> #VALUE! | AN76: =AF76*(1-$AA76) -> #VALUE! | AO76: =AG76*(1-$AA76) -> #VALUE! | AP76: =AH76*(1-$AA76) -> #VALUE! | AQ76: =AI76*(1-$AA76) -> #VALUE! | AR76: =(NPV(Y76,AK76,AL76,AM76,AN76,AO76,AP76,AQ76)+(SUM(AJ76,(J76*-1))))-(NPV(Y76,AC76,AD76,AE76,AF76,AG76,AH76,AI76)) -> #VALUE! | AS76: =SUM(AC76:AI76) -> #VALUE! | AT76: =SUM(AK76:AQ76) -> #VALUE! | AU76: =(((AVERAGE(AC76:AI76)/1000)-(AVERAGE(AK76:AQ76)/1000))+(((AJ76/1000)*-1)/7)+((J76/1000)/7))*-1 -> #VALUE! | AV76: =AU76/(((J76/1000)+((AJ76*-1)/1000))) -> #VALUE! | AW76: =IF(L76>1.1,"Fase de Degradação",IF(L76<1,"Confiabilidade em Crescimento","Fase de Vida Útil")) -> Confiabilidade em Crescimento | AX76: =VLOOKUP(D76,#REF!,5,FALSE) -> #REF! | AZ76: X | BB76: =IFERROR(VLOOKUP(Tabela1[[#This Row],[Denominação]],[10]Planilha1!$A:$B,2,FALSE),"") -> 1855986.5
A77: 76 | B77: CAB033 | C77: CAB033-CABINE DE RESFRIAMENTO | D77: 10006372 | E77: BR01-MOT-SAB-FINALL-CAB033 | F77: 2525 | G77: 46369 | H77: 2015 | I77: 38997.88 | J77: 13418 | K77: 455992.23 | L77: 0.86 | M77: 5406 | N77: 65015 | O77: 271 | P77: =IFERROR(VLOOKUP(Tabela1[[#This Row],[TAG]],#REF!,14,FALSE),"") | Q77: =P77+P77 -> #VALUE! | R77: =Q77+P77 -> #VALUE! | S77: =R77+P77 -> #VALUE! | T77: =S77+P77 -> #VALUE! | U77: =T77+P77 -> #VALUE! | V77: =U77+P77 -> #VALUE! | W77: 944.14 | X77: 5718.79 | Y77: 0.1 | Z77: =IF(Tabela1[[#This Row],[Ano Aquisição]]=2023,0,IFERROR(VLOOKUP(H77,inflação!$F:$H,3,FALSE),"")) -> 0.4834 | AA77: 0.8 | AB77: =I77*-1 -> -38997.88 | AC77: =-(((P77*$W77)+($X77*12))*((1+$Y77)^AC$1)) -> #VALUE! | AD77: =-((((Q77-P77)*$W77)+($X77*12))*((1+$Y77)^AD$1)) -> #VALUE! | AE77: =-((((R77-Q77)*$W77)+($X77*12))*((1+$Y77)^AE$1)) -> #VALUE! | AF77: =-((((S77-R77)*$W77)+($X77*12))*((1+$Y77)^AF$1)) -> #VALUE! | AG77: =-((((T77-S77)*$W77)+($X77*12))*((1+$Y77)^AG$1)) -> #VALUE! | AH77: =-((((U77-T77)*$W77)+($X77*12))*((1+$Y77)^AH$1)) -> #VALUE! | AI77: =-((((V77-U77)*$W77)+($X77*12))*((1+$Y77)^AI$1)) -> #VALUE! | AJ77: =-(I77*(1+Z77)) -> -57849.455 | AK77: =AC77*(1-$AA77) -> #VALUE! | AL77: =AD77*(1-$AA77) -> #VALUE! | AM77: =AE77*(1-$AA77) -> #VALUE! | AN77: =AF77*(1-$AA77) -> #VALUE! | AO77: =AG77*(1-$AA77) -> #VALUE! | AP77: =AH77*(1-$AA77) -> #VALUE! | AQ77: =AI77*(1-$AA77) -> #VALUE! | AR77: =(NPV(Y77,AK77,AL77,AM77,AN77,AO77,AP77,AQ77)+(SUM(AJ77,(J77*-1))))-(NPV(Y77,AC77,AD77,AE77,AF77,AG77,AH77,AI77)) -> #VALUE! | AS77: =SUM(AC77:AI77) -> #VALUE! | AT77: =SUM(AK77:AQ77) -> #VALUE! | AU77: =(((AVERAGE(AC77:AI77)/1000)-(AVERAGE(AK77:AQ77)/1000))+(((AJ77/1000)*-1)/7)+((J77/1000)/7))*-1 -> #VALUE! | AV77: =AU77/(((J77/1000)+((AJ77*-1)/1000))) -> #VALUE! | AW77: =IF(L77>1.1,"Fase de Degradação",IF(L77<1,"Confiabilidade em Crescimento","Fase de Vida Útil")) -> Confiabilidade em Crescimento | AX77: =VLOOKUP(D77,#REF!,5,FALSE) -> #REF! | AZ77: X | BB77: =IFERROR(VLOOKUP(Tabela1[[#This Row],[Denominação]],[10]Planilha1!$A:$B,2,FALSE),"") -> 455992.23
A78: 77 | B78: CAB107 | C78: CAB107-CABINE DE TESTE | D78: 10000219 | E78: BR01-MOT-MON-LINHA1 | F78: 4023 | G78: 37312 | H78: 2008 | I78: 96683.38 | J78: 12719 | K78: 305704.55 | L78: 1.4 | M78: 4547 | N78: 198057 | O78: 375 | P78: =IFERROR(VLOOKUP(Tabela1[[#This Row],[TAG]],#REF!,14,FALSE),"") | Q78: =P78+P78 -> #VALUE! | R78: =Q78+P78 -> #VALUE! | S78: =R78+P78 -> #VALUE! | T78: =S78+P78 -> #VALUE! | U78: =T78+P78 -> #VALUE! | V78: =U78+P78 -> #VALUE! | W78: 534.11 | X78: 1044.73 | Y78: 0.1 | Z78: =IF(Tabela1[[#This Row],[Ano Aquisição]]=2023,0,IFERROR(VLOOKUP(H78,inflação!$F:$H,3,FALSE),"")) -> 0.8912 | AA78: 0.8 | AB78: =I78*-1 -> -96683.38 | AC78: =-(((P78*$W78)+($X78*12))*((1+$Y78)^AC$1)) -> #VALUE! | AD78: =-((((Q78-P78)*$W78)+($X78*12))*((1+$Y78)^AD$1)) -> #VALUE! | AE78: =-((((R78-Q78)*$W78)+($X78*12))*((1+$Y78)^AE$1)) -> #VALUE! | AF78: =-((((S78-R78)*$W78)+($X78*12))*((1+$Y78)^AF$1)) -> #VALUE! | AG78: =-((((T78-S78)*$W78)+($X78*12))*((1+$Y78)^AG$1)) -> #VALUE! | AH78: =-((((U78-T78)*$W78)+($X78*12))*((1+$Y78)^AH$1)) -> #VALUE! | AI78: =-((((V78-U78)*$W78)+($X78*12))*((1+$Y78)^AI$1)) -> #VALUE! | AJ78: =-(I78*(1+Z78)) -> -182847.61 | AK78: =AC78*(1-$AA78) -> #VALUE! | AL78: =AD78*(1-$AA78) -> #VALUE! | AM78: =AE78*(1-$AA78) -> #VALUE! | AN78: =AF78*(1-$AA78) -> #VALUE! | AO78: =AG78*(1-$AA78) -> #VALUE! | AP78: =AH78*(1-$AA78) -> #VALUE! | AQ78: =AI78*(1-$AA78) -> #VALUE! | AR78: =(NPV(Y78,AK78,AL78,AM78,AN78,AO78,AP78,AQ78)+(SUM(AJ78,(J78*-1))))-(NPV(Y78,AC78,AD78,AE78,AF78,AG78,AH78,AI78)) -> #VALUE! | AS78: =SUM(AC78:AI78) -> #VALUE! | AT78: =SUM(AK78:AQ78) -> #VALUE! | AU78: =(((AVERAGE(AC78:AI78)/1000)-(AVERAGE(AK78:AQ78)/1000))+(((AJ78/1000)*-1)/7)+((J78/1000)/7))*-1 -> #VALUE! | AV78: =AU78/(((J78/1000)+((AJ78*-1)/1000))) -> #VALUE! | AW78: =IF(L78>1.1,"Fase de Degradação",IF(L78<1,"Confiabilidade em Crescimento","Fase de Vida Útil")) -> Fase de Degradação | AX78: =VLOOKUP(D78,#REF!,5,FALSE) -> #REF! | AZ78: X | BB78: =IFERROR(VLOOKUP(Tabela1[[#This Row],[Denominação]],[10]Planilha1!$A:$B,2,FALSE),"") -> 305704.55
A79: 78 | B79: CAB108 | C79: CAB108-CABINE DE TESTE | D79: 10000222 | E79: BR01-MOT-MON-LINHA1 | F79: 4023 | G79: 20050 | H79: 1995 | I79: 228817.81 | J79: 0 | K79: 214767.06 | L79: 1.44 | M79: 4547 | N79: 198595 | O79: 325 | P79: =IFERROR(VLOOKUP(Tabela1[[#This Row],[TAG]],#REF!,14,FALSE),"") | Q79: =P79+P79 -> #VALUE! | R79: =Q79+P79 -> #VALUE! | S79: =R79+P79 -> #VALUE! | T79: =S79+P79 -> #VALUE! | U79: =T79+P79 -> #VALUE! | V79: =U79+P79 -> #VALUE! | W79: 342.36 | X79: 1079.65 | Y79: 0.1 | Z79: =IF(Tabela1[[#This Row],[Ano Aquisição]]=2023,0,IFERROR(VLOOKUP(H79,inflação!$F:$H,3,FALSE),"")) -> 1.7719846 | AA79: 0.8 | AB79: =I79*-1 -> -228817.81 | AC79: =-(((P79*$W79)+($X79*12))*((1+$Y79)^AC$1)) -> #VALUE! | AD79: =-((((Q79-P79)*$W79)+($X79*12))*((1+$Y79)^AD$1)) -> #VALUE! | AE79: =-((((R79-Q79)*$W79)+($X79*12))*((1+$Y79)^AE$1)) -> #VALUE! | AF79: =-((((S79-R79)*$W79)+($X79*12))*((1+$Y79)^AF$1)) -> #VALUE! | AG79: =-((((T79-S79)*$W79)+($X79*12))*((1+$Y79)^AG$1)) -> #VALUE! | AH79: =-((((U79-T79)*$W79)+($X79*12))*((1+$Y79)^AH$1)) -> #VALUE! | AI79: =-((((V79-U79)*$W79)+($X79*12))*((1+$Y79)^AI$1)) -> #VALUE! | AJ79: =-(I79*(1+Z79)) -> -634279.45 | AK79: =AC79*(1-$AA79) -> #VALUE! | AL79: =AD79*(1-$AA79) -> #VALUE! | AM79: =AE79*(1-$AA79) -> #VALUE! | AN79: =AF79*(1-$AA79) -> #VALUE! | AO79: =AG79*(1-$AA79) -> #VALUE! | AP79: =AH79*(1-$AA79) -> #VALUE! | AQ79: =AI79*(1-$AA79) -> #VALUE! | AR79: =(NPV(Y79,AK79,AL79,AM79,AN79,AO79,AP79,AQ79)+(SUM(AJ79,(J79*-1))))-(NPV(Y79,AC79,AD79,AE79,AF79,AG79,AH79,AI79)) -> #VALUE! | AS79: =SUM(AC79:AI79) -> #VALUE! | AT79: =SUM(AK79:AQ79) -> #VALUE! | AU79: =(((AVERAGE(AC79:AI79)/1000)-(AVERAGE(AK79:AQ79)/1000))+(((AJ79/1000)*-1)/7)+((J79/1000)/7))*-1 -> #VALUE! | AV79: =AU79/(((J79/1000)+((AJ79*-1)/1000))) -> #VALUE! | AW79: =IF(L79>1.1,"Fase de Degradação",IF(L79<1,"Confiabilidade em Crescimento","Fase de Vida Útil")) -> Fase de Degradação | AX79: =VLOOKUP(D79,#REF!,5,FALSE) -> #REF! | AZ79: X | BB79: =IFERROR(VLOOKUP(Tabela1[[#This Row],[Denominação]],[10]Planilha1!$A:$B,2,FALSE),"") -> 214767.06
A80: 79 | B80: CAB109 | C80: CAB109-CABINE DE TESTE | D80: 10006180 | E80: BR01-MOT-MON-LINHA3 | F80: 4022 | G80: - | H80: 2000 | I80: 43128.89 | J80: 0 | K80: 112318.25 | L80: 1.11 | M80: 2753 | N80: 85032 | O80: 101 | P80: =IFERROR(VLOOKUP(Tabela1[[#This Row],[TAG]],#REF!,14,FALSE),"") | Q80: =P80+P80 -> #VALUE! | R80: =Q80+P80 -> #VALUE! | S80: =R80+P80 -> #VALUE! | T80: =S80+P80 -> #VALUE! | U80: =T80+P80 -> #VALUE! | V80: =U80+P80 -> #VALUE! | W80: 362.52 | X80: 770.54 | Y80: 0.1 | Z80: =IF(Tabela1[[#This Row],[Ano Aquisição]]=2023,0,IFERROR(VLOOKUP(H80,inflação!$F:$H,3,FALSE),"")) -> 1.4548 | AA80: 0.8 | AB80: =I80*-1 -> -43128.89 | AC80: =-(((P80*$W80)+($X80*12))*((1+$Y80)^AC$1)) -> #VALUE! | AD80: =-((((Q80-P80)*$W80)+($X80*12))*((1+$Y80)^AD$1)) -> #VALUE! | AE80: =-((((R80-Q80)*$W80)+($X80*12))*((1+$Y80)^AE$1)) -> #VALUE! | AF80: =-((((S80-R80)*$W80)+($X80*12))*((1+$Y80)^AF$1)) -> #VALUE! | AG80: =-((((T80-S80)*$W80)+($X80*12))*((1+$Y80)^AG$1)) -> #VALUE! | AH80: =-((((U80-T80)*$W80)+($X80*12))*((1+$Y80)^AH$1)) -> #VALUE! | AI80: =-((((V80-U80)*$W80)+($X80*12))*((1+$Y80)^AI$1)) -> #VALUE! | AJ80: =-(I80*(1+Z80)) -> -105872.8 | AK80: =AC80*(1-$AA80) -> #VALUE! | AL80: =AD80*(1-$AA80) -> #VALUE! | AM80: =AE80*(1-$AA80) -> #VALUE! | AN80: =AF80*(1-$AA80) -> #VALUE! | AO80: =AG80*(1-$AA80) -> #VALUE! | AP80: =AH80*(1-$AA80) -> #VALUE! | AQ80: =AI80*(1-$AA80) -> #VALUE! | AR80: =(NPV(Y80,AK80,AL80,AM80,AN80,AO80,AP80,AQ80)+(SUM(AJ80,(J80*-1))))-(NPV(Y80,AC80,AD80,AE80,AF80,AG80,AH80,AI80)) -> #VALUE! | AS80: =SUM(AC80:AI80) -> #VALUE! | AT80: =SUM(AK80:AQ80) -> #VALUE! | AU80: =(((AVERAGE(AC80:AI80)/1000)-(AVERAGE(AK80:AQ80)/1000))+(((AJ80/1000)*-1)/7)+((J80/1000)/7))*-1 -> #VALUE! | AV80: =AU80/(((J80/1000)+((AJ80*-1)/1000))) -> #VALUE! | AW80: =IF(L80>1.1,"Fase de Degradação",IF(L80<1,"Confiabilidade em Crescimento","Fase de Vida Útil")) -> Fase de Degradação | AX80: =VLOOKUP(D80,#REF!,5,FALSE) -> #REF! | AZ80: X | BB80: =IFERROR(VLOOKUP(Tabela1[[#This Row],[Denominação]],[10]Planilha1!$A:$B,2,FALSE),"") -> 112318.25
A81: 80 | B81: CAB110 | C81: CAB110-CABINE DE ESTANQUEIDADE | D81: 10001830 | E81: BR01-MOT-MON-LINHA3 | F81: 4022 | G81: 31765 | H81: 2001 | I81: 43128.89 | J81: 0 | K81: 109194.5 | L81: 1.97 | M81: 2753 | N81: 193437 | O81: 163 | P81: =IFERROR(VLOOKUP(Tabela1[[#This Row],[TAG]],#REF!,14,FALSE),"") | Q81: =P81+P81 -> #VALUE! | R81: =Q81+P81 -> #VALUE! | S81: =R81+P81 -> #VALUE! | T81: =S81+P81 -> #VALUE! | U81: =T81+P81 -> #VALUE! | V81: =U81+P81 -> #VALUE! | W81: 353.87 | X81: 743.13528 | Y81: 0.1 | Z81: =IF(Tabela1[[#This Row],[Ano Aquisição]]=2023,0,IFERROR(VLOOKUP(H81,inflação!$F:$H,3,FALSE),"")) -> 1.3951 | AA81: 0.8 | AB81: =I81*-1 -> -43128.89 | AC81: =-(((P81*$W81)+($X81*12))*((1+$Y81)^AC$1)) -> #VALUE! | AD81: =-((((Q81-P81)*$W81)+($X81*12))*((1+$Y81)^AD$1)) -> #VALUE! | AE81: =-((((R81-Q81)*$W81)+($X81*12))*((1+$Y81)^AE$1)) -> #VALUE! | AF81: =-((((S81-R81)*$W81)+($X81*12))*((1+$Y81)^AF$1)) -> #VALUE! | AG81: =-((((T81-S81)*$W81)+($X81*12))*((1+$Y81)^AG$1)) -> #VALUE! | AH81: =-((((U81-T81)*$W81)+($X81*12))*((1+$Y81)^AH$1)) -> #VALUE! | AI81: =-((((V81-U81)*$W81)+($X81*12))*((1+$Y81)^AI$1)) -> #VALUE! | AJ81: =-(I81*(1+Z81)) -> -103298 | AK81: =AC81*(1-$AA81) -> #VALUE! | AL81: =AD81*(1-$AA81) -> #VALUE! | AM81: =AE81*(1-$AA81) -> #VALUE! | AN81: =AF81*(1-$AA81) -> #VALUE! | AO81: =AG81*(1-$AA81) -> #VALUE! | AP81: =AH81*(1-$AA81) -> #VALUE! | AQ81: =AI81*(1-$AA81) -> #VALUE! | AR81: =(NPV(Y81,AK81,AL81,AM81,AN81,AO81,AP81,AQ81)+(SUM(AJ81,(J81*-1))))-(NPV(Y81,AC81,AD81,AE81,AF81,AG81,AH81,AI81)) -> #VALUE! | AS81: =SUM(AC81:AI81) -> #VALUE! | AT81: =SUM(AK81:AQ81) -> #VALUE! | AU81: =(((AVERAGE(AC81:AI81)/1000)-(AVERAGE(AK81:AQ81)/1000))+(((AJ81/1000)*-1)/7)+((J81/1000)/7))*-1 -> #VALUE! | AV81: =AU81/(((J81/1000)+((AJ81*-1)/1000))) -> #VALUE! | AW81: =IF(L81>1.1,"Fase de Degradação",IF(L81<1,"Confiabilidade em Crescimento","Fase de Vida Útil")) -> Fase de Degradação | AX81: =VLOOKUP(D81,#REF!,5,FALSE) -> #REF! | AZ81: X | BB81: =IFERROR(VLOOKUP(Tabela1[[#This Row],[Denominação]],[10]Planilha1!$A:$B,2,FALSE),"") -> 109194.5
A82: 81 | B82: CAB111 | C82: CAB111-CABINE DE MONTAGEM | D82: 10003433 | E82: BR01-MOT-MON-LINHA3 | F82: 4022 | H82: 2003 | I82: 43128.89 | J82: 0 | K82: 77727.95 | L82: 0.92 | M82: 2753 | N82: 141712 | O82: 123 | P82: =IFERROR(VLOOKUP(Tabela1[[#This Row],[TAG]],#REF!,14,FALSE),"") | Q82: =P82+P82 -> #VALUE! | R82: =Q82+P82 -> #VALUE! | S82: =R82+P82 -> #VALUE! | T82: =S82+P82 -> #VALUE! | U82: =T82+P82 -> #VALUE! | V82: =U82+P82 -> #VALUE! | W82: 388.14 | X82: 331.92 | Y82: 0.1 | Z82: =IF(Tabela1[[#This Row],[Ano Aquisição]]=2023,0,IFERROR(VLOOKUP(H82,inflação!$F:$H,3,FALSE),"")) -> 1.1931 | AA82: 0.8 | AB82: =I82*-1 -> -43128.89 | AC82: =-(((P82*$W82)+($X82*12))*((1+$Y82)^AC$1)) -> #VALUE! | AD82: =-((((Q82-P82)*$W82)+($X82*12))*((1+$Y82)^AD$1)) -> #VALUE! | AE82: =-((((R82-Q82)*$W82)+($X82*12))*((1+$Y82)^AE$1)) -> #VALUE! | AF82: =-((((S82-R82)*$W82)+($X82*12))*((1+$Y82)^AF$1)) -> #VALUE! | AG82: =-((((T82-S82)*$W82)+($X82*12))*((1+$Y82)^AG$1)) -> #VALUE! | AH82: =-((((U82-T82)*$W82)+($X82*12))*((1+$Y82)^AH$1)) -> #VALUE! | AI82: =-((((V82-U82)*$W82)+($X82*12))*((1+$Y82)^AI$1)) -> #VALUE! | AJ82: =-(I82*(1+Z82)) -> -94585.969 | AK82: =AC82*(1-$AA82) -> #VALUE! | AL82: =AD82*(1-$AA82) -> #VALUE! | AM82: =AE82*(1-$AA82) -> #VALUE! | AN82: =AF82*(1-$AA82) -> #VALUE! | AO82: =AG82*(1-$AA82) -> #VALUE! | AP82: =AH82*(1-$AA82) -> #VALUE! | AQ82: =AI82*(1-$AA82) -> #VALUE! | AR82: =(NPV(Y82,AK82,AL82,AM82,AN82,AO82,AP82,AQ82)+(SUM(AJ82,(J82*-1))))-(NPV(Y82,AC82,AD82,AE82,AF82,AG82,AH82,AI82)) -> #VALUE! | AS82: =SUM(AC82:AI82) -> #VALUE! | AT82: =SUM(AK82:AQ82) -> #VALUE! | AU82: =(((AVERAGE(AC82:AI82)/1000)-(AVERAGE(AK82:AQ82)/1000))+(((AJ82/1000)*-1)/7)+((J82/1000)/7))*-1 -> #VALUE! | AV82: =AU82/(((J82/1000)+((AJ82*-1)/1000))) -> #VALUE! | AW82: =IF(L82>1.1,"Fase de Degradação",IF(L82<1,"Confiabilidade em Crescimento","Fase de Vida Útil")) -> Confiabilidade em Crescimento | AX82: =VLOOKUP(D82,#REF!,5,FALSE) -> #REF! | AZ82: X | BB82: =IFERROR(VLOOKUP(Tabela1[[#This Row],[Denominação]],[10]Planilha1!$A:$B,2,FALSE),"") -> 77727.95
A83: 82 | B83: CAB112 | C83: CAB112-CABINE DE MONTAGEM | D83: 10000244 | E83: BR01-MOT-MON-LINHA3 | F83: 4022 | H83: 2000 | I83: 43128.89 | J83: 0 | K83: 106169.36 | L83: 1.34 | M83: 2753 | N83: 147425 | O83: 114 | P83: =IFERROR(VLOOKUP(Tabela1[[#This Row],[TAG]],#REF!,14,FALSE),"") | Q83: =P83+P83 -> #VALUE! | R83: =Q83+P83 -> #VALUE! | S83: =R83+P83 -> #VALUE! | T83: =S83+P83 -> #VALUE! | U83: =T83+P83 -> #VALUE! | V83: =U83+P83 -> #VALUE! | W83: 309.21 | X83: 779.38 | Y83: 0.1 | Z83: =IF(Tabela1[[#This Row],[Ano Aquisição]]=2023,0,IFERROR(VLOOKUP(H83,inflação!$F:$H,3,FALSE),"")) -> 1.4548 | AA83: 0.8 | AB83: =I83*-1 -> -43128.89 | AC83: =-(((P83*$W83)+($X83*12))*((1+$Y83)^AC$1)) -> #VALUE! | AD83: =-((((Q83-P83)*$W83)+($X83*12))*((1+$Y83)^AD$1)) -> #VALUE! | AE83: =-((((R83-Q83)*$W83)+($X83*12))*((1+$Y83)^AE$1)) -> #VALUE! | AF83: =-((((S83-R83)*$W83)+($X83*12))*((1+$Y83)^AF$1)) -> #VALUE! | AG83: =-((((T83-S83)*$W83)+($X83*12))*((1+$Y83)^AG$1)) -> #VALUE! | AH83: =-((((U83-T83)*$W83)+($X83*12))*((1+$Y83)^AH$1)) -> #VALUE! | AI83: =-((((V83-U83)*$W83)+($X83*12))*((1+$Y83)^AI$1)) -> #VALUE! | AJ83: =-(I83*(1+Z83)) -> -105872.8 | AK83: =AC83*(1-$AA83) -> #VALUE! | AL83: =AD83*(1-$AA83) -> #VALUE! | AM83: =AE83*(1-$AA83) -> #VALUE! | AN83: =AF83*(1-$AA83) -> #VALUE! | AO83: =AG83*(1-$AA83) -> #VALUE! | AP83: =AH83*(1-$AA83) -> #VALUE! | AQ83: =AI83*(1-$AA83) -> #VALUE! | AR83: =(NPV(Y83,AK83,AL83,AM83,AN83,AO83,AP83,AQ83)+(SUM(AJ83,(J83*-1))))-(NPV(Y83,AC83,AD83,AE83,AF83,AG83,AH83,AI83)) -> #VALUE! | AS83: =SUM(AC83:AI83) -> #VALUE! | AT83: =SUM(AK83:AQ83) -> #VALUE! | AU83: =(((AVERAGE(AC83:AI83)/1000)-(AVERAGE(AK83:AQ83)/1000))+(((AJ83/1000)*-1)/7)+((J83/1000)/7))*-1 -> #VALUE! | AV83: =AU83/(((J83/1000)+((AJ83*-1)/1000))) -> #VALUE! | AW83: =IF(L83>1.1,"Fase de Degradação",IF(L83<1,"Confiabilidade em Crescimento","Fase de Vida Útil")) -> Fase de Degradação | AX83: =VLOOKUP(D83,#REF!,5,FALSE) -> #REF! | AZ83: X | BB83: =IFERROR(VLOOKUP(Tabela1[[#This Row],[Denominação]],[10]Planilha1!$A:$B,2,FALSE),"") -> 106169.36
A84: 83 | B84: CAB114 | C84: CAB114-CABINE DE MONTAGEM | D84: 10003420 | E84: BR01-MOT-MON-LINHA3 | F84: 4022 | G84: 20343 | H84: 2003 | I84: 43128.89 | J84: 0 | K84: 229737.42 | L84: 1.34 | M84: 2753 | N84: 168049 | O84: 312 | P84: =IFERROR(VLOOKUP(Tabela1[[#This Row],[TAG]],#REF!,14,FALSE),"") | Q84: =P84+P84 -> #VALUE! | R84: =Q84+P84 -> #VALUE! | S84: =R84+P84 -> #VALUE! | T84: =S84+P84 -> #VALUE! | U84: =T84+P84 -> #VALUE! | V84: =U84+P84 -> #VALUE! | W84: 456.74 | X84: 754.87 | Y84: 0.1 | Z84: =IF(Tabela1[[#This Row],[Ano Aquisição]]=2023,0,IFERROR(VLOOKUP(H84,inflação!$F:$H,3,FALSE),"")) -> 1.1931 | AA84: 0.8 | AB84: =I84*-1 -> -43128.89 | AC84: =-(((P84*$W84)+($X84*12))*((1+$Y84)^AC$1)) -> #VALUE! | AD84: =-((((Q84-P84)*$W84)+($X84*12))*((1+$Y84)^AD$1)) -> #VALUE! | AE84: =-((((R84-Q84)*$W84)+($X84*12))*((1+$Y84)^AE$1)) -> #VALUE! | AF84: =-((((S84-R84)*$W84)+($X84*12))*((1+$Y84)^AF$1)) -> #VALUE! | AG84: =-((((T84-S84)*$W84)+($X84*12))*((1+$Y84)^AG$1)) -> #VALUE! | AH84: =-((((U84-T84)*$W84)+($X84*12))*((1+$Y84)^AH$1)) -> #VALUE! | AI84: =-((((V84-U84)*$W84)+($X84*12))*((1+$Y84)^AI$1)) -> #VALUE! | AJ84: =-(I84*(1+Z84)) -> -94585.969 | AK84: =AC84*(1-$AA84) -> #VALUE! | AL84: =AD84*(1-$AA84) -> #VALUE! | AM84: =AE84*(1-$AA84) -> #VALUE! | AN84: =AF84*(1-$AA84) -> #VALUE! | AO84: =AG84*(1-$AA84) -> #VALUE! | AP84: =AH84*(1-$AA84) -> #VALUE! | AQ84: =AI84*(1-$AA84) -> #VALUE! | AR84: =(NPV(Y84,AK84,AL84,AM84,AN84,AO84,AP84,AQ84)+(SUM(AJ84,(J84*-1))))-(NPV(Y84,AC84,AD84,AE84,AF84,AG84,AH84,AI84)) -> #VALUE! | AS84: =SUM(AC84:AI84) -> #VALUE! | AT84: =SUM(AK84:AQ84) -> #VALUE! | AU84: =(((AVERAGE(AC84:AI84)/1000)-(AVERAGE(AK84:AQ84)/1000))+(((AJ84/1000)*-1)/7)+((J84/1000)/7))*-1 -> #VALUE! | AV84: =AU84/(((J84/1000)+((AJ84*-1)/1000))) -> #VALUE! | AW84: =IF(L84>1.1,"Fase de Degradação",IF(L84<1,"Confiabilidade em Crescimento","Fase de Vida Útil")) -> Fase de Degradação | AX84: =VLOOKUP(D84,#REF!,5,FALSE) -> #REF! | AZ84: X | BB84: =IFERROR(VLOOKUP(Tabela1[[#This Row],[Denominação]],[10]Planilha1!$A:$B,2,FALSE),"") -> 229737.42
A85: 84 | B85: CAB115 | C85: CAB115-CABINE DE TESTE | D85: 10004021 | E85: BR01-MOT-MON-LINHA3 | F85: 4022 | G85: 20028 | H85: 1994 | I85: 92332.73 | J85: 0 | K85: 177850.68 | L85: 1.11 | M85: 2753 | N85: 141297 | O85: 312 | P85: =IFERROR(VLOOKUP(Tabela1[[#This Row],[TAG]],#REF!,14,FALSE),"") | Q85: =P85+P85 -> #VALUE! | R85: =Q85+P85 -> #VALUE! | S85: =R85+P85 -> #VALUE! | T85: =S85+P85 -> #VALUE! | U85: =T85+P85 -> #VALUE! | V85: =U85+P85 -> #VALUE! | W85: 423.74 | X85: 956.95 | Y85: 0.1 | Z85: =IF(Tabela1[[#This Row],[Ano Aquisição]]=2023,0,IFERROR(VLOOKUP(H85,inflação!$F:$H,3,FALSE),"")) -> 1.8354692 | AA85: 0.8 | AB85: =I85*-1 -> -92332.73 | AC85: =-(((P85*$W85)+($X85*12))*((1+$Y85)^AC$1)) -> #VALUE! | AD85: =-((((Q85-P85)*$W85)+($X85*12))*((1+$Y85)^AD$1)) -> #VALUE! | AE85: =-((((R85-Q85)*$W85)+($X85*12))*((1+$Y85)^AE$1)) -> #VALUE! | AF85: =-((((S85-R85)*$W85)+($X85*12))*((1+$Y85)^AF$1)) -> #VALUE! | AG85: =-((((T85-S85)*$W85)+($X85*12))*((1+$Y85)^AG$1)) -> #VALUE! | AH85: =-((((U85-T85)*$W85)+($X85*12))*((1+$Y85)^AH$1)) -> #VALUE! | AI85: =-((((V85-U85)*$W85)+($X85*12))*((1+$Y85)^AI$1)) -> #VALUE! | AJ85: =-(I85*(1+Z85)) -> -261806.61 | AK85: =AC85*(1-$AA85) -> #VALUE! | AL85: =AD85*(1-$AA85) -> #VALUE! | AM85: =AE85*(1-$AA85) -> #VALUE! | AN85: =AF85*(1-$AA85) -> #VALUE! | AO85: =AG85*(1-$AA85) -> #VALUE! | AP85: =AH85*(1-$AA85) -> #VALUE! | AQ85: =AI85*(1-$AA85) -> #VALUE! | AR85: =(NPV(Y85,AK85,AL85,AM85,AN85,AO85,AP85,AQ85)+(SUM(AJ85,(J85*-1))))-(NPV(Y85,AC85,AD85,AE85,AF85,AG85,AH85,AI85)) -> #VALUE! | AS85: =SUM(AC85:AI85) -> #VALUE! | AT85: =SUM(AK85:AQ85) -> #VALUE! | AU85: =(((AVERAGE(AC85:AI85)/1000)-(AVERAGE(AK85:AQ85)/1000))+(((AJ85/1000)*-1)/7)+((J85/1000)/7))*-1 -> #VALUE! | AV85: =AU85/(((J85/1000)+((AJ85*-1)/1000))) -> #VALUE! | AW85: =IF(L85>1.1,"Fase de Degradação",IF(L85<1,"Confiabilidade em Crescimento","Fase de Vida Útil")) -> Fase de Degradação | AX85: =VLOOKUP(D85,#REF!,5,FALSE) -> #REF! | AZ85: X | BB85: =IFERROR(VLOOKUP(Tabela1[[#This Row],[Denominação]],[10]Planilha1!$A:$B,2,FALSE),"") -> 177850.68
A86: 85 | B86: CAB116 | C86: CAB116-CABINE DE TESTE | D86: 10006183 | E86: BR01-MOT-MON-LINHA3 | F86: 4022 | G86: 20383 | H86: 2001 | I86: 133650.03 | J86: 0 | K86: 113622.52 | L86: 1.18 | M86: 2753 | N86: 84636 | O86: 156 | P86: =IFERROR(VLOOKUP(Tabela1[[#This Row],[TAG]],#REF!,14,FALSE),"") | Q86: =P86+P86 -> #VALUE! | R86: =Q86+P86 -> #VALUE! | S86: =R86+P86 -> #VALUE! | T86: =S86+P86 -> #VALUE! | U86: =T86+P86 -> #VALUE! | V86: =U86+P86 -> #VALUE! | W86: 460.32 | X86: 1022.92 | Y86: 0.1 | Z86: =IF(Tabela1[[#This Row],[Ano Aquisição]]=2023,0,IFERROR(VLOOKUP(H86,inflação!$F:$H,3,FALSE),"")) -> 1.3951 | AA86: 0.8 | AB86: =I86*-1 -> -133650.03 | AC86: =-(((P86*$W86)+($X86*12))*((1+$Y86)^AC$1)) -> #VALUE! | AD86: =-((((Q86-P86)*$W86)+($X86*12))*((1+$Y86)^AD$1)) -> #VALUE! | AE86: =-((((R86-Q86)*$W86)+($X86*12))*((1+$Y86)^AE$1)) -> #VALUE! | AF86: =-((((S86-R86)*$W86)+($X86*12))*((1+$Y86)^AF$1)) -> #VALUE! | AG86: =-((((T86-S86)*$W86)+($X86*12))*((1+$Y86)^AG$1)) -> #VALUE! | AH86: =-((((U86-T86)*$W86)+($X86*12))*((1+$Y86)^AH$1)) -> #VALUE! | AI86: =-((((V86-U86)*$W86)+($X86*12))*((1+$Y86)^AI$1)) -> #VALUE! | AJ86: =-(I86*(1+Z86)) -> -320105.19 | AK86: =AC86*(1-$AA86) -> #VALUE! | AL86: =AD86*(1-$AA86) -> #VALUE! | AM86: =AE86*(1-$AA86) -> #VALUE! | AN86: =AF86*(1-$AA86) -> #VALUE! | AO86: =AG86*(1-$AA86) -> #VALUE! | AP86: =AH86*(1-$AA86) -> #VALUE! | AQ86: =AI86*(1-$AA86) -> #VALUE! | AR86: =(NPV(Y86,AK86,AL86,AM86,AN86,AO86,AP86,AQ86)+(SUM(AJ86,(J86*-1))))-(NPV(Y86,AC86,AD86,AE86,AF86,AG86,AH86,AI86)) -> #VALUE! | AS86: =SUM(AC86:AI86) -> #VALUE! | AT86: =SUM(AK86:AQ86) -> #VALUE! | AU86: =(((AVERAGE(AC86:AI86)/1000)-(AVERAGE(AK86:AQ86)/1000))+(((AJ86/1000)*-1)/7)+((J86/1000)/7))*-1 -> #VALUE! | AV86: =AU86/(((J86/1000)+((AJ86*-1)/1000))) -> #VALUE! | AW86: =IF(L86>1.1,"Fase de Degradação",IF(L86<1,"Confiabilidade em Crescimento","Fase de Vida Útil")) -> Fase de Degradação | AX86: =VLOOKUP(D86,#REF!,5,FALSE) -> #REF! | AZ86: X | BB86: =IFERROR(VLOOKUP(Tabela1[[#This Row],[Denominação]],[10]Planilha1!$A:$B,2,FALSE),"") -> 113622.52
A87: 86 | B87: CAB117 | C87: CAB117-CABINE DE REGULAGEM | D87: 10004567 | E87: BR01-MOT-MON-LINHA2 | F87: 4026 | G87: 36403 | H87: 2009 | I87: 216216.11 | J87: 11815 | K87: 473760.07 | L87: 1.16 | M87: 2994 | N87: 142214 | O87: 378 | P87: =IFERROR(VLOOKUP(Tabela1[[#This Row],[TAG]],#REF!,14,FALSE),"") | Q87: =P87+P87 -> #VALUE! | R87: =Q87+P87 -> #VALUE! | S87: =R87+P87 -> #VALUE! | T87: =S87+P87 -> #VALUE! | U87: =T87+P87 -> #VALUE! | V87: =U87+P87 -> #VALUE! | W87: 517.37 | X87: 1892.31 | Y87: 0.1 | Z87: =IF(Tabela1[[#This Row],[Ano Aquisição]]=2023,0,IFERROR(VLOOKUP(H87,inflação!$F:$H,3,FALSE),"")) -> 0.8322 | AA87: 0.8 | AB87: =I87*-1 -> -216216.11 | AC87: =-(((P87*$W87)+($X87*12))*((1+$Y87)^AC$1)) -> #VALUE! | AD87: =-((((Q87-P87)*$W87)+($X87*12))*((1+$Y87)^AD$1)) -> #VALUE! | AE87: =-((((R87-Q87)*$W87)+($X87*12))*((1+$Y87)^AE$1)) -> #VALUE! | AF87: =-((((S87-R87)*$W87)+($X87*12))*((1+$Y87)^AF$1)) -> #VALUE! | AG87: =-((((T87-S87)*$W87)+($X87*12))*((1+$Y87)^AG$1)) -> #VALUE! | AH87: =-((((U87-T87)*$W87)+($X87*12))*((1+$Y87)^AH$1)) -> #VALUE! | AI87: =-((((V87-U87)*$W87)+($X87*12))*((1+$Y87)^AI$1)) -> #VALUE! | AJ87: =-(I87*(1+Z87)) -> -396151.16 | AK87: =AC87*(1-$AA87) -> #VALUE! | AL87: =AD87*(1-$AA87) -> #VALUE! | AM87: =AE87*(1-$AA87) -> #VALUE! | AN87: =AF87*(1-$AA87) -> #VALUE! | AO87: =AG87*(1-$AA87) -> #VALUE! | AP87: =AH87*(1-$AA87) -> #VALUE! | AQ87: =AI87*(1-$AA87) -> #VALUE! | AR87: =(NPV(Y87,AK87,AL87,AM87,AN87,AO87,AP87,AQ87)+(SUM(AJ87,(J87*-1))))-(NPV(Y87,AC87,AD87,AE87,AF87,AG87,AH87,AI87)) -> #VALUE! | AS87: =SUM(AC87:AI87) -> #VALUE! | AT87: =SUM(AK87:AQ87) -> #VALUE! | AU87: =(((AVERAGE(AC87:AI87)/1000)-(AVERAGE(AK87:AQ87)/1000))+(((AJ87/1000)*-1)/7)+((J87/1000)/7))*-1 -> #VALUE! | AV87: =AU87/(((J87/1000)+((AJ87*-1)/1000))) -> #VALUE! | AW87: =IF(L87>1.1,"Fase de Degradação",IF(L87<1,"Confiabilidade em Crescimento","Fase de Vida Útil")) -> Fase de Degradação | AX87: =VLOOKUP(D87,#REF!,5,FALSE) -> #REF! | AZ87: X | BB87: =IFERROR(VLOOKUP(Tabela1[[#This Row],[Denominação]],[10]Planilha1!$A:$B,2,FALSE),"") -> 473760.07
A88: 87 | B88: CAB118 | C88: CAB118-CABINE DE REGULAGEM | D88: 10004568 | E88: BR01-MOT-MON-LINHA2 | F88: 4026 | G88: 36401 | H88: 2009 | I88: 221090.19 | J88: 13108 | K88: 310092.51 | L88: 0.99 | M88: 2994 | N88: 144014 | O88: 289 | P88: =IFERROR(VLOOKUP(Tabela1[[#This Row],[TAG]],#REF!,14,FALSE),"") | Q88: =P88+P88 -> #VALUE! | R88: =Q88+P88 -> #VALUE! | S88: =R88+P88 -> #VALUE! | T88: =S88+P88 -> #VALUE! | U88: =T88+P88 -> #VALUE! | V88: =U88+P88 -> #VALUE! | W88: 503.21 | X88: 717.25 | Y88: 0.1 | Z88: =IF(Tabela1[[#This Row],[Ano Aquisição]]=2023,0,IFERROR(VLOOKUP(H88,inflação!$F:$H,3,FALSE),"")) -> 0.8322 | AA88: 0.8 | AB88: =I88*-1 -> -221090.19 | AC88: =-(((P88*$W88)+($X88*12))*((1+$Y88)^AC$1)) -> #VALUE! | AD88: =-((((Q88-P88)*$W88)+($X88*12))*((1+$Y88)^AD$1)) -> #VALUE! | AE88: =-((((R88-Q88)*$W88)+($X88*12))*((1+$Y88)^AE$1)) -> #VALUE! | AF88: =-((((S88-R88)*$W88)+($X88*12))*((1+$Y88)^AF$1)) -> #VALUE! | AG88: =-((((T88-S88)*$W88)+($X88*12))*((1+$Y88)^AG$1)) -> #VALUE! | AH88: =-((((U88-T88)*$W88)+($X88*12))*((1+$Y88)^AH$1)) -> #VALUE! | AI88: =-((((V88-U88)*$W88)+($X88*12))*((1+$Y88)^AI$1)) -> #VALUE! | AJ88: =-(I88*(1+Z88)) -> -405081.45 | AK88: =AC88*(1-$AA88) -> #VALUE! | AL88: =AD88*(1-$AA88) -> #VALUE! | AM88: =AE88*(1-$AA88) -> #VALUE! | AN88: =AF88*(1-$AA88) -> #VALUE! | AO88: =AG88*(1-$AA88) -> #VALUE! | AP88: =AH88*(1-$AA88) -> #VALUE! | AQ88: =AI88*(1-$AA88) -> #VALUE! | AR88: =(NPV(Y88,AK88,AL88,AM88,AN88,AO88,AP88,AQ88)+(SUM(AJ88,(J88*-1))))-(NPV(Y88,AC88,AD88,AE88,AF88,AG88,AH88,AI88)) -> #VALUE! | AS88: =SUM(AC88:AI88) -> #VALUE! | AT88: =SUM(AK88:AQ88) -> #VALUE! | AU88: =(((AVERAGE(AC88:AI88)/1000)-(AVERAGE(AK88:AQ88)/1000))+(((AJ88/1000)*-1)/7)+((J88/1000)/7))*-1 -> #VALUE! | AV88: =AU88/(((J88/1000)+((AJ88*-1)/1000))) -> #VALUE! | AW88: =IF(L88>1.1,"Fase de Degradação",IF(L88<1,"Confiabilidade em Crescimento","Fase de Vida Útil")) -> Confiabilidade em Crescimento | AX88: =VLOOKUP(D88,#REF!,5,FALSE) -> #REF! | AZ88: X | BB88: =IFERROR(VLOOKUP(Tabela1[[#This Row],[Denominação]],[10]Planilha1!$A:$B,2,FALSE),"") -> 310092.51
A89: 88 | B89: CAB119 | C89: CAB119-CABINE DE REGULAGEM | D89: 10004569 | E89: BR01-MOT-MON-LINHA2 | F89: 4026 | G89: 36400 | H89: 2009 | I89: 233912.15 | J89: 13108 | K89: 531143.43 | L89: 0.99 | M89: 2994 | N89: 142202 | O89: 320 | P89: =IFERROR(VLOOKUP(Tabela1[[#This Row],[TAG]],#REF!,14,FALSE),"") | Q89: =P89+P89 -> #VALUE! | R89: =Q89+P89 -> #VALUE! | S89: =R89+P89 -> #VALUE! | T89: =S89+P89 -> #VALUE! | U89: =T89+P89 -> #VALUE! | V89: =U89+P89 -> #VALUE! | W89: 347.11 | X89: 1234.2 | Y89: 0.1 | Z89: =IF(Tabela1[[#This Row],[Ano Aquisição]]=2023,0,IFERROR(VLOOKUP(H89,inflação!$F:$H,3,FALSE),"")) -> 0.8322 | AA89: 0.8 | AB89: =I89*-1 -> -233912.15 | AC89: =-(((P89*$W89)+($X89*12))*((1+$Y89)^AC$1)) -> #VALUE! | AD89: =-((((Q89-P89)*$W89)+($X89*12))*((1+$Y89)^AD$1)) -> #VALUE! | AE89: =-((((R89-Q89)*$W89)+($X89*12))*((1+$Y89)^AE$1)) -> #VALUE! | AF89: =-((((S89-R89)*$W89)+($X89*12))*((1+$Y89)^AF$1)) -> #VALUE! | AG89: =-((((T89-S89)*$W89)+($X89*12))*((1+$Y89)^AG$1)) -> #VALUE! | AH89: =-((((U89-T89)*$W89)+($X89*12))*((1+$Y89)^AH$1)) -> #VALUE! | AI89: =-((((V89-U89)*$W89)+($X89*12))*((1+$Y89)^AI$1)) -> #VALUE! | AJ89: =-(I89*(1+Z89)) -> -428573.84 | AK89: =AC89*(1-$AA89) -> #VALUE! | AL89: =AD89*(1-$AA89) -> #VALUE! | AM89: =AE89*(1-$AA89) -> #VALUE! | AN89: =AF89*(1-$AA89) -> #VALUE! | AO89: =AG89*(1-$AA89) -> #VALUE! | AP89: =AH89*(1-$AA89) -> #VALUE! | AQ89: =AI89*(1-$AA89) -> #VALUE! | AR89: =(NPV(Y89,AK89,AL89,AM89,AN89,AO89,AP89,AQ89)+(SUM(AJ89,(J89*-1))))-(NPV(Y89,AC89,AD89,AE89,AF89,AG89,AH89,AI89)) -> #VALUE! | AS89: =SUM(AC89:AI89) -> #VALUE! | AT89: =SUM(AK89:AQ89) -> #VALUE! | AU89: =(((AVERAGE(AC89:AI89)/1000)-(AVERAGE(AK89:AQ89)/1000))+(((AJ89/1000)*-1)/7)+((J89/1000)/7))*-1 -> #VALUE! | AV89: =AU89/(((J89/1000)+((AJ89*-1)/1000))) -> #VALUE! | AW89: =IF(L89>1.1,"Fase de Degradação",IF(L89<1,"Confiabilidade em Crescimento","Fase de Vida Útil")) -> Confiabilidade em Crescimento | AX89: =VLOOKUP(D89,#REF!,5,FALSE) -> #REF! | AZ89: X | BB89: =IFERROR(VLOOKUP(Tabela1[[#This Row],[Denominação]],[10]Planilha1!$A:$B,2,FALSE),"") -> 531143.43
A90: 89 | B90: CAB120 | C90: CAB120-CABINE DE REGULAGEM | D90: 10005906 | E90: BR01-MOT-MON-LINHA2 | F90: 4026 | G90: 36402 | H90: 2009 | I90: 217489.28 | J90: 13108 | K90: 268944.68 | L90: 1.37 | M90: 2994 | N90: 100949 | O90: 177 | P90: =IFERROR(VLOOKUP(Tabela1[[#This Row],[TAG]],#REF!,14,FALSE),"") | Q90: =P90+P90 -> #VALUE! | R90: =Q90+P90 -> #VALUE! | S90: =R90+P90 -> #VALUE! | T90: =S90+P90 -> #VALUE! | U90: =T90+P90 -> #VALUE! | V90: =U90+P90 -> #VALUE! | W90: 569.92 | X90: 1164.7 | Y90: 0.1 | Z90: =IF(Tabela1[[#This Row],[Ano Aquisição]]=2023,0,IFERROR(VLOOKUP(H90,inflação!$F:$H,3,FALSE),"")) -> 0.8322 | AA90: 0.8 | AB90: =I90*-1 -> -217489.28 | AC90: =-(((P90*$W90)+($X90*12))*((1+$Y90)^AC$1)) -> #VALUE! | AD90: =-((((Q90-P90)*$W90)+($X90*12))*((1+$Y90)^AD$1)) -> #VALUE! | AE90: =-((((R90-Q90)*$W90)+($X90*12))*((1+$Y90)^AE$1)) -> #VALUE! | AF90: =-((((S90-R90)*$W90)+($X90*12))*((1+$Y90)^AF$1)) -> #VALUE! | AG90: =-((((T90-S90)*$W90)+($X90*12))*((1+$Y90)^AG$1)) -> #VALUE! | AH90: =-((((U90-T90)*$W90)+($X90*12))*((1+$Y90)^AH$1)) -> #VALUE! | AI90: =-((((V90-U90)*$W90)+($X90*12))*((1+$Y90)^AI$1)) -> #VALUE! | AJ90: =-(I90*(1+Z90)) -> -398483.86 | AK90: =AC90*(1-$AA90) -> #VALUE! | AL90: =AD90*(1-$AA90) -> #VALUE! | AM90: =AE90*(1-$AA90) -> #VALUE! | AN90: =AF90*(1-$AA90) -> #VALUE! | AO90: =AG90*(1-$AA90) -> #VALUE! | AP90: =AH90*(1-$AA90) -> #VALUE! | AQ90: =AI90*(1-$AA90) -> #VALUE! | AR90: =(NPV(Y90,AK90,AL90,AM90,AN90,AO90,AP90,AQ90)+(SUM(AJ90,(J90*-1))))-(NPV(Y90,AC90,AD90,AE90,AF90,AG90,AH90,AI90)) -> #VALUE! | AS90: =SUM(AC90:AI90) -> #VALUE! | AT90: =SUM(AK90:AQ90) -> #VALUE! | AU90: =(((AVERAGE(AC90:AI90)/1000)-(AVERAGE(AK90:AQ90)/1000))+(((AJ90/1000)*-1)/7)+((J90/1000)/7))*-1 -> #VALUE! | AV90: =AU90/(((J90/1000)+((AJ90*-1)/1000))) -> #VALUE! | AW90: =IF(L90>1.1,"Fase de Degradação",IF(L90<1,"Confiabilidade em Crescimento","Fase de Vida Útil")) -> Fase de Degradação | AX90: =VLOOKUP(D90,#REF!,5,FALSE) -> #REF! | AZ90: X | BB90: =IFERROR(VLOOKUP(Tabela1[[#This Row],[Denominação]],[10]Planilha1!$A:$B,2,FALSE),"") -> 268944.68
A91: 90 | B91: CAB121 | C91: CAB121-CABINE DE TESTE | D91: 10005907 | E91: BR01-MOT-MON-LINHA1 | F91: 4023 | G91: 37313 | H91: 2008 | I91: 154287.62 | J91: 9522 | K91: 180353.57 | L91: 0.99 | M91: 4547 | N91: 92832 | O91: 194 | P91: =IFERROR(VLOOKUP(Tabela1[[#This Row],[TAG]],#REF!,14,FALSE),"") | Q91: =P91+P91 -> #VALUE! | R91: =Q91+P91 -> #VALUE! | S91: =R91+P91 -> #VALUE! | T91: =S91+P91 -> #VALUE! | U91: =T91+P91 -> #VALUE! | V91: =U91+P91 -> #VALUE! | W91: 489.23 | X91: 931.69333 | Y91: 0.1 | Z91: =IF(Tabela1[[#This Row],[Ano Aquisição]]=2023,0,IFERROR(VLOOKUP(H91,inflação!$F:$H,3,FALSE),"")) -> 0.8912 | AA91: 0.8 | AB91: =I91*-1 -> -154287.62 | AC91: =-(((P91*$W91)+($X91*12))*((1+$Y91)^AC$1)) -> #VALUE! | AD91: =-((((Q91-P91)*$W91)+($X91*12))*((1+$Y91)^AD$1)) -> #VALUE! | AE91: =-((((R91-Q91)*$W91)+($X91*12))*((1+$Y91)^AE$1)) -> #VALUE! | AF91: =-((((S91-R91)*$W91)+($X91*12))*((1+$Y91)^AF$1)) -> #VALUE! | AG91: =-((((T91-S91)*$W91)+($X91*12))*((1+$Y91)^AG$1)) -> #VALUE! | AH91: =-((((U91-T91)*$W91)+($X91*12))*((1+$Y91)^AH$1)) -> #VALUE! | AI91: =-((((V91-U91)*$W91)+($X91*12))*((1+$Y91)^AI$1)) -> #VALUE! | AJ91: =-(I91*(1+Z91)) -> -291788.75 | AK91: =AC91*(1-$AA91) -> #VALUE! | AL91: =AD91*(1-$AA91) -> #VALUE! | AM91: =AE91*(1-$AA91) -> #VALUE! | AN91: =AF91*(1-$AA91) -> #VALUE! | AO91: =AG91*(1-$AA91) -> #VALUE! | AP91: =AH91*(1-$AA91) -> #VALUE! | AQ91: =AI91*(1-$AA91) -> #VALUE! | AR91: =(NPV(Y91,AK91,AL91,AM91,AN91,AO91,AP91,AQ91)+(SUM(AJ91,(J91*-1))))-(NPV(Y91,AC91,AD91,AE91,AF91,AG91,AH91,AI91)) -> #VALUE! | AS91: =SUM(AC91:AI91) -> #VALUE! | AT91: =SUM(AK91:AQ91) -> #VALUE! | AU91: =(((AVERAGE(AC91:AI91)/1000)-(AVERAGE(AK91:AQ91)/1000))+(((AJ91/1000)*-1)/7)+((J91/1000)/7))*-1 -> #VALUE! | AV91: =AU91/(((J91/1000)+((AJ91*-1)/1000))) -> #VALUE! | AW91: =IF(L91>1.1,"Fase de Degradação",IF(L91<1,"Confiabilidade em Crescimento","Fase de Vida Útil")) -> Confiabilidade em Crescimento | AX91: =VLOOKUP(D91,#REF!,5,FALSE) -> #REF! | AZ91: X | BB91: =IFERROR(VLOOKUP(Tabela1[[#This Row],[Denominação]],[10]Planilha1!$A:$B,2,FALSE),"") -> 180353.57
A92: 91 | B92: CAB122 | C92: CAB122 CABINE DE REGULAGEM E TESTE | D92: 10004516 | E92: BR01-MOT-MON-LINHA5 | F92: 4032 | G92: 35245 | H92: 2008 | I92: 66741.66 | J92: 5398 | K92: 151255.25 | L92: 1.01 | M92: 3159 | N92: 144753 | O92: 120 | P92: =IFERROR(VLOOKUP(Tabela1[[#This Row],[TAG]],#REF!,14,FALSE),"") | Q92: =P92+P92 -> #VALUE! | R92: =Q92+P92 -> #VALUE! | S92: =R92+P92 -> #VALUE! | T92: =S92+P92 -> #VALUE! | U92: =T92+P92 -> #VALUE! | V92: =U92+P92 -> #VALUE! | W92: 600.88 | X92: 1323.37 | Y92: 0.1 | Z92: =IF(Tabela1[[#This Row],[Ano Aquisição]]=2023,0,IFERROR(VLOOKUP(H92,inflação!$F:$H,3,FALSE),"")) -> 0.8912 | AA92: 0.8 | AB92: =I92*-1 -> -66741.66 | AC92: =-(((P92*$W92)+($X92*12))*((1+$Y92)^AC$1)) -> #VALUE! | AD92: =-((((Q92-P92)*$W92)+($X92*12))*((1+$Y92)^AD$1)) -> #VALUE! | AE92: =-((((R92-Q92)*$W92)+($X92*12))*((1+$Y92)^AE$1)) -> #VALUE! | AF92: =-((((S92-R92)*$W92)+($X92*12))*((1+$Y92)^AF$1)) -> #VALUE! | AG92: =-((((T92-S92)*$W92)+($X92*12))*((1+$Y92)^AG$1)) -> #VALUE! | AH92: =-((((U92-T92)*$W92)+($X92*12))*((1+$Y92)^AH$1)) -> #VALUE! | AI92: =-((((V92-U92)*$W92)+($X92*12))*((1+$Y92)^AI$1)) -> #VALUE! | AJ92: =-(I92*(1+Z92)) -> -126221.83 | AK92: =AC92*(1-$AA92) -> #VALUE! | AL92: =AD92*(1-$AA92) -> #VALUE! | AM92: =AE92*(1-$AA92) -> #VALUE! | AN92: =AF92*(1-$AA92) -> #VALUE! | AO92: =AG92*(1-$AA92) -> #VALUE! | AP92: =AH92*(1-$AA92) -> #VALUE! | AQ92: =AI92*(1-$AA92) -> #VALUE! | AR92: =(NPV(Y92,AK92,AL92,AM92,AN92,AO92,AP92,AQ92)+(SUM(AJ92,(J92*-1))))-(NPV(Y92,AC92,AD92,AE92,AF92,AG92,AH92,AI92)) -> #VALUE! | AS92: =SUM(AC92:AI92) -> #VALUE! | AT92: =SUM(AK92:AQ92) -> #VALUE! | AU92: =(((AVERAGE(AC92:AI92)/1000)-(AVERAGE(AK92:AQ92)/1000))+(((AJ92/1000)*-1)/7)+((J92/1000)/7))*-1 -> #VALUE! | AV92: =AU92/(((J92/1000)+((AJ92*-1)/1000))) -> #VALUE! | AW92: =IF(L92>1.1,"Fase de Degradação",IF(L92<1,"Confiabilidade em Crescimento","Fase de Vida Útil")) -> Fase de Vida Útil | AX92: =VLOOKUP(D92,#REF!,5,FALSE) -> #REF! | AZ92: X | BB92: =IFERROR(VLOOKUP(Tabela1[[#This Row],[Denominação]],[10]Planilha1!$A:$B,2,FALSE),"") -> 151255.25
A93: 92 | B93: CAB124 | C93: CAB124-CABINE DE REGULAGEM | D93: 10006741 | E93: BR01-MOT-MON-LINHA4 | F93: 4024 | G93: 55737 | H93: 2021 | I93: 176429.67 | J93: 159159 | K93: 34694.16 | L93: 0.77 | M93: 4441 | N93: 7481 | O93: 62 | P93: =IFERROR(VLOOKUP(Tabela1[[#This Row],[TAG]],#REF!,14,FALSE),"") | Q93: =P93+P93 -> #VALUE! | R93: =Q93+P93 -> #VALUE! | S93: =R93+P93 -> #VALUE! | T93: =S93+P93 -> #VALUE! | U93: =T93+P93 -> #VALUE! | V93: =U93+P93 -> #VALUE! | W93: 733.28 | X93: 2590.82 | Y93: 0.1 | Z93: =IF(Tabela1[[#This Row],[Ano Aquisição]]=2023,0,IFERROR(VLOOKUP(H93,inflação!$F:$H,3,FALSE),"")) -> 0.1585 | AA93: 0.8 | AB93: =I93*-1 -> -176429.67 | AC93: =-(((P93*$W93)+($X93*12))*((1+$Y93)^AC$1)) -> #VALUE! | AD93: =-((((Q93-P93)*$W93)+($X93*12))*((1+$Y93)^AD$1)) -> #VALUE! | AE93: =-((((R93-Q93)*$W93)+($X93*12))*((1+$Y93)^AE$1)) -> #VALUE! | AF93: =-((((S93-R93)*$W93)+($X93*12))*((1+$Y93)^AF$1)) -> #VALUE! | AG93: =-((((T93-S93)*$W93)+($X93*12))*((1+$Y93)^AG$1)) -> #VALUE! | AH93: =-((((U93-T93)*$W93)+($X93*12))*((1+$Y93)^AH$1)) -> #VALUE! | AI93: =-((((V93-U93)*$W93)+($X93*12))*((1+$Y93)^AI$1)) -> #VALUE! | AJ93: =-(I93*(1+Z93)) -> -204393.77 | AK93: =AC93*(1-$AA93) -> #VALUE! | AL93: =AD93*(1-$AA93) -> #VALUE! | AM93: =AE93*(1-$AA93) -> #VALUE! | AN93: =AF93*(1-$AA93) -> #VALUE! | AO93: =AG93*(1-$AA93) -> #VALUE! | AP93: =AH93*(1-$AA93) -> #VALUE! | AQ93: =AI93*(1-$AA93) -> #VALUE! | AR93: =(NPV(Y93,AK93,AL93,AM93,AN93,AO93,AP93,AQ93)+(SUM(AJ93,(J93*-1))))-(NPV(Y93,AC93,AD93,AE93,AF93,AG93,AH93,AI93)) -> #VALUE! | AS93: =SUM(AC93:AI93) -> #VALUE! | AT93: =SUM(AK93:AQ93) -> #VALUE! | AU93: =(((AVERAGE(AC93:AI93)/1000)-(AVERAGE(AK93:AQ93)/1000))+(((AJ93/1000)*-1)/7)+((J93/1000)/7))*-1 -> #VALUE! | AV93: =AU93/(((J93/1000)+((AJ93*-1)/1000))) -> #VALUE! | AW93: =IF(L93>1.1,"Fase de Degradação",IF(L93<1,"Confiabilidade em Crescimento","Fase de Vida Útil")) -> Confiabilidade em Crescimento | AX93: =VLOOKUP(D93,#REF!,5,FALSE) -> #REF! | AZ93: X | BB93: =IFERROR(VLOOKUP(Tabela1[[#This Row],[Denominação]],[10]Planilha1!$A:$B,2,FALSE),"") -> 34694.16
A94: 93 | B94: CAB125 | C94: CAB125-CABINE DE REGULAGEM | D94: 10006742 | E94: BR01-MOT-MON-LINHA4 | F94: 4024 | G94: 55738 | H94: 2021 | I94: 175448.4 | J94: 158272 | K94: 47726.37 | L94: 0.68 | M94: 4441 | N94: 6030 | O94: 42 | P94: =IFERROR(VLOOKUP(Tabela1[[#This Row],[TAG]],#REF!,14,FALSE),"") | Q94: =P94+P94 -> #VALUE! | R94: =Q94+P94 -> #VALUE! | S94: =R94+P94 -> #VALUE! | T94: =S94+P94 -> #VALUE! | U94: =T94+P94 -> #VALUE! | V94: =U94+P94 -> #VALUE! | W94: 589.84 | X94: 1635.15 | Y94: 0.1 | Z94: =IF(Tabela1[[#This Row],[Ano Aquisição]]=2023,0,IFERROR(VLOOKUP(H94,inflação!$F:$H,3,FALSE),"")) -> 0.1585 | AA94: 0.8 | AB94: =I94*-1 -> -175448.4 | AC94: =-(((P94*$W94)+($X94*12))*((1+$Y94)^AC$1)) -> #VALUE! | AD94: =-((((Q94-P94)*$W94)+($X94*12))*((1+$Y94)^AD$1)) -> #VALUE! | AE94: =-((((R94-Q94)*$W94)+($X94*12))*((1+$Y94)^AE$1)) -> #VALUE! | AF94: =-((((S94-R94)*$W94)+($X94*12))*((1+$Y94)^AF$1)) -> #VALUE! | AG94: =-((((T94-S94)*$W94)+($X94*12))*((1+$Y94)^AG$1)) -> #VALUE! | AH94: =-((((U94-T94)*$W94)+($X94*12))*((1+$Y94)^AH$1)) -> #VALUE! | AI94: =-((((V94-U94)*$W94)+($X94*12))*((1+$Y94)^AI$1)) -> #VALUE! | AJ94: =-(I94*(1+Z94)) -> -203256.97 | AK94: =AC94*(1-$AA94) -> #VALUE! | AL94: =AD94*(1-$AA94) -> #VALUE! | AM94: =AE94*(1-$AA94) -> #VALUE! | AN94: =AF94*(1-$AA94) -> #VALUE! | AO94: =AG94*(1-$AA94) -> #VALUE! | AP94: =AH94*(1-$AA94) -> #VALUE! | AQ94: =AI94*(1-$AA94) -> #VALUE! | AR94: =(NPV(Y94,AK94,AL94,AM94,AN94,AO94,AP94,AQ94)+(SUM(AJ94,(J94*-1))))-(NPV(Y94,AC94,AD94,AE94,AF94,AG94,AH94,AI94)) -> #VALUE! | AS94: =SUM(AC94:AI94) -> #VALUE! | AT94: =SUM(AK94:AQ94) -> #VALUE! | AU94: =(((AVERAGE(AC94:AI94)/1000)-(AVERAGE(AK94:AQ94)/1000))+(((AJ94/1000)*-1)/7)+((J94/1000)/7))*-1 -> #VALUE! | AV94: =AU94/(((J94/1000)+((AJ94*-1)/1000))) -> #VALUE! | AW94: =IF(L94>1.1,"Fase de Degradação",IF(L94<1,"Confiabilidade em Crescimento","Fase de Vida Útil")) -> Confiabilidade em Crescimento | AX94: =VLOOKUP(D94,#REF!,5,FALSE) -> #REF! | AZ94: X | BB94: =IFERROR(VLOOKUP(Tabela1[[#This Row],[Denominação]],[10]Planilha1!$A:$B,2,FALSE),"") -> 47726.37
